Workbook

Sheet 안내(README)
A1: 두위드(Do With) 재무 모델링 연습용 36개월 데이터
A2: 주식회사 두위드 · 정보통신업 · 데이터베이스 및 온라인 정보 제공업 · B2C AI SaaS / 마켓플레이스 / 데이터 플랫폼 · 국내 개인·법인 고객
A3: 기간: 2025-05(설립) ~ 2028-04, 36개월 · 단위: 원 · 회계연도: 1~12월
A5: 데이터 구분(각 시트 4행 색상)
A6: 회색 = 실적배분: 2025-05~12월. 연간 합계는 2025 표준재무제표와 원 단위까지 일치, 월·세부항목 배분은 가정
A7: 하늘색 = 가상(실적 대체): 2026-01~09월. 실제 데이터를 받으면 이 구간부터 교체
A8: 주황색 = 가상(전망): 2026-10~2028-04월
A9: 글자색: 파란색 = 입력값(데이터), 검정 = 산식, 초록 = 다른 시트 연결 산식
A10: 시트 연결: 매출·매출원가·판관비 → 손익계산서 → 현금흐름표(간접법) → 재무상태표 현금. 재무상태표 36행 '검증'이 0이면 3개 재무제표가 맞물린 것입니다.
A12: 2025 표준재무제표 대사(실적 vs 이 파일)
A13: 항목 | B13: 2025 신고 실적 | C13: 이 파일 FY2025 | D13: 차이
A14: 매출액 | B14: 37277876 | C14: ='손익계산서(P&L)'!AP5 -> 37277876 | D14: =C14-B14 -> 0
A15: 매출원가+판관비 | B15: 83568716 | C15: ='손익계산서(P&L)'!AP9+'손익계산서(P&L)'!AP18 -> 83568716 | D15: =C15-B15 -> 0
A16: 영업손실 | B16: -46290840 | C16: ='손익계산서(P&L)'!AP24 -> -46290840 | D16: =C16-B16 -> 0
A17: 영업외수익 | B17: 23703137 | C17: ='손익계산서(P&L)'!AP27 -> 23703137 | D17: =C17-B17 -> 0
A18: 영업외비용 | B18: 438822 | C18: ='손익계산서(P&L)'!AP30 -> 438822 | D18: =C18-B18 -> 0
A19: 당기순손실 | B19: -23026525 | C19: ='손익계산서(P&L)'!AP35 -> -23026525 | D19: =C19-B19 -> 0
A20: 현금및현금성자산(12/31) | B20: 198790542 | C20: ='재무상태표(BS)'!AP7 -> 198790542 | D20: =C20-B20 -> 0
A21: 자산총계 | B21: 199742022 | C21: ='재무상태표(BS)'!AP16 -> 199742022 | D21: =C21-B21 -> 0
A22: 부채총계 | B22: 212768547 | C22: ='재무상태표(BS)'!AP29 -> 212768547 | D22: =C22-B22 -> 0
A23: 자본총계 | B23: -13026525 | C23: ='재무상태표(BS)'!AP34 -> -13026525 | D23: =C23-B23 -> 0

Sheet 매출(Revenue)
A1: 매출(Revenue) 월별 상세 (단위: 원, VAT 별도)
A2: ※ 분해축: 1)사업부문·플랜(a: Pro/Max/크레딧, b, c) → 2)결제주기·상품·셀러유형 → 3)고객유형(개인/법인). 2025-05~12월은 2025 표준손익계산서 매출액(37,277,876원)을 월·항목별로 배분한 값, 2026-01 이후는 연습용 가상 데이터. 연간구독은 결제액을 12개월 안분, 크레딧은 사용 시 인식, 입장권은 행사월 인식.
A3: 표준재무제표_계정과목 | B3: 그룹(Level1) | C3: 중분류(Level2) | D3: 소분류(Level3) | E3: 성격 | F3: 2025-05-31 | G3: 2025-06-30 | H3: 2025-07-31 | I3: 2025-08-31 | J3: 2025-09-30 | K3: 2025-10-31 | L3: 2025-11-30 | M3: 2025-12-31 | N3: 2026-01-31 | O3: 2026-02-28 | P3: 2026-03-31 | Q3: 2026-04-30 | R3: 2026-05-31 | S3: 2026-06-30 | T3: 2026-07-31 | U3: 2026-08-31 | V3: 2026-09-30 | W3: 2026-10-31 | X3: 2026-11-30 | Y3: 2026-12-31 | Z3: 2027-01-31 | AA3: 2027-02-28 | AB3: 2027-03-31 | AC3: 2027-04-30 | AD3: 2027-05-31 | AE3: 2027-06-30 | AF3: 2027-07-31 | AG3: 2027-08-31 | AH3: 2027-09-30 | AI3: 2027-10-31 | AJ3: 2027-11-30 | AK3: 2027-12-31 | AL3: 2028-01-31 | AM3: 2028-02-29 | AN3: 2028-03-31 | AO3: 2028-04-30 | AP3: FY2025(5~12월) | AQ3: FY2026 | AR3: FY2027 | AS3: FY2028(1~4월) | AT3: 참고_표준손익계산서 계정(세무신고 매핑)
A4: ※ 데이터구분 | F4: 실적배분 | G4: 실적배분 | H4: 실적배분 | I4: 실적배분 | J4: 실적배분 | K4: 실적배분 | L4: 실적배분 | M4: 실적배분 | N4: 가상 | O4: 가상 | P4: 가상 | Q4: 가상 | R4: 가상 | S4: 가상 | T4: 가상 | U4: 가상 | V4: 가상 | W4: 가상 | X4: 가상 | Y4: 가상 | Z4: 가상 | AA4: 가상 | AB4: 가상 | AC4: 가상 | AD4: 가상 | AE4: 가상 | AF4: 가상 | AG4: 가상 | AH4: 가상 | AI4: 가상 | AJ4: 가상 | AK4: 가상 | AL4: 가상 | AM4: 가상 | AN4: 가상 | AO4: 가상 | AP4: 연간 집계 | AQ4: 연간 집계 | AR4: 연간 집계 | AS4: 연간 집계
A5: 매출액 | B5: [a] AI 취업준비 SaaS - Pro 플랜 | C5: 월간 구독 | D5: 개인 | E5: 반복 | F5: 0 | G5: 0 | H5: 0 | I5: 0 | J5: 810000 | K5: 1404000 | L5: 1782000 | M5: 2016000 | N5: 2430000 | O5: 3006000 | P5: 3852000 | Q5: 4500000 | R5: 4842000 | S5: 5094000 | T5: 5526000 | U5: 6426000 | V5: 7812000 | W5: 8694000 | X5: 9108000 | Y5: 9216000 | Z5: 10026000 | AA5: 11250000 | AB5: 13086000 | AC5: 14328000 | AD5: 14778000 | AE5: 14994000 | AF5: 15498000 | AG5: 16812000 | AH5: 18864000 | AI5: 19962000 | AJ5: 20160000 | AK5: 19818000 | AL5: 20196000 | AM5: 21186000 | AN5: 23112000 | AO5: 24228000 | AP5: =SUM(F5:M5) -> 6012000 | AQ5: =SUM(N5:Y5) -> 70506000 | AR5: =SUM(Z5:AK5) -> 189576000 | AS5: =SUM(AL5:AO5) -> 88722000 | AT5: 매출액 (2025 신고: 국내상품매출)
A6: 매출액 | B6: [a] AI 취업준비 SaaS - Pro 플랜 | C6: 월간 구독 | D6: 법인 | E6: 반복 | F6: 0 | G6: 0 | H6: 0 | I6: 0 | J6: 0 | K6: 0 | L6: 0 | M6: 0 | N6: 0 | O6: 0 | P6: 0 | Q6: 0 | R6: 160000 | S6: 208000 | T6: 256000 | U6: 304000 | V6: 352000 | W6: 400000 | X6: 448000 | Y6: 496000 | Z6: 544000 | AA6: 592000 | AB6: 640000 | AC6: 688000 | AD6: 736000 | AE6: 784000 | AF6: 832000 | AG6: 880000 | AH6: 928000 | AI6: 960000 | AJ6: 960000 | AK6: 960000 | AL6: 960000 | AM6: 960000 | AN6: 960000 | AO6: 960000 | AP6: =SUM(F6:M6) -> 0 | AQ6: =SUM(N6:Y6) -> 2624000 | AR6: =SUM(Z6:AK6) -> 9504000 | AS6: =SUM(AL6:AO6) -> 3840000 | AT6: 매출액 (2025 신고: 국내상품매출)
A7: 매출액 | B7: [a] AI 취업준비 SaaS - Pro 플랜 | C7: 연간 구독 | D7: 개인 | E7: 반복(연간 선결제 → 12개월 안분 인식) | F7: 0 | G7: 0 | H7: 0 | I7: 0 | J7: 0 | K7: 0 | L7: 0 | M7: 0 | N7: 75000 | O7: 165000 | P7: 285000 | Q7: 405000 | R7: 495000 | S7: 600000 | T7: 705000 | U7: 885000 | V7: 1110000 | W7: 1305000 | X7: 1470000 | Y7: 1605000 | Z7: 1755000 | AA7: 1950000 | AB7: 2205000 | AC7: 2415000 | AD7: 2580000 | AE7: 2730000 | AF7: 2895000 | AG7: 3120000 | AH7: 3405000 | AI7: 3630000 | AJ7: 3795000 | AK7: 3930000 | AL7: 4080000 | AM7: 4275000 | AN7: 4515000 | AO7: 4710000 | AP7: =SUM(F7:M7) -> 0 | AQ7: =SUM(N7:Y7) -> 9105000 | AR7: =SUM(Z7:AK7) -> 34410000 | AS7: =SUM(AL7:AO7) -> 17580000 | AT7: 매출액 (2025 신고: 국내상품매출)
A8: 매출액 | B8: [a] AI 취업준비 SaaS - Pro 플랜 | C8: 연간 구독 | D8: 법인 | E8: 반복(연간 선결제 → 12개월 안분 인식) | F8: 0 | G8: 0 | H8: 0 | I8: 0 | J8: 0 | K8: 0 | L8: 0 | M8: 0 | N8: 0 | O8: 0 | P8: 1250000 | Q8: 1250000 | R8: 1250000 | S8: 1250000 | T8: 1250000 | U8: 1250000 | V8: 2250000 | W8: 2250000 | X8: 2250000 | Y8: 2250000 | Z8: 2250000 | AA8: 2250000 | AB8: 4500000 | AC8: 4500000 | AD8: 4500000 | AE8: 4500000 | AF8: 4500000 | AG8: 4500000 | AH8: 6175000 | AI8: 6175000 | AJ8: 6175000 | AK8: 6175000 | AL8: 6175000 | AM8: 6175000 | AN8: 5475000 | AO8: 5475000 | AP8: =SUM(F8:M8) -> 0 | AQ8: =SUM(N8:Y8) -> 16500000 | AR8: =SUM(Z8:AK8) -> 56200000 | AS8: =SUM(AL8:AO8) -> 23300000 | AT8: 매출액 (2025 신고: 국내상품매출)
A9: 매출액 | B9: [a] AI 취업준비 SaaS - Max 플랜 | C9: 월간 구독 | D9: 개인 | E9: 반복 | F9: 0 | G9: 0 | H9: 0 | I9: 0 | J9: 0 | K9: 432000 | L9: 720000 | M9: 936000 | N9: 1260000 | O9: 1656000 | P9: 2232000 | Q9: 2700000 | R9: 2988000 | S9: 3204000 | T9: 3564000 | U9: 4176000 | V9: 5076000 | W9: 5724000 | X9: 6048000 | Y9: 6228000 | Z9: 6768000 | AA9: 7524000 | AB9: 8676000 | AC9: 9504000 | AD9: 9864000 | AE9: 10080000 | AF9: 10440000 | AG9: 11304000 | AH9: 12600000 | AI9: 13356000 | AJ9: 13572000 | AK9: 13464000 | AL9: 13788000 | AM9: 14472000 | AN9: 15696000 | AO9: 16452000 | AP9: =SUM(F9:M9) -> 2088000 | AQ9: =SUM(N9:Y9) -> 44856000 | AR9: =SUM(Z9:AK9) -> 127152000 | AS9: =SUM(AL9:AO9) -> 60408000 | AT9: 매출액 (2025 신고: 국내상품매출)
A10: 매출액 | B10: [a] AI 취업준비 SaaS - Max 플랜 | C10: 월간 구독 | D10: 법인 | E10: 반복 | F10: 0 | G10: 0 | H10: 0 | I10: 0 | J10: 0 | K10: 0 | L10: 0 | M10: 0 | N10: 0 | O10: 0 | P10: 0 | Q10: 0 | R10: 0 | S10: 0 | T10: 0 | U10: 160000 | V10: 192000 | W10: 224000 | X10: 256000 | Y10: 288000 | Z10: 320000 | AA10: 352000 | AB10: 384000 | AC10: 416000 | AD10: 448000 | AE10: 480000 | AF10: 512000 | AG10: 544000 | AH10: 576000 | AI10: 608000 | AJ10: 640000 | AK10: 640000 | AL10: 640000 | AM10: 640000 | AN10: 640000 | AO10: 640000 | AP10: =SUM(F10:M10) -> 0 | AQ10: =SUM(N10:Y10) -> 1120000 | AR10: =SUM(Z10:AK10) -> 5920000 | AS10: =SUM(AL10:AO10) -> 2560000 | AT10: 매출액 (2025 신고: 국내상품매출)
A11: 매출액 | B11: [a] AI 취업준비 SaaS - Max 플랜 | C11: 연간 구독 | D11: 개인 | E11: 반복(연간 선결제 → 12개월 안분 인식) | F11: 0 | G11: 0 | H11: 0 | I11: 0 | J11: 0 | K11: 0 | L11: 0 | M11: 0 | N11: 60000 | O11: 150000 | P11: 300000 | Q11: 420000 | R11: 510000 | S11: 600000 | T11: 720000 | U11: 870000 | V11: 1110000 | W11: 1290000 | X11: 1470000 | Y11: 1590000 | Z11: 1770000 | AA11: 1950000 | AB11: 2190000 | AC11: 2430000 | AD11: 2580000 | AE11: 2730000 | AF11: 2910000 | AG11: 3120000 | AH11: 3390000 | AI11: 3630000 | AJ11: 3810000 | AK11: 3930000 | AL11: 4080000 | AM11: 4260000 | AN11: 4500000 | AO11: 4710000 | AP11: =SUM(F11:M11) -> 0 | AQ11: =SUM(N11:Y11) -> 9090000 | AR11: =SUM(Z11:AK11) -> 34440000 | AS11: =SUM(AL11:AO11) -> 17550000 | AT11: 매출액 (2025 신고: 국내상품매출)
A12: 매출액 | B12: [a] AI 취업준비 SaaS - Max 플랜 | C12: 연간 구독 | D12: 법인 | E12: 반복(연간 선결제 → 12개월 안분 인식) | F12: 0 | G12: 0 | H12: 0 | I12: 0 | J12: 0 | K12: 0 | L12: 0 | M12: 0 | N12: 0 | O12: 0 | P12: 0 | Q12: 0 | R12: 0 | S12: 0 | T12: 0 | U12: 0 | V12: 0 | W12: 0 | X12: 0 | Y12: 0 | Z12: 0 | AA12: 0 | AB12: 1000000 | AC12: 1000000 | AD12: 1000000 | AE12: 1000000 | AF12: 1000000 | AG12: 1000000 | AH12: 1000000 | AI12: 1000000 | AJ12: 1000000 | AK12: 1000000 | AL12: 1000000 | AM12: 1000000 | AN12: 800000 | AO12: 800000 | AP12: =SUM(F12:M12) -> 0 | AQ12: =SUM(N12:Y12) -> 0 | AR12: =SUM(Z12:AK12) -> 10000000 | AS12: =SUM(AL12:AO12) -> 3600000 | AT12: 매출액 (2025 신고: 국내상품매출)
A13: 매출액 | B13: [a] AI 취업준비 SaaS - 크레딧 | C13: 1회 구매(크레딧 충전) | D13: 개인 | E13: 일시(크레딧 사용 시 인식) | F13: 0 | G13: 0 | H13: 0 | I13: 0 | J13: 0 | K13: 0 | L13: 0 | M13: 0 | N13: 0 | O13: 752136 | P13: 1571592 | Q13: 1802592 | R13: 1576646 | S13: 1416586 | T13: 1617151 | U13: 2380186 | V13: 3635054 | W13: 3752722 | X13: 3088121 | Y13: 2442981 | Z13: 2896344 | AA13: 3978933 | AB13: 5766552 | AC13: 6109488 | AD13: 5050358 | AE13: 4336049 | AF13: 4684680 | AG13: 6415766 | AH13: 9042830 | AI13: 8830574 | AJ13: 6965753 | AK13: 5325219 | AL13: 5950296 | AM13: 7675347 | AN13: 10434072 | AO13: 10574784 | AP13: =SUM(F13:M13) -> 0 | AQ13: =SUM(N13:Y13) -> 24035767 | AR13: =SUM(Z13:AK13) -> 69402546 | AS13: =SUM(AL13:AO13) -> 34634499 | AT13: 매출액 (2025 신고: 국내상품매출)
A14: 매출액 | B14: [a] AI 취업준비 SaaS - 크레딧 | C14: 1회 구매(크레딧 충전) | D14: 법인 | E14: 일시(크레딧 사용 시 인식) | F14: 0 | G14: 0 | H14: 0 | I14: 0 | J14: 0 | K14: 0 | L14: 0 | M14: 0 | N14: 0 | O14: 0 | P14: 0 | Q14: 0 | R14: 0 | S14: 666667 | T14: 666667 | U14: 666667 | V14: 833333 | W14: 833333 | X14: 833333 | Y14: 1000000 | Z14: 1000000 | AA14: 1000000 | AB14: 1166667 | AC14: 1166667 | AD14: 1166667 | AE14: 1333333 | AF14: 1333333 | AG14: 1333333 | AH14: 1500000 | AI14: 1500000 | AJ14: 1500000 | AK14: 1666667 | AL14: 1666667 | AM14: 1666667 | AN14: 1833333 | AO14: 1833333 | AP14: =SUM(F14:M14) -> 0 | AQ14: =SUM(N14:Y14) -> 5500000 | AR14: =SUM(Z14:AK14) -> 15666667 | AS14: =SUM(AL14:AO14) -> 7000000 | AT14: 매출액 (2025 신고: 국내상품매출)
A15: 매출액 | B15: [b] 전자책 판매 중개수수료 | C15: 국내 | D15: 개인셀러 | E15: 판매발생시 발생 | F15: 0 | G15: 0 | H15: 0 | I15: 0 | J15: 0 | K15: 0 | L15: 0 | M15: 0 | N15: 0 | O15: 0 | P15: 504000 | Q15: 479002 | R15: 398297 | S15: 392481 | T15: 489427 | U15: 723265 | V15: 1001912 | W15: 888163 | X15: 738035 | Y15: 635922 | Z15: 849061 | AA15: 1077522 | AB15: 1423781 | AC15: 1266842 | AD15: 986171 | AE15: 909723 | AF15: 1061968 | AG15: 1469056 | AH15: 1904906 | AI15: 1580607 | AJ15: 1229361 | AK15: 991429 | AL15: 1296315 | AM15: 1610995 | AN15: 2084441 | AO15: 1816050 | AP15: =SUM(F15:M15) -> 0 | AQ15: =SUM(N15:Y15) -> 6250504 | AR15: =SUM(Z15:AK15) -> 14750427 | AS15: =SUM(AL15:AO15) -> 6807801 | AT15: 매출액 (2025 신고: 국내상품매출)
A16: 매출액 | B16: [b] 전자책 판매 중개수수료 | C16: 국내 | D16: 사업자셀러 | E16: 판매발생시 발생 | F16: 0 | G16: 0 | H16: 0 | I16: 0 | J16: 0 | K16: 0 | L16: 0 | M16: 0 | N16: 0 | O16: 0 | P16: 336000 | Q16: 327398 | R16: 279079 | S16: 281885 | T16: 360273 | U16: 545621 | V16: 774528 | W16: 703527 | X16: 598985 | Y16: 528771 | Z16: 723274 | AA16: 940309 | AB16: 1272774 | AC16: 1160058 | AD16: 925013 | AE16: 874048 | AF16: 1045112 | AG16: 1480856 | AH16: 1966854 | AI16: 1671671 | AJ16: 1331808 | AK16: 1100193 | AL16: 1473589 | AM16: 1876007 | AN16: 2486701 | AO16: 2219616 | AP16: =SUM(F16:M16) -> 0 | AQ16: =SUM(N16:Y16) -> 4736067 | AR16: =SUM(Z16:AK16) -> 14491970 | AS16: =SUM(AL16:AO16) -> 8055913 | AT16: 매출액 (2025 신고: 국내상품매출)
... A22: 매출액 | B22: [c] 컨퍼런스 입장권 | C22: 단체·기업 티켓 | D22: 법인 | E22: 일시(행사일 인식) | F22: 0 | G22: 0 | H22: 0 | I22: 0 | J22: 0 | K22: 0 | L22: 0 | M22: 0 | N22: 0 | O22: 0 | P22: 0 | Q22: 2000000 | R22: 0 | S22: 0 | T22: 0 | U22: 0 | V22: 0 | W22: 3000000 | X22: 0 | Y22: 0 | Z22: 0 | AA22: 0 | AB22: 0 | AC22: 4500000 | AD22: 0 | AE22: 0 | AF22: 0 | AG22: 0 | AH22: 0 | AI22: 6000000 | AJ22: 0 | AK22: 0 | AL22: 0 | AM22: 0 | AN22: 0 | AO22: 7000000 | AP22: =SUM(F22:M22) -> 0 | AQ22: =SUM(N22:Y22) -> 5000000 | AR22: =SUM(Z22:AK22) -> 10500000 | AS22: =SUM(AL22:AO22) -> 7000000 | AT22: 매출액 (2025 신고: 국내상품매출)
A24: 소계: [a] AI 취업준비 SaaS | F24: =SUM(F5:F14) -> 0 | G24: =SUM(G5:G14) -> 0 | H24: =SUM(H5:H14) -> 0 | I24: =SUM(I5:I14) -> 0 | J24: =SUM(J5:J14) -> 810000 | K24: =SUM(K5:K14) -> 1836000 | L24: =SUM(L5:L14) -> 2502000 | M24: =SUM(M5:M14) -> 2952000 | ... AS24: =SUM(AS5:AS14) -> 259194499
A25: 소계: [b] 전자책·강의 중개수수료 | F25: =SUM(F15:F18) -> 0 | G25: =SUM(G15:G18) -> 0 | H25: =SUM(H15:H18) -> 0 | I25: =SUM(I15:I18) -> 0 | J25: =SUM(J15:J18) -> 0 | K25: =SUM(K15:K18) -> 0 | L25: =SUM(L15:L18) -> 0 | M25: =SUM(M15:M18) -> 0 | ... AS25: =SUM(AS15:AS18) -> 28176459
A26: 소계: [c] 자체 콘텐츠·컨퍼런스 | F26: =SUM(F19:F22) -> 1500000 | G26: =SUM(G19:G22) -> 2600000 | H26: =SUM(H19:H22) -> 3200000 | I26: =SUM(I19:I22) -> 3600000 | J26: =SUM(J19:J22) -> 4200000 | K26: =SUM(K19:K22) -> 3900000 | L26: =SUM(L19:L22) -> 6700000 | M26: =SUM(M19:M22) -> 3477876 | ... AS26: =SUM(AS19:AS22) -> 53140931
A27: 합계: 매출(Revenue) | F27: =SUM(F5:F22) -> 1500000 | G27: =SUM(G5:G22) -> 2600000 | H27: =SUM(H5:H22) -> 3200000 | I27: =SUM(I5:I22) -> 3600000 | J27: =SUM(J5:J22) -> 5010000 | K27: =SUM(K5:K22) -> 5736000 | L27: =SUM(L5:L22) -> 9202000 | M27: =SUM(M5:M22) -> 6429876 | ... AS27: =SUM(AS5:AS22) -> 340511889

Sheet 매출원가(COGS)
A1: 매출원가(COGS) 월별 상세 (단위: 원)
A2: ※ 2025년은 신고서상 매출원가 0원·지급수수료 50,385,211원으로 처리된 금액 중 클라우드·LLM·PG·행사비를 매출원가로 재분류한 값. 마켓플레이스는 순액(수수료) 매출 인식을 가정해 '제3자 판매자 정산대금'은 0원, 정산대금은 재무상태표 '셀러 정산 예수금'으로 관리.
A3: 표준재무제표_계정과목 | B3: 그룹(Level1) | C3: 중분류(Level2) | D3: 소분류(Level3) | E3: 성격 | F3: 2025-05-31 | G3: 2025-06-30 | H3: 2025-07-31 | I3: 2025-08-31 | J3: 2025-09-30 | K3: 2025-10-31 | L3: 2025-11-30 | M3: 2025-12-31 | N3: 2026-01-31 | O3: 2026-02-28 | P3: 2026-03-31 | Q3: 2026-04-30 | R3: 2026-05-31 | S3: 2026-06-30 | T3: 2026-07-31 | U3: 2026-08-31 | V3: 2026-09-30 | W3: 2026-10-31 | X3: 2026-11-30 | Y3: 2026-12-31 | Z3: 2027-01-31 | AA3: 2027-02-28 | AB3: 2027-03-31 | AC3: 2027-04-30 | AD3: 2027-05-31 | AE3: 2027-06-30 | AF3: 2027-07-31 | AG3: 2027-08-31 | AH3: 2027-09-30 | AI3: 2027-10-31 | AJ3: 2027-11-30 | AK3: 2027-12-31 | AL3: 2028-01-31 | AM3: 2028-02-29 | AN3: 2028-03-31 | AO3: 2028-04-30 | AP3: FY2025(5~12월) | AQ3: FY2026 | AR3: FY2027 | AS3: FY2028(1~4월) | AT3: 참고_표준손익계산서 계정(세무신고 매핑)
A4: ※ 데이터구분 | F4: 실적배분 | G4: 실적배분 | H4: 실적배분 | I4: 실적배분 | J4: 실적배분 | K4: 실적배분 | L4: 실적배분 | M4: 실적배분 | N4: 가상 | O4: 가상 | P4: 가상 | Q4: 가상 | R4: 가상 | S4: 가상 | T4: 가상 | U4: 가상 | V4: 가상 | W4: 가상 | X4: 가상 | Y4: 가상 | Z4: 가상 | AA4: 가상 | AB4: 가상 | AC4: 가상 | AD4: 가상 | AE4: 가상 | AF4: 가상 | AG4: 가상 | AH4: 가상 | AI4: 가상 | AJ4: 가상 | AK4: 가상 | AL4: 가상 | AM4: 가상 | AN4: 가상 | AO4: 가상 | AP4: 연간 집계 | AQ4: 연간 집계 | AR4: 연간 집계 | AS4: 연간 집계
A5: 매출원가 | B5: 인프라비용 | C5: 클라우드 인프라(AWS·Vercel) | D5: [a] AI 취업준비 SaaS (리소스 태그·프로젝트 기준) | E5: 변동 | F5: 0 | G5: 0 | H5: 0 | I5: 0 | J5: 378350 | K5: 414260 | L5: 437570 | M5: 453320 | N5: 483875 | O5: 550520 | P5: 682171 | Q5: 737716 | R5: 763758 | S5: 806374 | T5: 850669 | U5: 949125 | V5: 1132964 | W5: 1206557 | X5: 1224001 | Y5: 1229059 | Z5: 1306527 | AA5: 1429643 | AB5: 1736498 | AC5: 1839500 | AD5: 1844606 | AE5: 1853858 | AF5: 1911175 | AG5: 2066018 | AH5: 2361829 | AI5: 2437805 | AJ5: 2400221 | AK5: 2341811 | AL5: 2398759 | AM5: 2530850 | AN5: 2728789 | AO5: 2813409 | AP5: =SUM(F5:M5) -> 1683500 | AQ5: =SUM(N5:Y5) -> 10616789 | AR5: =SUM(Z5:AK5) -> 23529491 | AS5: =SUM(AL5:AO5) -> 10471807 | AT5: 매출원가 > 지급수수료
A6: 매출원가 | B6: AI비용 | C6: LLM 토큰비용(OpenAI GPT·Anthropic Claude API) | D6: [a] AI 취업준비 SaaS 직접대응 | E6: 변동 | F6: 0 | G6: 0 | H6: 0 | I6: 0 | J6: 173250 | K6: 396900 | L6: 542150 | M6: 640500 | N6: 836850 | O6: 1359098 | P6: 2024338 | Q6: 2384341 | R6: 2496609 | S6: 2808264 | T6: 3093539 | U6: 3749526 | V6: 4564281 | W6: 4980457 | X6: 5003930 | Y6: 4978705 | Z6: 5452304 | AA6: 6244731 | AB6: 7324818 | AC6: 7885638 | AD6: 7802592 | AE6: 7794287 | AF6: 8123326 | AG6: 9090428 | AH6: 9995987 | AI6: 10338865 | AJ6: 9988936 | AK6: 9580272 | AL6: 9917514 | AM6: 10715549 | AN6: 11163949 | AO6: 11555899 | AP6: =SUM(F6:M6) -> 1752800 | AQ6: =SUM(N6:Y6) -> 38279938 | AR6: =SUM(Z6:AK6) -> 99622184 | AS6: =SUM(AL6:AO6) -> 43352911 | AT6: 매출원가 > 지급수수료
A7: 매출원가 | B7: 결제비용 | C7: PG 카드결제 수수료 | D7: [a] AI 취업준비 SaaS 직접대응 | E7: 변동 | F7: 0 | G7: 0 | H7: 0 | I7: 0 | J7: 26730 | K7: 60588 | L7: 82566 | M7: 97416 | N7: 176103 | O7: 261688 | P7: 360082 | Q7: 391157 | R7: 383811 | S7: 394044 | T7: 447658 | U7: 570264 | V7: 739409 | W7: 752764 | X7: 723089 | Y7: 693448 | Z7: 835981 | AA7: 987290 | AB7: 1226190 | AC7: 1249068 | AD7: 1173045 | AE7: 1157054 | AF7: 1240845 | AG7: 1471307 | AH7: 1768486 | AI7: 1712606 | AJ7: 1586327 | AK7: 1472994 | AL7: 1630609 | AM7: 1820783 | AN7: 2142779 | AO7: 2107460 | AP7: =SUM(F7:M7) -> 267300 | AQ7: =SUM(N7:Y7) -> 5893517 | AR7: =SUM(Z7:AK7) -> 15881193 | AS7: =SUM(AL7:AO7) -> 7701631 | AT7: 매출원가 > 지급수수료
A8: 매출원가 | B8: 인프라비용 | C8: 클라우드 인프라(AWS·Vercel) | D8: [b] 콘텐츠 중개 (리소스 태그·프로젝트 기준) | E8: 변동 | F8: 0 | G8: 0 | H8: 0 | I8: 0 | J8: 0 | K8: 0 | L8: 0 | M8: 0 | N8: 0 | O8: 0 | P8: 175200 | Q8: 174192 | R8: 181121 | S8: 181271 | T8: 189774 | U8: 209967 | V8: 234775 | W8: 226714 | X8: 215092 | Y8: 207285 | Z8: 227622 | AA8: 249987 | AB8: 284121 | AC8: 271165 | AD8: 245780 | AE8: 239737 | AF8: 256409 | AG8: 299549 | AH8: 347046 | AI8: 316165 | AJ8: 281370 | AK8: 257709 | AL8: 292638 | AM8: 329566 | AN8: 385394 | AO8: 357819 | AP8: =SUM(F8:M8) -> 0 | AQ8: =SUM(N8:Y8) -> 1995391 | AR8: =SUM(Z8:AK8) -> 3276660 | AS8: =SUM(AL8:AO8) -> 1365417 | AT8: 매출원가 > 지급수수료
A9: 매출원가 | B9: 결제비용 | C9: PG 카드결제 수수료 | D9: [b] 콘텐츠 중개 (거래액 기준) | E9: 변동 | F9: 0 | G9: 0 | H9: 0 | I9: 0 | J9: 0 | K9: 0 | L9: 0 | M9: 0 | N9: 0 | O9: 0 | P9: 126000 | Q9: 120960 | R9: 155606 | S9: 156355 | T9: 198870 | U9: 299836 | V9: 423877 | W9: 383571 | X9: 325458 | Y9: 286425 | Z9: 388110 | AA9: 499935 | AB9: 670606 | AC9: 605826 | AD9: 478902 | AE9: 448684 | AF9: 532045 | AG9: 747743 | AH9: 985228 | AI9: 830827 | AJ9: 656849 | AK9: 538547 | AL9: 713191 | AM9: 897828 | AN9: 1176971 | AO9: 1039097 | AP9: =SUM(F9:M9) -> 0 | AQ9: =SUM(N9:Y9) -> 2476958 | AR9: =SUM(Z9:AK9) -> 7383302 | AS9: =SUM(AL9:AO9) -> 3827087 | AT9: 매출원가 > 지급수수료
A10: 매출원가 | B10: 판매자정산 | C10: 제3자 판매자 정산대금(총액 매출 인식 시에만 사용) | D10: [b] 콘텐츠 중개 직접대응 | E10: 변동 | F10: 0 | G10: 0 | H10: 0 | I10: 0 | J10: 0 | K10: 0 | L10: 0 | M10: 0 | N10: 0 | O10: 0 | P10: 0 | Q10: 0 | R10: 0 | S10: 0 | T10: 0 | U10: 0 | V10: 0 | W10: 0 | X10: 0 | Y10: 0 | Z10: 0 | AA10: 0 | AB10: 0 | AC10: 0 | AD10: 0 | AE10: 0 | AF10: 0 | AG10: 0 | AH10: 0 | AI10: 0 | AJ10: 0 | AK10: 0 | AL10: 0 | AM10: 0 | AN10: 0 | AO10: 0 | AP10: =SUM(F10:M10) -> 0 | AQ10: =SUM(N10:Y10) -> 0 | AR10: =SUM(Z10:AK10) -> 0 | AS10: =SUM(AL10:AO10) -> 0 | AT10: 매출원가 > 상품매출원가 (순액 인식 시 손익 외 처리)
A11: 매출원가 | B11: 운영원가 | C11: 셀러 온보딩·창구 운영비 | D11: [b] 콘텐츠 중개 직접대응 | E11: 고정 | F11: 0 | G11: 0 | H11: 0 | I11: 0 | J11: 0 | K11: 0 | L11: 0 | M11: 0 | N11: 0 | O11: 600000 | P11: 900000 | Q11: 900000 | R11: 900000 | S11: 900000 | T11: 900000 | U11: 900000 | V11: 900000 | W11: 900000 | X11: 900000 | Y11: 900000 | Z11: 1300000 | AA11: 1300000 | AB11: 1300000 | AC11: 1300000 | AD11: 1300000 | AE11: 1300000 | AF11: 1300000 | AG11: 1300000 | AH11: 1300000 | AI11: 1300000 | AJ11: 1300000 | AK11: 1300000 | AL11: 1500000 | AM11: 1500000 | AN11: 1500000 | AO11: 1500000 | AP11: =SUM(F11:M11) -> 0 | AQ11: =SUM(N11:Y11) -> 9600000 | AR11: =SUM(Z11:AK11) -> 15600000 | AS11: =SUM(AL11:AO11) -> 6000000 | AT11: 매출원가 > 지급수수료
A12: 매출원가 | B12: 운영원가 | C12: CS 소프트웨어 구독료 | D12: [b] 콘텐츠 중개 직접대응 | E12: 고정 | F12: 0 | G12: 0 | H12: 0 | I12: 0 | J12: 0 | K12: 0 | L12: 0 | M12: 0 | N12: 0 | O12: 0 | P12: 110000 | Q12: 110000 | R12: 110000 | S12: 110000 | T12: 110000 | U12: 110000 | V12: 110000 | W12: 110000 | X12: 110000 | Y12: 110000 | Z12: 165000 | AA12: 165000 | AB12: 165000 | AC12: 165000 | AD12: 165000 | AE12: 165000 | AF12: 165000 | AG12: 165000 | AH12: 165000 | AI12: 165000 | AJ12: 165000 | AK12: 165000 | AL12: 165000 | AM12: 165000 | AN12: 165000 | AO12: 165000 | AP12: =SUM(F12:M12) -> 0 | AQ12: =SUM(N12:Y12) -> 1100000 | AR12: =SUM(Z12:AK12) -> 1980000 | AS12: =SUM(AL12:AO12) -> 660000 | AT12: 매출원가 > 지급수수료
A13: 매출원가 | B13: 운영원가 | C13: 기타 마켓플레이스 운영비 | D13: [b] 콘텐츠 중개 직접대응 | E13: 변동 | F13: 0 | G13: 0 | H13: 0 | I13: 0 | J13: 0 | K13: 0 | L13: 0 | M13: 0 | N13: 0 | O13: 0 | P13: 133600 | Q13: 132256 | R13: 141495 | S13: 141695 | T13: 153032 | U13: 179956 | V13: 213034 | W13: 202286 | X13: 186789 | Y13: 176380 | Z13: 203496 | AA13: 233316 | AB13: 278828 | AC13: 261554 | AD13: 227707 | AE13: 219649 | AF13: 241879 | AG13: 299398 | AH13: 362728 | AI13: 321554 | AJ13: 275160 | AK13: 243613 | AL13: 290184 | AM13: 339421 | AN13: 413859 | AO13: 377093 | AP13: =SUM(F13:M13) -> 0 | AQ13: =SUM(N13:Y13) -> 1660523 | AR13: =SUM(Z13:AK13) -> 3168882 | AS13: =SUM(AL13:AO13) -> 1420557 | AT13: 매출원가 > 지급수수료
A14: 매출원가 | B14: 행사원가 | C14: 장소 대관료 | D14: [c] 컨퍼런스 직접대응 | E14: 변동 | F14: 0 | G14: 0 | H14: 0 | I14: 0 | J14: 0 | K14: 0 | L14: 1800000 | M14: 0 | N14: 0 | O14: 0 | P14: 0 | Q14: 2500000 | R14: 0 | S14: 0 | T14: 0 | U14: 0 | V14: 0 | W14: 3000000 | X14: 0 | Y14: 0 | Z14: 0 | AA14: 0 | AB14: 0 | AC14: 3500000 | AD14: 0 | AE14: 0 | AF14: 0 | AG14: 0 | AH14: 0 | AI14: 4000000 | AJ14: 0 | AK14: 0 | AL14: 0 | AM14: 0 | AN14: 0 | AO14: 4500000 | AP14: =SUM(F14:M14) -> 1800000 | AQ14: =SUM(N14:Y14) -> 5500000 | AR14: =SUM(Z14:AK14) -> 7500000 | AS14: =SUM(AL14:AO14) -> 4500000 | AT14: 매출원가 > 임차료
A15: 매출원가 | B15: 행사원가 | C15: 행사 장치·시설비(무대·음향·영상) | D15: [c] 컨퍼런스 직접대응 | E15: 변동 | F15: 0 | G15: 0 | H15: 0 | I15: 0 | J15: 0 | K15: 0 | L15: 1200000 | M15: 0 | N15: 0 | O15: 0 | P15: 0 | Q15: 2000000 | R15: 0 | S15: 0 | T15: 0 | U15: 0 | V15: 0 | W15: 2500000 | X15: 0 | Y15: 0 | Z15: 0 | AA15: 0 | AB15: 0 | AC15: 3000000 | AD15: 0 | AE15: 0 | AF15: 0 | AG15: 0 | AH15: 0 | AI15: 3500000 | AJ15: 0 | AK15: 0 | AL15: 0 | AM15: 0 | AN15: 0 | AO15: 4000000 | AP15: =SUM(F15:M15) -> 1200000 | AQ15: =SUM(N15:Y15) -> 4500000 | AR15: =SUM(Z15:AK15) -> 6500000 | AS15: =SUM(AL15:AO15) -> 4000000 | AT15: 매출원가 > 외주용역비
A16: 매출원가 | B16: 결제비용 | C16: PG 카드결제 수수료 | D16: [c] 자체 콘텐츠·컨퍼런스 (콘텐츠·입장권 결제액 기준) | E16: 변동 | F16: 49500 | G16: 85800 | H16: 105600 | I16: 118800 | J16: 138600 | K16: 172260 | L16: 177540 | M16: 114770 | N16: 98010 | O16: 120988 | P16: 238024 | Q16: 258390 | R16: 101990 | S16: 91564 | T16: 104040 | U16: 140107 | V16: 301625 | W16: 330033 | X16: 108264 | Y16: 85047 | Z16: 110440 | AA16: 136332 | AB16: 353449 | AC16: 419015 | AD16: 114924 | AE16: 103177 | AF16: 117234 | AG16: 157876 | AH16: 417118 | AI16: 487749 | AJ16: 121995 | AK16: 95834 | AL16: 124447 | AM16: 153623 | AN16: 472035 | AO16: 582797 | AP16: =SUM(F16:M16) -> 962870 | AQ16: =SUM(N16:Y16) -> 1978082 | AR16: =SUM(Z16:AK16) -> 2635143 | AS16: =SUM(AL16:AO16) -> 1332902 | AT16: 매출원가 > 지급수수료
A18: 소계: [a] AI 취업준비 SaaS | F18: =SUM(F5:F7) -> 0 | G18: =SUM(G5:G7) -> 0 | H18: =SUM(H5:H7) -> 0 | I18: =SUM(I5:I7) -> 0 | J18: =SUM(J5:J7) -> 578330 | K18: =SUM(K5:K7) -> 871748 | L18: =SUM(L5:L7) -> 1062286 | M18: =SUM(M5:M7) -> 1191236 | ... AS18: =SUM(AS5:AS7) -> 61526349
A19: 소계: [b] 콘텐츠 중개 | F19: =SUM(F8:F13) -> 0 | G19: =SUM(G8:G13) -> 0 | H19: =SUM(H8:H13) -> 0 | I19: =SUM(I8:I13) -> 0 | J19: =SUM(J8:J13) -> 0 | K19: =SUM(K8:K13) -> 0 | L19: =SUM(L8:L13) -> 0 | M19: =SUM(M8:M13) -> 0 | ... AS19: =SUM(AS8:AS13) -> 13273061
A20: 소계: [c] 자체 콘텐츠·컨퍼런스 | F20: =SUM(F14:F16) -> 49500 | G20: =SUM(G14:G16) -> 85800 | H20: =SUM(H14:H16) -> 105600 | I20: =SUM(I14:I16) -> 118800 | J20: =SUM(J14:J16) -> 138600 | K20: =SUM(K14:K16) -> 172260 | L20: =SUM(L14:L16) -> 3177540 | M20: =SUM(M14:M16) -> 114770 | ... AS20: =SUM(AS14:AS16) -> 9832902
A21: 합계: 매출원가(COGS) | F21: =SUM(F5:F16) -> 49500 | G21: =SUM(G5:G16) -> 85800 | H21: =SUM(H5:H16) -> 105600 | I21: =SUM(I5:I16) -> 118800 | J21: =SUM(J5:J16) -> 716930 | K21: =SUM(K5:K16) -> 1044008 | L21: =SUM(L5:L16) -> 4239826 | M21: =SUM(M5:M16) -> 1306006 | ... AS21: =SUM(AS5:AS16) -> 84632312

Sheet 판관비(SG&A)
A1: 판관비(SG&A) 월별 상세 (단위: 원)
A2: ※ 2025년은 표준손익계산서 판관비 계정(급여·보험료·복리후생비·여비교통비·기업업무추진비·세금과공과·지급수수료·소모품비)을 5대 그룹으로 재분류. 지급수수료 중 매출원가·SaaS·자문·광고 외 잔액은 MVP 외주 개발비(R&D)로 가정.
A3: 표준재무제표_계정과목 | B3: 그룹(Level1) | C3: 중분류(Level2) | D3: 소분류(Level3) | E3: 성격 | F3: 2025-05-31 | G3: 2025-06-30 | H3: 2025-07-31 | I3: 2025-08-31 | J3: 2025-09-30 | K3: 2025-10-31 | L3: 2025-11-30 | M3: 2025-12-31 | N3: 2026-01-31 | O3: 2026-02-28 | P3: 2026-03-31 | Q3: 2026-04-30 | R3: 2026-05-31 | S3: 2026-06-30 | T3: 2026-07-31 | U3: 2026-08-31 | V3: 2026-09-30 | W3: 2026-10-31 | X3: 2026-11-30 | Y3: 2026-12-31 | Z3: 2027-01-31 | AA3: 2027-02-28 | AB3: 2027-03-31 | AC3: 2027-04-30 | AD3: 2027-05-31 | AE3: 2027-06-30 | AF3: 2027-07-31 | AG3: 2027-08-31 | AH3: 2027-09-30 | AI3: 2027-10-31 | AJ3: 2027-11-30 | AK3: 2027-12-31 | AL3: 2028-01-31 | AM3: 2028-02-29 | AN3: 2028-03-31 | AO3: 2028-04-30 | AP3: FY2025(5~12월) | AQ3: FY2026 | AR3: FY2027 | AS3: FY2028(1~4월) | AT3: 참고_표준손익계산서 계정(세무신고 매핑)
A4: ※ 데이터구분 | F4: 실적배분 | G4: 실적배분 | H4: 실적배분 | I4: 실적배분 | J4: 실적배분 | K4: 실적배분 | L4: 실적배분 | M4: 실적배분 | N4: 가상 | O4: 가상 | P4: 가상 | Q4: 가상 | R4: 가상 | S4: 가상 | T4: 가상 | U4: 가상 | V4: 가상 | W4: 가상 | X4: 가상 | Y4: 가상 | Z4: 가상 | AA4: 가상 | AB4: 가상 | AC4: 가상 | AD4: 가상 | AE4: 가상 | AF4: 가상 | AG4: 가상 | AH4: 가상 | AI4: 가상 | AJ4: 가상 | AK4: 가상 | AL4: 가상 | AM4: 가상 | AN4: 가상 | AO4: 가상 | AP4: 연간 집계 | AQ4: 연간 집계 | AR4: 연간 집계 | AS4: 연간 집계
A5: 판매비와관리비 | B5: Labor Costs(인건비) | C5: 부서별 급여(인원은 KPI 시트 참조) | D5: 개발조직 급여 | E5: 고정 | F5: 0 | G5: 2999024 | H5: 2999024 | I5: 2999024 | J5: 2999024 | K5: 2999024 | L5: 2999024 | M5: 2999021 | N5: 7800000 | O5: 7800000 | P5: 7800000 | Q5: 12600000 | R5: 12600000 | S5: 12600000 | T5: 12600000 | U5: 12600000 | V5: 12600000 | W5: 12600000 | X5: 12600000 | Y5: 12600000 | Z5: 13230000 | AA5: 13230000 | AB5: 13230000 | AC5: 13230000 | AD5: 13230000 | AE5: 13230000 | AF5: 13230000 | AG5: 13230000 | AH5: 18480000 | AI5: 18480000 | AJ5: 18480000 | AK5: 18480000 | AL5: 19404000 | AM5: 19404000 | AN5: 19404000 | AO5: 19404000 | AP5: =SUM(F5:M5) -> 20993165 | AQ5: =SUM(N5:Y5) -> 136800000 | AR5: =SUM(Z5:AK5) -> 179760000 | AS5: =SUM(AL5:AO5) -> 77616000 | AT5: 급여 > 직원급여
A6: 판매비와관리비 | B6: Labor Costs(인건비) | C6: 부서별 급여(인원은 KPI 시트 참조) | D6: 사업·마케팅조직 급여 | E6: 고정 | F6: 0 | G6: 0 | H6: 0 | I6: 0 | J6: 0 | K6: 0 | L6: 0 | M6: 0 | N6: 0 | O6: 0 | P6: 0 | Q6: 3400000 | R6: 3400000 | S6: 3400000 | T6: 3400000 | U6: 3400000 | V6: 3400000 | W6: 3400000 | X6: 3400000 | Y6: 3400000 | Z6: 3570000 | AA6: 3570000 | AB6: 7350000 | AC6: 7350000 | AD6: 7350000 | AE6: 7350000 | AF6: 7350000 | AG6: 7350000 | AH6: 7350000 | AI6: 7350000 | AJ6: 7350000 | AK6: 7350000 | AL6: 7717500 | AM6: 7717500 | AN6: 7717500 | AO6: 7717500 | AP6: =SUM(F6:M6) -> 0 | AQ6: =SUM(N6:Y6) -> 30600000 | AR6: =SUM(Z6:AK6) -> 80640000 | AS6: =SUM(AL6:AO6) -> 30870000 | AT6: 급여 > 직원급여
A7: 판매비와관리비 | B7: Labor Costs(인건비) | C7: 부서별 급여(인원은 KPI 시트 참조) | D7: 경영지원·운영조직 급여 | E7: 고정 | F7: 0 | G7: 0 | H7: 0 | I7: 0 | J7: 1669457 | K7: 1669457 | L7: 1669457 | M7: 1669457 | N7: 3000000 | O7: 3000000 | P7: 3000000 | Q7: 3000000 | R7: 3000000 | S7: 3000000 | T7: 7000000 | U7: 7000000 | V7: 7000000 | W7: 7000000 | X7: 7000000 | Y7: 7000000 | Z7: 7350000 | AA7: 7350000 | AB7: 7350000 | AC7: 7350000 | AD7: 7350000 | AE7: 10710000 | AF7: 10710000 | AG7: 10710000 | AH7: 10710000 | AI7: 10710000 | AJ7: 10710000 | AK7: 10710000 | AL7: 11245500 | AM7: 11245500 | AN7: 11245500 | AO7: 11245500 | AP7: =SUM(F7:M7) -> 6677828 | AQ7: =SUM(N7:Y7) -> 60000000 | AR7: =SUM(Z7:AK7) -> 111720000 | AS7: =SUM(AL7:AO7) -> 44982000 | AT7: 급여 > 직원급여
A8: 판매비와관리비 | B8: Labor Costs(인건비) | C8: 퇴직급여 | D8: 퇴직급여(퇴직연금 부담금) | E8: 고정 | F8: 0 | G8: 0 | H8: 0 | I8: 0 | J8: 0 | K8: 0 | L8: 0 | M8: 0 | N8: 900000 | O8: 900000 | P8: 900000 | Q8: 1583333 | R8: 1583333 | S8: 1583333 | T8: 1916667 | U8: 1916667 | V8: 1916667 | W8: 1916667 | X8: 1916667 | Y8: 1916667 | Z8: 2012500 | AA8: 2012500 | AB8: 2327500 | AC8: 2327500 | AD8: 2327500 | AE8: 2607500 | AF8: 2607500 | AG8: 2607500 | AH8: 3045000 | AI8: 3045000 | AJ8: 3045000 | AK8: 3045000 | AL8: 3197250 | AM8: 3197250 | AN8: 3197250 | AO8: 3197250 | AP8: =SUM(F8:M8) -> 0 | AQ8: =SUM(N8:Y8) -> 18950001 | AR8: =SUM(Z8:AK8) -> 31010000 | AS8: =SUM(AL8:AO8) -> 12789000 | AT8: 퇴직급여
A9: 판매비와관리비 | B9: Labor Costs(인건비) | C9: 법정부담금 | D9: 4대보험료(회사부담분) | E9: 고정 | F9: 0 | G9: 50221 | H9: 50221 | I9: 50221 | J9: 78177 | K9: 78177 | L9: 78177 | M9: 78176 | N9: 1058400 | O9: 1058400 | P9: 1058400 | Q9: 1862000 | R9: 1862000 | S9: 1862000 | T9: 2254000 | U9: 2254000 | V9: 2254000 | W9: 2254000 | X9: 2254000 | Y9: 2254000 | Z9: 2366700 | AA9: 2366700 | AB9: 2737140 | AC9: 2737140 | AD9: 2737140 | AE9: 3066420 | AF9: 3066420 | AG9: 3066420 | AH9: 3580920 | AI9: 3580920 | AJ9: 3580920 | AK9: 3580920 | AL9: 3759966 | AM9: 3759966 | AN9: 3759966 | AO9: 3759966 | AP9: =SUM(F9:M9) -> 463370 | AQ9: =SUM(N9:Y9) -> 22285200 | AR9: =SUM(Z9:AK9) -> 36467760 | AS9: =SUM(AL9:AO9) -> 15039864 | AT9: 보험료 / 복리후생비
A10: 판매비와관리비 | B10: Labor Costs(인건비) | C10: 복리후생 | D10: 복리후생비(식대·경조사·건강검진 등) | E10: 변동 | F10: 0 | G10: 261448 | H10: 261448 | I10: 261448 | J10: 406987 | K10: 406987 | L10: 406987 | M10: 406984 | N10: 750000 | O10: 1350000 | P10: 750000 | Q10: 1250000 | R10: 1250000 | S10: 1250000 | T10: 1500000 | U10: 1500000 | V10: 2700000 | W10: 1500000 | X10: 1500000 | Y10: 1500000 | Z10: 1500000 | AA10: 2700000 | AB10: 1750000 | AC10: 1750000 | AD10: 1750000 | AE10: 2000000 | AF10: 2000000 | AG10: 2000000 | AH10: 4050000 | AI10: 2250000 | AJ10: 2250000 | AK10: 2250000 | AL10: 2250000 | AM10: 4050000 | AN10: 2250000 | AO10: 2250000 | AP10: =SUM(F10:M10) -> 2412289 | AQ10: =SUM(N10:Y10) -> 16800000 | AR10: =SUM(Z10:AK10) -> 26250000 | AS10: =SUM(AL10:AO10) -> 10800000 | AT10: 복리후생비
A11: 판매비와관리비 | B11: D&A(감가상각·무형자산상각) | C11: 유형자산상각 | D11: 유형자산 감가상각비(노트북·서버·비품) | E11: 고정 | F11: 0 | G11: 0 | H11: 0 | I11: 0 | J11: 0 | K11: 0 | L11: 0 | M11: 0 | N11: 0 | O11: 83333 | P11: 83333 | Q11: 83333 | R11: 156667 | S11: 156667 | T11: 156667 | U11: 193333 | V11: 193333 | W11: 193333 | X11: 193333 | Y11: 193333 | Z11: 343333 | AA11: 343333 | AB11: 343333 | AC11: 380000 | AD11: 380000 | AE11: 380000 | AF11: 380000 | AG11: 380000 | AH11: 380000 | AI11: 420000 | AJ11: 420000 | AK11: 420000 | AL11: 420000 | AM11: 420000 | AN11: 420000 | AO11: 420000 | AP11: =SUM(F11:M11) -> 0 | AQ11: =SUM(N11:Y11) -> 1686665 | AR11: =SUM(Z11:AK11) -> 4569999 | AS11: =SUM(AL11:AO11) -> 1680000 | AT11: 감가상각비
A12: 판매비와관리비 | B12: D&A(감가상각·무형자산상각) | C12: 무형자산상각 | D12: 무형자산 상각비(개발비 자산화분·SW 라이선스) | E12: 고정 | F12: 0 | G12: 0 | H12: 0 | I12: 0 | J12: 0 | K12: 0 | L12: 0 | M12: 0 | N12: 0 | O12: 0 | P12: 25000 | Q12: 25000 | R12: 25000 | S12: 25000 | T12: 25000 | U12: 25000 | V12: 25000 | W12: 25000 | X12: 25000 | Y12: 25000 | Z12: 25000 | AA12: 25000 | AB12: 25000 | AC12: 25000 | AD12: 25000 | AE12: 58333 | AF12: 58333 | AG12: 58333 | AH12: 58333 | AI12: 58333 | AJ12: 58333 | AK12: 58333 | AL12: 58333 | AM12: 58333 | AN12: 58333 | AO12: 58333 | AP12: =SUM(F12:M12) -> 0 | AQ12: =SUM(N12:Y12) -> 250000 | AR12: =SUM(Z12:AK12) -> 533331 | AS12: =SUM(AL12:AO12) -> 233332 | AT12: 무형자산상각비
A13: 판매비와관리비 | B13: R&D(연구개발비) | C13: 외주비 | D13: 외주 개발비 | E13: 변동 | F13: 6883054 | G13: 6883054 | H13: 6883054 | I13: 4588702 | J13: 2294351 | K13: 1147176 | L13: 1147176 | M13: 1147174 | N13: 3000000 | O13: 3000000 | P13: 3000000 | Q13: 2000000 | R13: 2000000 | S13: 2000000 | T13: 2000000 | U13: 2000000 | V13: 2000000 | W13: 2000000 | X13: 4000000 | Y13: 4000000 | Z13: 4000000 | AA13: 4000000 | AB13: 4000000 | AC13: 4000000 | AD13: 4000000 | AE13: 4000000 | AF13: 4000000 | AG13: 4000000 | AH13: 4000000 | AI13: 4000000 | AJ13: 4000000 | AK13: 4000000 | AL13: 4000000 | AM13: 4000000 | AN13: 4000000 | AO13: 4000000 | AP13: =SUM(F13:M13) -> 30973741 | AQ13: =SUM(N13:Y13) -> 31000000 | AR13: =SUM(Z13:AK13) -> 48000000 | AS13: =SUM(AL13:AO13) -> 16000000 | AT13: 경상연구개발비
A14: 판매비와관리비 | B14: R&D(연구개발비) | C14: 개발환경 | D14: 개발·테스트용 클라우드·LLM 사용료 | E14: 변동 | F14: 0 | G14: 300000 | H14: 300000 | I14: 300000 | J14: 200000 | K14: 200000 | L14: 200000 | M14: 200000 | N14: 350000 | O14: 350000 | P14: 350000 | Q14: 350000 | R14: 350000 | S14: 350000 | T14: 350000 | U14: 350000 | V14: 350000 | W14: 350000 | X14: 350000 | Y14: 350000 | Z14: 500000 | AA14: 500000 | AB14: 500000 | AC14: 500000 | AD14: 500000 | AE14: 500000 | AF14: 500000 | AG14: 500000 | AH14: 500000 | AI14: 500000 | AJ14: 500000 | AK14: 500000 | AL14: 500000 | AM14: 500000 | AN14: 500000 | AO14: 500000 | AP14: =SUM(F14:M14) -> 1700000 | AQ14: =SUM(N14:Y14) -> 4200000 | AR14: =SUM(Z14:AK14) -> 6000000 | AS14: =SUM(AL14:AO14) -> 2000000 | AT14: 경상연구개발비
A15: 판매비와관리비 | B15: R&D(연구개발비) | C15: 기타 | D15: 기타 연구개발비(데이터·도구 구입 등) | E15: 변동 | F15: 0 | G15: 0 | H15: 0 | I15: 0 | J15: 0 | K15: 0 | L15: 0 | M15: 0 | N15: 0 | O15: 0 | P15: 500000 | Q15: 500000 | R15: 500000 | S15: 500000 | T15: 500000 | U15: 500000 | V15: 500000 | W15: 500000 | X15: 500000 | Y15: 500000 | Z15: 800000 | AA15: 800000 | AB15: 800000 | AC15: 800000 | AD15: 800000 | AE15: 800000 | AF15: 800000 | AG15: 800000 | AH15: 800000 | AI15: 800000 | AJ15: 800000 | AK15: 800000 | AL15: 800000 | AM15: 800000 | AN15: 800000 | AO15: 800000 | AP15: =SUM(F15:M15) -> 0 | AQ15: =SUM(N15:Y15) -> 5000000 | AR15: =SUM(Z15:AK15) -> 9600000 | AS15: =SUM(AL15:AO15) -> 3200000 | AT15: 경상연구개발비
A16: 판매비와관리비 | B16: S&M(판매및마케팅비) | C16: 퍼포먼스마케팅 | D16: 광고선전비 - [a] AI 취업준비 SaaS 구독자 획득 | E16: 변동 | F16: 0 | G16: 0 | H16: 0 | I16: 0 | J16: 800000 | K16: 900000 | L16: 700000 | M16: 600000 | N16: 1120000 | O16: 1500000 | P16: 2080000 | Q16: 1940000 | R16: 1600000 | S16: 1540000 | T16: 1900000 | U16: 2740000 | V16: 3740000 | W16: 3260000 | X16: 2680000 | Y16: 2260000 | Z16: 3816000 | AA16: 4800000 | AB16: 6288000 | AC16: 5544000 | AD16: 4296000 | AE16: 3912000 | AF16: 4536000 | AG16: 6240000 | AH16: 8040000 | AI16: 6624000 | AJ16: 5112000 | AK16: 4104000 | AL16: 5876000 | AM16: 7332000 | AN16: 9516000 | AO16: 8320000 | AP16: =SUM(F16:M16) -> 3000000 | AQ16: =SUM(N16:Y16) -> 26360000 | AR16: =SUM(Z16:AK16) -> 63312000 | AS16: =SUM(AL16:AO16) -> 31044000 | AT16: 광고선전비
... A31: 판매비와관리비 | B31: Other G&A(기타관리비) | C31: 기타 | D31: 기타판관비 | E31: 변동 | F31: 0 | G31: 0 | H31: 0 | I31: 0 | J31: 0 | K31: 0 | L31: 0 | M31: 0 | N31: 80000 | O31: 80000 | P31: 80000 | Q31: 80000 | R31: 80000 | S31: 80000 | T31: 80000 | U31: 80000 | V31: 80000 | W31: 80000 | X31: 80000 | Y31: 80000 | Z31: 150000 | AA31: 150000 | AB31: 150000 | AC31: 150000 | AD31: 150000 | AE31: 150000 | AF31: 150000 | AG31: 150000 | AH31: 150000 | AI31: 150000 | AJ31: 150000 | AK31: 150000 | AL31: 150000 | AM31: 150000 | AN31: 150000 | AO31: 150000 | AP31: =SUM(F31:M31) -> 0 | AQ31: =SUM(N31:Y31) -> 960000 | AR31: =SUM(Z31:AK31) -> 1800000 | AS31: =SUM(AL31:AO31) -> 600000 | AT31: 잡비 등
A33: 소계: Labor Costs(인건비) | F33: =SUM(F5:F10) -> 0 | G33: =SUM(G5:G10) -> 3310693 | H33: =SUM(H5:H10) -> 3310693 | I33: =SUM(I5:I10) -> 3310693 | J33: =SUM(J5:J10) -> 5153645 | K33: =SUM(K5:K10) -> 5153645 | L33: =SUM(L5:L10) -> 5153645 | M33: =SUM(M5:M10) -> 5153638 | ... AS33: =SUM(AS5:AS10) -> 192096864
A34: 소계: D&A(감가상각·무형자산상각) | F34: =SUM(F11:F12) -> 0 | G34: =SUM(G11:G12) -> 0 | H34: =SUM(H11:H12) -> 0 | I34: =SUM(I11:I12) -> 0 | J34: =SUM(J11:J12) -> 0 | K34: =SUM(K11:K12) -> 0 | L34: =SUM(L11:L12) -> 0 | M34: =SUM(M11:M12) -> 0 | ... AS34: =SUM(AS11:AS12) -> 1913332
A35: 소계: R&D(연구개발비) | F35: =SUM(F13:F15) -> 6883054 | G35: =SUM(G13:G15) -> 7183054 | H35: =SUM(H13:H15) -> 7183054 | I35: =SUM(I13:I15) -> 4888702 | J35: =SUM(J13:J15) -> 2494351 | K35: =SUM(K13:K15) -> 1347176 | L35: =SUM(L13:L15) -> 1347176 | M35: =SUM(M13:M15) -> 1347174 | ... AS35: =SUM(AS13:AS15) -> 21200000
A36: 소계: S&M(판매및마케팅비) | F36: =SUM(F16:F19) -> 0 | G36: =SUM(G16:G19) -> 300000 | H36: =SUM(H16:H19) -> 300000 | I36: =SUM(I16:I19) -> 600000 | J36: =SUM(J16:J19) -> 1400000 | K36: =SUM(K16:K19) -> 2100000 | L36: =SUM(L16:L19) -> 1200000 | M36: =SUM(M16:M19) -> 1100000 | ... AS36: =SUM(AS16:AS19) -> 46471087
A37: 소계: Other G&A(기타관리비) | F37: =SUM(F20:F31) -> 1660495 | G37: =SUM(G20:G31) -> 476613 | H37: =SUM(H20:H31) -> 476613 | I37: =SUM(I20:I31) -> 476257 | J37: =SUM(J20:J31) -> 568553 | K37: =SUM(K20:K31) -> 669257 | L37: =SUM(L20:L31) -> 697492 | M37: =SUM(M20:M31) -> 656573 | ... AS37: =SUM(AS20:AS31) -> 23032000
A38: 합계: 판관비(SG&A) | F38: =SUM(F5:F31) -> 8543549 | G38: =SUM(G5:G31) -> 11270360 | H38: =SUM(H5:H31) -> 11270360 | I38: =SUM(I5:I31) -> 9275652 | J38: =SUM(J5:J31) -> 9616549 | K38: =SUM(K5:K31) -> 9270078 | L38: =SUM(L5:L31) -> 8398313 | M38: =SUM(M5:M31) -> 8257385 | ... AS38: =SUM(AS5:AS31) -> 284713283

Sheet 손익계산서(P&L)
A1: 손익계산서(P&L) 월별 요약 (단위: 원)
A2: ※ 매출·매출원가·판관비는 상세 시트 합계를 연결(초록색). 영업외손익은 입력값(파란색): 2025년은 표준손익계산서 실적, 2026년 이후 정부보조금은 초기창업패키지(2026-05~11, 월 700만원)·TIPS R&D(2026-11~, 월 1,600만원) 가정.
A3: 항목 | B3: 산식·비고 | F3: 2025-05-31 | G3: 2025-06-30 | H3: 2025-07-31 | I3: 2025-08-31 | J3: 2025-09-30 | K3: 2025-10-31 | L3: 2025-11-30 | M3: 2025-12-31 | N3: 2026-01-31 | O3: 2026-02-28 | P3: 2026-03-31 | Q3: 2026-04-30 | R3: 2026-05-31 | S3: 2026-06-30 | T3: 2026-07-31 | U3: 2026-08-31 | V3: 2026-09-30 | W3: 2026-10-31 | X3: 2026-11-30 | Y3: 2026-12-31 | Z3: 2027-01-31 | AA3: 2027-02-28 | AB3: 2027-03-31 | AC3: 2027-04-30 | AD3: 2027-05-31 | AE3: 2027-06-30 | AF3: 2027-07-31 | AG3: 2027-08-31 | AH3: 2027-09-30 | AI3: 2027-10-31 | AJ3: 2027-11-30 | AK3: 2027-12-31 | AL3: 2028-01-31 | AM3: 2028-02-29 | AN3: 2028-03-31 | AO3: 2028-04-30 | AP3: FY2025(5~12월) | AQ3: FY2026 | AR3: FY2027 | AS3: FY2028(1~4월) | AT3: 참고_표준손익계산서 계정
A4: ※ 데이터구분 | F4: 실적배분 | G4: 실적배분 | H4: 실적배분 | I4: 실적배분 | J4: 실적배분 | K4: 실적배분 | L4: 실적배분 | M4: 실적배분 | N4: 가상 | O4: 가상 | P4: 가상 | Q4: 가상 | R4: 가상 | S4: 가상 | T4: 가상 | U4: 가상 | V4: 가상 | W4: 가상 | X4: 가상 | Y4: 가상 | Z4: 가상 | AA4: 가상 | AB4: 가상 | AC4: 가상 | AD4: 가상 | AE4: 가상 | AF4: 가상 | AG4: 가상 | AH4: 가상 | AI4: 가상 | AJ4: 가상 | AK4: 가상 | AL4: 가상 | AM4: 가상 | AN4: 가상 | AO4: 가상 | AP4: 연간 집계 | AQ4: 연간 집계 | AR4: 연간 집계 | AS4: 연간 집계
A5: 매출액 | F5: ='매출(Revenue)'!F27 -> 1500000 | G5: ='매출(Revenue)'!G27 -> 2600000 | H5: ='매출(Revenue)'!H27 -> 3200000 | I5: ='매출(Revenue)'!I27 -> 3600000 | J5: ='매출(Revenue)'!J27 -> 5010000 | K5: ='매출(Revenue)'!K27 -> 5736000 | L5: ='매출(Revenue)'!L27 -> 9202000 | M5: ='매출(Revenue)'!M27 -> 6429876 | ... AS5: ='매출(Revenue)'!AS27 -> 340511889 | AT5: Ⅰ.매출액
A6: [a] AI 취업준비 SaaS | F6: ='매출(Revenue)'!F24 -> 0 | G6: ='매출(Revenue)'!G24 -> 0 | H6: ='매출(Revenue)'!H24 -> 0 | I6: ='매출(Revenue)'!I24 -> 0 | J6: ='매출(Revenue)'!J24 -> 810000 | K6: ='매출(Revenue)'!K24 -> 1836000 | L6: ='매출(Revenue)'!L24 -> 2502000 | M6: ='매출(Revenue)'!M24 -> 2952000 | ... AS6: ='매출(Revenue)'!AS24 -> 259194499
A7: [b] 전자책·강의 중개수수료 | F7: ='매출(Revenue)'!F25 -> 0 | G7: ='매출(Revenue)'!G25 -> 0 | H7: ='매출(Revenue)'!H25 -> 0 | I7: ='매출(Revenue)'!I25 -> 0 | J7: ='매출(Revenue)'!J25 -> 0 | K7: ='매출(Revenue)'!K25 -> 0 | L7: ='매출(Revenue)'!L25 -> 0 | M7: ='매출(Revenue)'!M25 -> 0 | ... AS7: ='매출(Revenue)'!AS25 -> 28176459
A8: [c] 자체 콘텐츠·컨퍼런스 | F8: ='매출(Revenue)'!F26 -> 1500000 | G8: ='매출(Revenue)'!G26 -> 2600000 | H8: ='매출(Revenue)'!H26 -> 3200000 | I8: ='매출(Revenue)'!I26 -> 3600000 | J8: ='매출(Revenue)'!J26 -> 4200000 | K8: ='매출(Revenue)'!K26 -> 3900000 | L8: ='매출(Revenue)'!L26 -> 6700000 | M8: ='매출(Revenue)'!M26 -> 3477876 | ... AS8: ='매출(Revenue)'!AS26 -> 53140931
A9: 매출원가 | F9: ='매출원가(COGS)'!F21 -> 49500 | G9: ='매출원가(COGS)'!G21 -> 85800 | H9: ='매출원가(COGS)'!H21 -> 105600 | I9: ='매출원가(COGS)'!I21 -> 118800 | J9: ='매출원가(COGS)'!J21 -> 716930 | K9: ='매출원가(COGS)'!K21 -> 1044008 | L9: ='매출원가(COGS)'!L21 -> 4239826 | M9: ='매출원가(COGS)'!M21 -> 1306006 | ... AS9: ='매출원가(COGS)'!AS21 -> 84632312 | AT9: Ⅱ.매출원가
A10: [a] AI 취업준비 SaaS | F10: ='매출원가(COGS)'!F18 -> 0 | G10: ='매출원가(COGS)'!G18 -> 0 | H10: ='매출원가(COGS)'!H18 -> 0 | I10: ='매출원가(COGS)'!I18 -> 0 | J10: ='매출원가(COGS)'!J18 -> 578330 | K10: ='매출원가(COGS)'!K18 -> 871748 | L10: ='매출원가(COGS)'!L18 -> 1062286 | M10: ='매출원가(COGS)'!M18 -> 1191236 | ... AS10: ='매출원가(COGS)'!AS18 -> 61526349
A11: [b] 콘텐츠 중개 | F11: ='매출원가(COGS)'!F19 -> 0 | G11: ='매출원가(COGS)'!G19 -> 0 | H11: ='매출원가(COGS)'!H19 -> 0 | I11: ='매출원가(COGS)'!I19 -> 0 | J11: ='매출원가(COGS)'!J19 -> 0 | K11: ='매출원가(COGS)'!K19 -> 0 | L11: ='매출원가(COGS)'!L19 -> 0 | M11: ='매출원가(COGS)'!M19 -> 0 | ... AS11: ='매출원가(COGS)'!AS19 -> 13273061
A12: [c] 자체 콘텐츠·컨퍼런스 | F12: ='매출원가(COGS)'!F20 -> 49500 | G12: ='매출원가(COGS)'!G20 -> 85800 | H12: ='매출원가(COGS)'!H20 -> 105600 | I12: ='매출원가(COGS)'!I20 -> 118800 | J12: ='매출원가(COGS)'!J20 -> 138600 | K12: ='매출원가(COGS)'!K20 -> 172260 | L12: ='매출원가(COGS)'!L20 -> 3177540 | M12: ='매출원가(COGS)'!M20 -> 114770 | ... AS12: ='매출원가(COGS)'!AS20 -> 9832902
A13: 매출총이익 | F13: =F5-F9 -> 1450500 | G13: =G5-G9 -> 2514200 | H13: =H5-H9 -> 3094400 | I13: =I5-I9 -> 3481200 | J13: =J5-J9 -> 4293070 | K13: =K5-K9 -> 4691992 | L13: =L5-L9 -> 4962174 | M13: =M5-M9 -> 5123870 | ... AS13: =AS5-AS9 -> 255879577 | AT13: Ⅲ.매출총손익
A14: 매출총이익률 | F14: =IF(F5=0,0,F13/F5) -> 0.967 | G14: =IF(G5=0,0,G13/G5) -> 0.967 | H14: =IF(H5=0,0,H13/H5) -> 0.967 | I14: =IF(I5=0,0,I13/I5) -> 0.967 | J14: =IF(J5=0,0,J13/J5) -> 0.8569002 | K14: =IF(K5=0,0,K13/K5) -> 0.81799024 | L14: =IF(L5=0,0,L13/L5) -> 0.53924951 | M14: =IF(M5=0,0,M13/M5) -> 0.79688473 | ... AS14: =IF(AS5=0,0,AS13/AS5) -> 0.75145563
A15: [a] 매출총이익률 | F15: =IF(F6=0,0,(F6-F10)/F6) -> 0 | G15: =IF(G6=0,0,(G6-G10)/G6) -> 0 | H15: =IF(H6=0,0,(H6-H10)/H6) -> 0 | I15: =IF(I6=0,0,(I6-I10)/I6) -> 0 | J15: =IF(J6=0,0,(J6-J10)/J6) -> 0.28601235 | K15: =IF(K6=0,0,(K6-K10)/K6) -> 0.52519172 | L15: =IF(L6=0,0,(L6-L10)/L6) -> 0.57542526 | M15: =IF(M6=0,0,(M6-M10)/M6) -> 0.59646477 | ... AS15: =IF(AS6=0,0,(AS6-AS10)/AS6) -> 0.76262479
A16: [b] 매출총이익률 | F16: =IF(F7=0,0,(F7-F11)/F7) -> 0 | G16: =IF(G7=0,0,(G7-G11)/G7) -> 0 | H16: =IF(H7=0,0,(H7-H11)/H7) -> 0 | I16: =IF(I7=0,0,(I7-I11)/I7) -> 0 | J16: =IF(J7=0,0,(J7-J11)/J7) -> 0 | K16: =IF(K7=0,0,(K7-K11)/K7) -> 0 | L16: =IF(L7=0,0,(L7-L11)/L7) -> 0 | M16: =IF(M7=0,0,(M7-M11)/M7) -> 0 | ... AS16: =IF(AS7=0,0,(AS7-AS11)/AS7) -> 0.52893084
A17: [c] 매출총이익률 | F17: =IF(F8=0,0,(F8-F12)/F8) -> 0.967 | G17: =IF(G8=0,0,(G8-G12)/G8) -> 0.967 | H17: =IF(H8=0,0,(H8-H12)/H8) -> 0.967 | I17: =IF(I8=0,0,(I8-I12)/I8) -> 0.967 | J17: =IF(J8=0,0,(J8-J12)/J8) -> 0.967 | K17: =IF(K8=0,0,(K8-K12)/K8) -> 0.95583077 | L17: =IF(L8=0,0,(L8-L12)/L8) -> 0.5257403 | M17: =IF(M8=0,0,(M8-M12)/M8) -> 0.96699997 | ... AS17: =IF(AS8=0,0,(AS8-AS12)/AS8) -> 0.81496557
A18: 판매비와관리비 | F18: ='판관비(SG&A)'!F38 -> 8543549 | G18: ='판관비(SG&A)'!G38 -> 11270360 | H18: ='판관비(SG&A)'!H38 -> 11270360 | I18: ='판관비(SG&A)'!I38 -> 9275652 | J18: ='판관비(SG&A)'!J38 -> 9616549 | K18: ='판관비(SG&A)'!K38 -> 9270078 | L18: ='판관비(SG&A)'!L38 -> 8398313 | M18: ='판관비(SG&A)'!M38 -> 8257385 | ... AS18: ='판관비(SG&A)'!AS38 -> 284713283 | AT18: Ⅳ.판매비와관리비
A19: Labor Costs(인건비) | F19: ='판관비(SG&A)'!F33 -> 0 | G19: ='판관비(SG&A)'!G33 -> 3310693 | H19: ='판관비(SG&A)'!H33 -> 3310693 | I19: ='판관비(SG&A)'!I33 -> 3310693 | J19: ='판관비(SG&A)'!J33 -> 5153645 | K19: ='판관비(SG&A)'!K33 -> 5153645 | L19: ='판관비(SG&A)'!L33 -> 5153645 | M19: ='판관비(SG&A)'!M33 -> 5153638 | ... AS19: ='판관비(SG&A)'!AS33 -> 192096864
A20: D&A(감가상각·무형자산상각) | F20: ='판관비(SG&A)'!F34 -> 0 | G20: ='판관비(SG&A)'!G34 -> 0 | H20: ='판관비(SG&A)'!H34 -> 0 | I20: ='판관비(SG&A)'!I34 -> 0 | J20: ='판관비(SG&A)'!J34 -> 0 | K20: ='판관비(SG&A)'!K34 -> 0 | L20: ='판관비(SG&A)'!L34 -> 0 | M20: ='판관비(SG&A)'!M34 -> 0 | ... AS20: ='판관비(SG&A)'!AS34 -> 1913332
A21: R&D(연구개발비) | F21: ='판관비(SG&A)'!F35 -> 6883054 | G21: ='판관비(SG&A)'!G35 -> 7183054 | H21: ='판관비(SG&A)'!H35 -> 7183054 | I21: ='판관비(SG&A)'!I35 -> 4888702 | J21: ='판관비(SG&A)'!J35 -> 2494351 | K21: ='판관비(SG&A)'!K35 -> 1347176 | L21: ='판관비(SG&A)'!L35 -> 1347176 | M21: ='판관비(SG&A)'!M35 -> 1347174 | ... AS21: ='판관비(SG&A)'!AS35 -> 21200000
A22: S&M(판매및마케팅비) | F22: ='판관비(SG&A)'!F36 -> 0 | G22: ='판관비(SG&A)'!G36 -> 300000 | H22: ='판관비(SG&A)'!H36 -> 300000 | I22: ='판관비(SG&A)'!I36 -> 600000 | J22: ='판관비(SG&A)'!J36 -> 1400000 | K22: ='판관비(SG&A)'!K36 -> 2100000 | L22: ='판관비(SG&A)'!L36 -> 1200000 | M22: ='판관비(SG&A)'!M36 -> 1100000 | ... AS22: ='판관비(SG&A)'!AS36 -> 46471087
A23: Other G&A(기타관리비) | F23: ='판관비(SG&A)'!F37 -> 1660495 | G23: ='판관비(SG&A)'!G37 -> 476613 | H23: ='판관비(SG&A)'!H37 -> 476613 | I23: ='판관비(SG&A)'!I37 -> 476257 | J23: ='판관비(SG&A)'!J37 -> 568553 | K23: ='판관비(SG&A)'!K37 -> 669257 | L23: ='판관비(SG&A)'!L37 -> 697492 | M23: ='판관비(SG&A)'!M37 -> 656573 | ... AS23: ='판관비(SG&A)'!AS37 -> 23032000
A24: 영업이익(손실) | F24: =F13-F18 -> -7093049 | G24: =G13-G18 -> -8756160 | H24: =H13-H18 -> -8175960 | I24: =I13-I18 -> -5794452 | J24: =J13-J18 -> -5323479 | K24: =K13-K18 -> -4578086 | L24: =L13-L18 -> -3436139 | M24: =M13-M18 -> -3133515 | ... AS24: =AS13-AS18 -> -28833706 | AT24: Ⅴ.영업손익
A25: 영업이익률 | F25: =IF(F5=0,0,F24/F5) -> -4.7286993 | G25: =IF(G5=0,0,G24/G5) -> -3.3677538 | H25: =IF(H5=0,0,H24/H5) -> -2.5549875 | I25: =IF(I5=0,0,I24/I5) -> -1.60957 | J25: =IF(J5=0,0,J24/J5) -> -1.0625707 | K25: =IF(K5=0,0,K24/K5) -> -0.79813215 | L25: =IF(L5=0,0,L24/L5) -> -0.37341219 | M25: =IF(M5=0,0,M24/M5) -> -0.48733677 | ... AS25: =IF(AS5=0,0,AS24/AS5) -> -0.084677531
A26: EBITDA(영업이익+감가상각비) | F26: =F24+F20 -> -7093049 | G26: =G24+G20 -> -8756160 | H26: =H24+H20 -> -8175960 | I26: =I24+I20 -> -5794452 | J26: =J24+J20 -> -5323479 | K26: =K24+K20 -> -4578086 | L26: =L24+L20 -> -3436139 | M26: =M24+M20 -> -3133515 | ... AS26: =AS24+AS20 -> -26920374
A27: 영업외수익 | F27: =F28+F29 -> 0 | G27: =G28+G29 -> 5141680 | H27: =H28+H29 -> 5141680 | I27: =I28+I29 -> 4113344 | J27: =J28+J29 -> 3085008 | K27: =K28+K29 -> 2056672 | L27: =L28+L29 -> 2071672 | M27: =M28+M29 -> 2093081 | ... AS27: =AS28+AS29 -> 67762020 | AT27: Ⅵ.영업외수익
A28: 이자수익 | B28: 2026~: 전월 말 현금 × 연 1.8% ÷ 12 | F28: 0 | G28: 0 | H28: 0 | I28: 0 | J28: 0 | K28: 0 | L28: 15000 | M28: 36410 | N28: 298186 | O28: 261372 | P28: 238020 | Q28: 227934 | R28: 937939 | S28: 944999 | T28: 927558 | U28: 903045 | V28: 890511 | W28: 886277 | X28: 873416 | Y28: 905437 | Z28: 839991 | AA28: 836193 | AB28: 838857 | AC28: 845646 | AD28: 835459 | AE28: 918468 | AF28: 908592 | AG28: 896830 | AH28: 911693 | AI28: 927743 | AJ28: 918716 | AK28: 965620 | AL28: 946110 | AM28: 927695 | AN28: 931633 | AO28: 956582 | AP28: =SUM(F28:M28) -> 51410 | AQ28: =SUM(N28:Y28) -> 8294694 | AR28: =SUM(Z28:AK28) -> 10643808 | AS28: =SUM(AL28:AO28) -> 3762020 | AT28: 1.이자수익
A29: 정부보조금·기타잡이익 | B29: 2025: 신고서 기타잡이익(창업지원금 가정) | F29: 0 | G29: 5141680 | H29: 5141680 | I29: 4113344 | J29: 3085008 | K29: 2056672 | L29: 2056672 | M29: 2056671 | N29: 0 | O29: 0 | P29: 0 | Q29: 0 | R29: 7000000 | S29: 7000000 | T29: 7000000 | U29: 7000000 | V29: 7000000 | W29: 7000000 | X29: 23000000 | Y29: 16000000 | Z29: 16000000 | AA29: 16000000 | AB29: 16000000 | AC29: 16000000 | AD29: 16000000 | AE29: 16000000 | AF29: 16000000 | AG29: 16000000 | AH29: 16000000 | AI29: 16000000 | AJ29: 16000000 | AK29: 16000000 | AL29: 16000000 | AM29: 16000000 | AN29: 16000000 | AO29: 16000000 | AP29: =SUM(F29:M29) -> 23651727 | AQ29: =SUM(N29:Y29) -> 81000000 | AR29: =SUM(Z29:AK29) -> 192000000 | AS29: =SUM(AL29:AO29) -> 64000000 | AT29: 28.기타잡이익
A30: 영업외비용 | F30: =F31+F32 -> 0 | G30: =G31+G32 -> 0 | H30: =H31+H32 -> 0 | I30: =I31+I32 -> 0 | J30: =J31+J32 -> 0 | K30: =K31+K32 -> 0 | L30: =L31+L32 -> 0 | M30: =M31+M32 -> 438822 | ... AS30: =AS31+AS32 -> 1564629 | AT30: Ⅶ.영업외비용
A31: 이자비용 | B31: 장기차입금 2억 × 연 2.5% ÷ 12 | F31: 0 | G31: 0 | H31: 0 | I31: 0 | J31: 0 | K31: 0 | L31: 0 | M31: 435982 | N31: 416667 | O31: 416667 | P31: 416667 | Q31: 416667 | R31: 416667 | S31: 416667 | T31: 416667 | U31: 416667 | V31: 416667 | W31: 416667 | X31: 416667 | Y31: 416667 | Z31: 416667 | AA31: 416667 | AB31: 416667 | AC31: 416667 | AD31: 416667 | AE31: 416667 | AF31: 416667 | AG31: 416667 | AH31: 416667 | AI31: 416667 | AJ31: 416667 | AK31: 405093 | AL31: 393519 | AM31: 381944 | AN31: 370370 | AO31: 358796 | AP31: =SUM(F31:M31) -> 435982 | AQ31: =SUM(N31:Y31) -> 5000004 | AR31: =SUM(Z31:AK31) -> 4988430 | AS31: =SUM(AL31:AO31) -> 1504629 | AT31: 1.이자비용
A32: 기타잡손실(환차손 등) | F32: 0 | G32: 0 | H32: 0 | I32: 0 | J32: 0 | K32: 0 | L32: 0 | M32: 2840 | N32: 15000 | O32: 15000 | P32: 15000 | Q32: 15000 | R32: 15000 | S32: 15000 | T32: 15000 | U32: 15000 | V32: 15000 | W32: 15000 | X32: 15000 | Y32: 15000 | Z32: 15000 | AA32: 15000 | AB32: 15000 | AC32: 15000 | AD32: 15000 | AE32: 15000 | AF32: 15000 | AG32: 15000 | AH32: 15000 | AI32: 15000 | AJ32: 15000 | AK32: 15000 | AL32: 15000 | AM32: 15000 | AN32: 15000 | AO32: 15000 | AP32: =SUM(F32:M32) -> 2840 | AQ32: =SUM(N32:Y32) -> 180000 | AR32: =SUM(Z32:AK32) -> 180000 | AS32: =SUM(AL32:AO32) -> 60000 | AT32: 21.기타잡손실
A33: 법인세비용차감전순이익(손실) | F33: =F24+F27-F30 -> -7093049 | G33: =G24+G27-G30 -> -3614480 | H33: =H24+H27-H30 -> -3034280 | I33: =I24+I27-I30 -> -1681108 | J33: =J24+J27-J30 -> -2238471 | K33: =K24+K27-K30 -> -2521414 | L33: =L24+L27-L30 -> -1364467 | M33: =M24+M27-M30 -> -1479256 | ... AS33: =AS24+AS27-AS30 -> 37363685 | AT33: Ⅷ.법인세비용차감전손익
A34: 법인세비용 | B34: 누적 결손(이월결손금)으로 0원 가정 | F34: 0 | G34: 0 | H34: 0 | I34: 0 | J34: 0 | K34: 0 | L34: 0 | M34: 0 | N34: 0 | O34: 0 | P34: 0 | Q34: 0 | R34: 0 | S34: 0 | T34: 0 | U34: 0 | V34: 0 | W34: 0 | X34: 0 | Y34: 0 | Z34: 0 | AA34: 0 | AB34: 0 | AC34: 0 | AD34: 0 | AE34: 0 | AF34: 0 | AG34: 0 | AH34: 0 | AI34: 0 | AJ34: 0 | AK34: 0 | AL34: 0 | AM34: 0 | AN34: 0 | AO34: 0 | AP34: =SUM(F34:M34) -> 0 | AQ34: =SUM(N34:Y34) -> 0 | AR34: =SUM(Z34:AK34) -> 0 | AS34: =SUM(AL34:AO34) -> 0 | AT34: Ⅸ.법인세비용
A35: 당기순이익(손실) | F35: =F33-F34 -> -7093049 | G35: =G33-G34 -> -3614480 | H35: =H33-H34 -> -3034280 | I35: =I33-I34 -> -1681108 | J35: =J33-J34 -> -2238471 | K35: =K33-K34 -> -2521414 | L35: =L33-L34 -> -1364467 | M35: =M33-M34 -> -1479256 | ... AS35: =AS33-AS34 -> 37363685 | AT35: Ⅹ.당기순손익

Sheet 현금흐름표(CF)
A1: 현금흐름표(CF) 월별 · 간접법 (단위: 원)
A2: ※ 당기순이익에서 출발해 비현금비용(감가상각)과 재무상태표 운전자본 증감을 가감(간접법). 투자·재무활동은 입력값(파란색). 기말현금이 재무상태표 현금으로 연결됩니다.
A3: 항목 | B3: 산식·비고 | F3: 2025-05-31 | G3: 2025-06-30 | H3: 2025-07-31 | I3: 2025-08-31 | J3: 2025-09-30 | K3: 2025-10-31 | L3: 2025-11-30 | M3: 2025-12-31 | N3: 2026-01-31 | O3: 2026-02-28 | P3: 2026-03-31 | Q3: 2026-04-30 | R3: 2026-05-31 | S3: 2026-06-30 | T3: 2026-07-31 | U3: 2026-08-31 | V3: 2026-09-30 | W3: 2026-10-31 | X3: 2026-11-30 | Y3: 2026-12-31 | Z3: 2027-01-31 | AA3: 2027-02-28 | AB3: 2027-03-31 | AC3: 2027-04-30 | AD3: 2027-05-31 | AE3: 2027-06-30 | AF3: 2027-07-31 | AG3: 2027-08-31 | AH3: 2027-09-30 | AI3: 2027-10-31 | AJ3: 2027-11-30 | AK3: 2027-12-31 | AL3: 2028-01-31 | AM3: 2028-02-29 | AN3: 2028-03-31 | AO3: 2028-04-30 | AP3: FY2025(5~12월) | AQ3: FY2026 | AR3: FY2027 | AS3: FY2028(1~4월) | AT3: 참고
A4: ※ 데이터구분 | F4: 실적배분 | G4: 실적배분 | H4: 실적배분 | I4: 실적배분 | J4: 실적배분 | K4: 실적배분 | L4: 실적배분 | M4: 실적배분 | N4: 가상 | O4: 가상 | P4: 가상 | Q4: 가상 | R4: 가상 | S4: 가상 | T4: 가상 | U4: 가상 | V4: 가상 | W4: 가상 | X4: 가상 | Y4: 가상 | Z4: 가상 | AA4: 가상 | AB4: 가상 | AC4: 가상 | AD4: 가상 | AE4: 가상 | AF4: 가상 | AG4: 가상 | AH4: 가상 | AI4: 가상 | AJ4: 가상 | AK4: 가상 | AL4: 가상 | AM4: 가상 | AN4: 가상 | AO4: 가상 | AP4: 연간 집계 | AQ4: 연간 집계 | AR4: 연간 집계 | AS4: 연간 집계
A5: Ⅰ. 영업활동현금흐름 | F5: =F6+F7+F8+SUM(F10:F21) -> -4593049 | G5: =G6+G7+G8+SUM(G10:G21) -> -1994480 | H5: =H6+H7+H8+SUM(H10:H21) -> -1504280 | I5: =I6+I7+I8+SUM(I10:I21) -> -151108 | J5: =J6+J7+J8+SUM(J10:J21) -> -1118471 | K5: =K6+K7+K8+SUM(K10:K21) -> -151414 | L5: =L6+L7+L8+SUM(L10:L21) -> -2634467 | M5: =M6+M7+M8+SUM(M10:M21) -> 937811 | ... AO5: =AO6+AO7+AO8+SUM(AO10:AO21) -> 31454 | AP5: =SUM(F5:M5) -> -11209458 | AQ5: =SUM(N5:Y5) -> -85196708 | AR5: =SUM(Z5:AK5) -> 90457054 | AS5: =SUM(AL5:AO5) -> 23679557
A6: 당기순이익(손실) | F6: ='손익계산서(P&L)'!F35 -> -7093049 | G6: ='손익계산서(P&L)'!G35 -> -3614480 | H6: ='손익계산서(P&L)'!H35 -> -3034280 | I6: ='손익계산서(P&L)'!I35 -> -1681108 | J6: ='손익계산서(P&L)'!J35 -> -2238471 | K6: ='손익계산서(P&L)'!K35 -> -2521414 | L6: ='손익계산서(P&L)'!L35 -> -1364467 | M6: ='손익계산서(P&L)'!M35 -> -1479256 | ... AO6: ='손익계산서(P&L)'!AO35 -> 31628416 | AP6: =SUM(F6:M6) -> -23026525 | AQ6: =SUM(N6:Y6) -> -130364048 | AR6: =SUM(Z6:AK6) -> 18492086 | AS6: =SUM(AL6:AO6) -> 37363685
A7: 감가상각비 가산 | F7: ='판관비(SG&A)'!F11 -> 0 | G7: ='판관비(SG&A)'!G11 -> 0 | H7: ='판관비(SG&A)'!H11 -> 0 | I7: ='판관비(SG&A)'!I11 -> 0 | J7: ='판관비(SG&A)'!J11 -> 0 | K7: ='판관비(SG&A)'!K11 -> 0 | L7: ='판관비(SG&A)'!L11 -> 0 | M7: ='판관비(SG&A)'!M11 -> 0 | ... AO7: ='판관비(SG&A)'!AO11 -> 420000 | AP7: =SUM(F7:M7) -> 0 | AQ7: =SUM(N7:Y7) -> 1686665 | AR7: =SUM(Z7:AK7) -> 4569999 | AS7: =SUM(AL7:AO7) -> 1680000
A8: 무형자산상각비 가산 | F8: ='판관비(SG&A)'!F12 -> 0 | G8: ='판관비(SG&A)'!G12 -> 0 | H8: ='판관비(SG&A)'!H12 -> 0 | I8: ='판관비(SG&A)'!I12 -> 0 | J8: ='판관비(SG&A)'!J12 -> 0 | K8: ='판관비(SG&A)'!K12 -> 0 | L8: ='판관비(SG&A)'!L12 -> 0 | M8: ='판관비(SG&A)'!M12 -> 0 | ... AO8: ='판관비(SG&A)'!AO12 -> 58333 | AP8: =SUM(F8:M8) -> 0 | AQ8: =SUM(N8:Y8) -> 250000 | AR8: =SUM(Z8:AK8) -> 533331 | AS8: =SUM(AL8:AO8) -> 233332
A9: [운전자본 변동]
A10: 매출채권 감소(증가) | F10: =0-'재무상태표(BS)'!F8 -> 0 | G10: ='재무상태표(BS)'!F8-'재무상태표(BS)'!G8 -> 0 | H10: ='재무상태표(BS)'!G8-'재무상태표(BS)'!H8 -> 0 | I10: ='재무상태표(BS)'!H8-'재무상태표(BS)'!I8 -> 0 | J10: ='재무상태표(BS)'!I8-'재무상태표(BS)'!J8 -> 0 | K10: ='재무상태표(BS)'!J8-'재무상태표(BS)'!K8 -> 0 | L10: ='재무상태표(BS)'!K8-'재무상태표(BS)'!L8 -> 0 | M10: ='재무상태표(BS)'!L8-'재무상태표(BS)'!M8 -> 0 | N10: ='재무상태표(BS)'!M8-'재무상태표(BS)'!N8 -> 0 | ... AO10: ='재무상태표(BS)'!AN8-'재무상태표(BS)'!AO8 -> -4950000 | AP10: =SUM(F10:M10) -> 0 | AQ10: =SUM(N10:Y10) -> -4162400 | AR10: =SUM(Z10:AK10) -> -3097600 | AS10: =SUM(AL10:AO10) -> -53020000
A11: 미수금(PG) 감소(증가) | F11: =0-'재무상태표(BS)'!F9 -> 0 | G11: ='재무상태표(BS)'!F9-'재무상태표(BS)'!G9 -> 0 | H11: ='재무상태표(BS)'!G9-'재무상태표(BS)'!H9 -> 0 | I11: ='재무상태표(BS)'!H9-'재무상태표(BS)'!I9 -> 0 | J11: ='재무상태표(BS)'!I9-'재무상태표(BS)'!J9 -> 0 | K11: ='재무상태표(BS)'!J9-'재무상태표(BS)'!K9 -> 0 | L11: ='재무상태표(BS)'!K9-'재무상태표(BS)'!L9 -> 0 | M11: ='재무상태표(BS)'!L9-'재무상태표(BS)'!M9 -> 0 | N11: ='재무상태표(BS)'!M9-'재무상태표(BS)'!N9 -> -1370567 | ... AO11: ='재무상태표(BS)'!AN9-'재무상태표(BS)'!AO9 -> 381090 | AP11: =SUM(F11:M11) -> 0 | AQ11: =SUM(N11:Y11) -> -5467814 | AR11: =SUM(Z11:AK11) -> -5338336 | AS11: =SUM(AL11:AO11) -> -8360167
A12: 선급금 감소(증가) | F12: =0-'재무상태표(BS)'!F10 -> 0 | G12: ='재무상태표(BS)'!F10-'재무상태표(BS)'!G10 -> 0 | H12: ='재무상태표(BS)'!G10-'재무상태표(BS)'!H10 -> 0 | I12: ='재무상태표(BS)'!H10-'재무상태표(BS)'!I10 -> 0 | J12: ='재무상태표(BS)'!I10-'재무상태표(BS)'!J10 -> 0 | K12: ='재무상태표(BS)'!J10-'재무상태표(BS)'!K10 -> 0 | L12: ='재무상태표(BS)'!K10-'재무상태표(BS)'!L10 -> -500000 | M12: ='재무상태표(BS)'!L10-'재무상태표(BS)'!M10 -> -451480 | N12: ='재무상태표(BS)'!M10-'재무상태표(BS)'!N10 -> 951480 | ... AO12: ='재무상태표(BS)'!AN10-'재무상태표(BS)'!AO10 -> 1350000 | AP12: =SUM(F12:M12) -> -951480 | AQ12: =SUM(N12:Y12) -> 951480 | AR12: =SUM(Z12:AK12) -> 0 | AS12: =SUM(AL12:AO12) -> 0
A13: 부가세대급금 감소(증가) | F13: =0-'재무상태표(BS)'!F11 -> 0 | G13: ='재무상태표(BS)'!F11-'재무상태표(BS)'!G11 -> 0 | H13: ='재무상태표(BS)'!G11-'재무상태표(BS)'!H11 -> 0 | I13: ='재무상태표(BS)'!H11-'재무상태표(BS)'!I11 -> 0 | J13: ='재무상태표(BS)'!I11-'재무상태표(BS)'!J11 -> 0 | K13: ='재무상태표(BS)'!J11-'재무상태표(BS)'!K11 -> 0 | L13: ='재무상태표(BS)'!K11-'재무상태표(BS)'!L11 -> 0 | M13: ='재무상태표(BS)'!L11-'재무상태표(BS)'!M11 -> 0 | N13: ='재무상태표(BS)'!M11-'재무상태표(BS)'!N11 -> -178764 | ... AO13: ='재무상태표(BS)'!AN11-'재무상태표(BS)'!AO11 -> 0 | AP13: =SUM(F13:M13) -> 0 | AQ13: =SUM(N13:Y13) -> 0 | AR13: =SUM(Z13:AK13) -> 0 | AS13: =SUM(AL13:AO13) -> 0
A14: 매입채무 증가(감소) | F14: ='재무상태표(BS)'!F19-0 -> 0 | G14: ='재무상태표(BS)'!G19-'재무상태표(BS)'!F19 -> 0 | H14: ='재무상태표(BS)'!H19-'재무상태표(BS)'!G19 -> 0 | I14: ='재무상태표(BS)'!I19-'재무상태표(BS)'!H19 -> 0 | J14: ='재무상태표(BS)'!J19-'재무상태표(BS)'!I19 -> 0 | K14: ='재무상태표(BS)'!K19-'재무상태표(BS)'!J19 -> 0 | L14: ='재무상태표(BS)'!L19-'재무상태표(BS)'!K19 -> 0 | M14: ='재무상태표(BS)'!M19-'재무상태표(BS)'!L19 -> 56354 | N14: ='재무상태표(BS)'!N19-'재무상태표(BS)'!M19 -> 1614371 | ... AO14: ='재무상태표(BS)'!AO19-'재무상태표(BS)'!AN19 -> 448995 | AP14: =SUM(F14:M14) -> 56354 | AQ14: =SUM(N14:Y14) -> 6708695 | AR14: =SUM(Z14:AK14) -> 5914743 | AS14: =SUM(AL14:AO14) -> 2547335
A15: 미지급금 증가(감소) | F15: ='재무상태표(BS)'!F20-0 -> 2500000 | G15: ='재무상태표(BS)'!G20-'재무상태표(BS)'!F20 -> 1500000 | H15: ='재무상태표(BS)'!H20-'재무상태표(BS)'!G20 -> 1500000 | I15: ='재무상태표(BS)'!I20-'재무상태표(BS)'!H20 -> 1500000 | J15: ='재무상태표(BS)'!J20-'재무상태표(BS)'!I20 -> 1000000 | K15: ='재무상태표(BS)'!K20-'재무상태표(BS)'!J20 -> 1000000 | L15: ='재무상태표(BS)'!L20-'재무상태표(BS)'!K20 -> 500000 | M15: ='재무상태표(BS)'!M20-'재무상태표(BS)'!L20 -> 488590 | N15: ='재무상태표(BS)'!N20-'재무상태표(BS)'!M20 -> -6543390 | ... AO15: ='재무상태표(BS)'!AO20-'재무상태표(BS)'!AN20 -> 1336147 | AP15: =SUM(F15:M15) -> 9988590 | AQ15: =SUM(N15:Y15) -> -3926047 | AR15: =SUM(Z15:AK15) -> 3732495 | AS15: =SUM(AL15:AO15) -> 7727516
A16: 예수금 증가(감소) | F16: ='재무상태표(BS)'!F21-0 -> 0 | G16: ='재무상태표(BS)'!G21-'재무상태표(BS)'!F21 -> 120000 | H16: ='재무상태표(BS)'!H21-'재무상태표(BS)'!G21 -> 30000 | I16: ='재무상태표(BS)'!I21-'재무상태표(BS)'!H21 -> 30000 | J16: ='재무상태표(BS)'!J21-'재무상태표(BS)'!I21 -> 120000 | K16: ='재무상태표(BS)'!K21-'재무상태표(BS)'!J21 -> 50000 | L16: ='재무상태표(BS)'!L21-'재무상태표(BS)'!K21 -> 50000 | M16: ='재무상태표(BS)'!M21-'재무상태표(BS)'!L21 -> 175420 | N16: ='재무상태표(BS)'!N21-'재무상태표(BS)'!M21 -> 1778980 | ... AO16: ='재무상태표(BS)'!AO21-'재무상태표(BS)'!AN21 -> 0 | AP16: =SUM(F16:M16) -> 575420 | AQ16: =SUM(N16:Y16) -> 4438580 | AR16: =SUM(Z16:AK16) -> 2951720 | AS16: =SUM(AL16:AO16) -> 398286
A17: 셀러 정산 예수금 증가(감소) | F17: ='재무상태표(BS)'!F22-0 -> 0 | G17: ='재무상태표(BS)'!G22-'재무상태표(BS)'!F22 -> 0 | H17: ='재무상태표(BS)'!H22-'재무상태표(BS)'!G22 -> 0 | I17: ='재무상태표(BS)'!I22-'재무상태표(BS)'!H22 -> 0 | J17: ='재무상태표(BS)'!J22-'재무상태표(BS)'!I22 -> 0 | K17: ='재무상태표(BS)'!K22-'재무상태표(BS)'!J22 -> 0 | L17: ='재무상태표(BS)'!L22-'재무상태표(BS)'!K22 -> 0 | M17: ='재무상태표(BS)'!M22-'재무상태표(BS)'!L22 -> 0 | N17: ='재무상태표(BS)'!N22-'재무상태표(BS)'!M22 -> 0 | ... AO17: ='재무상태표(BS)'!AO22-'재무상태표(BS)'!AN22 -> -3580712 | AP17: =SUM(F17:M17) -> 0 | AQ17: =SUM(N17:Y17) -> 7451793 | AR17: =SUM(Z17:AK17) -> 6534799 | AS17: =SUM(AL17:AO17) -> 12999750
A18: 부가세예수금 증가(감소) | F18: ='재무상태표(BS)'!F23-0 -> 0 | G18: ='재무상태표(BS)'!G23-'재무상태표(BS)'!F23 -> 0 | H18: ='재무상태표(BS)'!H23-'재무상태표(BS)'!G23 -> 0 | I18: ='재무상태표(BS)'!I23-'재무상태표(BS)'!H23 -> 0 | J18: ='재무상태표(BS)'!J23-'재무상태표(BS)'!I23 -> 0 | K18: ='재무상태표(BS)'!K23-'재무상태표(BS)'!J23 -> 0 | L18: ='재무상태표(BS)'!L23-'재무상태표(BS)'!K23 -> 0 | M18: ='재무상태표(BS)'!M23-'재무상태표(BS)'!L23 -> 0 | N18: ='재무상태표(BS)'!N23-'재무상태표(BS)'!M23 -> 0 | ... AO18: ='재무상태표(BS)'!AO23-'재무상태표(BS)'!AN23 -> -13813448 | AP18: =SUM(F18:M18) -> 0 | AQ18: =SUM(N18:Y18) -> 5871359 | AR18: =SUM(Z18:AK18) -> 8645149 | AS18: =SUM(AL18:AO18) -> -7162083
A19: 선수수익 증가(감소) | F19: ='재무상태표(BS)'!F24-0 -> 0 | G19: ='재무상태표(BS)'!G24-'재무상태표(BS)'!F24 -> 0 | H19: ='재무상태표(BS)'!H24-'재무상태표(BS)'!G24 -> 0 | I19: ='재무상태표(BS)'!I24-'재무상태표(BS)'!H24 -> 0 | J19: ='재무상태표(BS)'!J24-'재무상태표(BS)'!I24 -> 0 | K19: ='재무상태표(BS)'!K24-'재무상태표(BS)'!J24 -> 0 | L19: ='재무상태표(BS)'!L24-'재무상태표(BS)'!K24 -> 0 | M19: ='재무상태표(BS)'!M24-'재무상태표(BS)'!L24 -> 0 | N19: ='재무상태표(BS)'!N24-'재무상태표(BS)'!M24 -> 1509263 | ... AO19: ='재무상태표(BS)'!AO24-'재무상태표(BS)'!AN24 -> -4927367 | AP19: =SUM(F19:M19) -> 0 | AQ19: =SUM(N19:Y19) -> 33513212 | AR19: =SUM(Z19:AK19) -> 47518668 | AS19: =SUM(AL19:AO19) -> 29271903
A20: 선수금 증가(감소) | F20: ='재무상태표(BS)'!F25-0 -> 0 | G20: ='재무상태표(BS)'!G25-'재무상태표(BS)'!F25 -> 0 | H20: ='재무상태표(BS)'!H25-'재무상태표(BS)'!G25 -> 0 | I20: ='재무상태표(BS)'!I25-'재무상태표(BS)'!H25 -> 0 | J20: ='재무상태표(BS)'!J25-'재무상태표(BS)'!I25 -> 0 | K20: ='재무상태표(BS)'!K25-'재무상태표(BS)'!J25 -> 1320000 | L20: ='재무상태표(BS)'!L25-'재무상태표(BS)'!K25 -> -1320000 | M20: ='재무상태표(BS)'!M25-'재무상태표(BS)'!L25 -> 0 | N20: ='재무상태표(BS)'!N25-'재무상태표(BS)'!M25 -> 0 | ... AO20: ='재무상태표(BS)'!AO25-'재무상태표(BS)'!AN25 -> -8320000 | AP20: =SUM(F20:M20) -> 0 | AQ20: =SUM(N20:Y20) -> 0 | AR20: =SUM(Z20:AK20) -> 0 | AS20: =SUM(AL20:AO20) -> 0
A21: 미지급법인세 증가(감소) | F21: ='재무상태표(BS)'!F26-0 -> 0 | G21: ='재무상태표(BS)'!G26-'재무상태표(BS)'!F26 -> 0 | H21: ='재무상태표(BS)'!H26-'재무상태표(BS)'!G26 -> 0 | I21: ='재무상태표(BS)'!I26-'재무상태표(BS)'!H26 -> 0 | J21: ='재무상태표(BS)'!J26-'재무상태표(BS)'!I26 -> 0 | K21: ='재무상태표(BS)'!K26-'재무상태표(BS)'!J26 -> 0 | L21: ='재무상태표(BS)'!L26-'재무상태표(BS)'!K26 -> 0 | M21: ='재무상태표(BS)'!M26-'재무상태표(BS)'!L26 -> 2148183 | N21: ='재무상태표(BS)'!N26-'재무상태표(BS)'!M26 -> -2148183 | ... AO21: ='재무상태표(BS)'!AO26-'재무상태표(BS)'!AN26 -> 0 | AP21: =SUM(F21:M21) -> 2148183 | AQ21: =SUM(N21:Y21) -> -2148183 | AR21: =SUM(Z21:AK21) -> 0 | AS21: =SUM(AL21:AO21) -> 0
A22: Ⅱ. 투자활동현금흐름 | F22: =SUM(F23:F25) -> 0 | G22: =SUM(G23:G25) -> 0 | H22: =SUM(H23:H25) -> 0 | I22: =SUM(I23:I25) -> 0 | J22: =SUM(J23:J25) -> 0 | K22: =SUM(K23:K25) -> 0 | L22: =SUM(L23:L25) -> 0 | M22: =SUM(M23:M25) -> 0 | ... AO22: =SUM(AO23:AO25) -> 0 | AP22: =SUM(F22:M22) -> 0 | AQ22: =SUM(N22:Y22) -> -53600000 | AR22: =SUM(Z22:AK22) -> -8600000 | AS22: =SUM(AL22:AO22) -> 0
A23: 유형자산 취득 | B23: 노트북·비품 등, 5년 정액 상각 | F23: 0 | G23: 0 | H23: 0 | I23: 0 | J23: 0 | K23: 0 | L23: 0 | M23: 0 | N23: -5000000 | O23: 0 | P23: 0 | Q23: -4400000 | R23: 0 | S23: 0 | T23: -2200000 | U23: 0 | V23: 0 | W23: 0 | X23: 0 | Y23: -9000000 | Z23: 0 | AA23: 0 | AB23: -2200000 | AC23: 0 | AD23: 0 | AE23: 0 | AF23: 0 | AG23: 0 | AH23: -2400000 | AI23: 0 | AJ23: 0 | AK23: 0 | AL23: 0 | AM23: 0 | AN23: 0 | AO23: 0 | AP23: =SUM(F23:M23) -> 0 | AQ23: =SUM(N23:Y23) -> -20600000 | AR23: =SUM(Z23:AK23) -> -4600000 | AS23: =SUM(AL23:AO23) -> 0
A24: 무형자산 취득 | B24: 상표권·특허, 10년 정액 상각 | F24: 0 | G24: 0 | H24: 0 | I24: 0 | J24: 0 | K24: 0 | L24: 0 | M24: 0 | N24: 0 | O24: -3000000 | P24: 0 | Q24: 0 | R24: 0 | S24: 0 | T24: 0 | U24: 0 | V24: 0 | W24: 0 | X24: 0 | Y24: 0 | Z24: 0 | AA24: 0 | AB24: 0 | AC24: 0 | AD24: -4000000 | AE24: 0 | AF24: 0 | AG24: 0 | AH24: 0 | AI24: 0 | AJ24: 0 | AK24: 0 | AL24: 0 | AM24: 0 | AN24: 0 | AO24: 0 | AP24: =SUM(F24:M24) -> 0 | AQ24: =SUM(N24:Y24) -> -3000000 | AR24: =SUM(Z24:AK24) -> -4000000 | AS24: =SUM(AL24:AO24) -> 0
A25: 임차보증금 지급 | B25: 2027-01 사무실 이전 대비 보증금 | F25: 0 | G25: 0 | H25: 0 | I25: 0 | J25: 0 | K25: 0 | L25: 0 | M25: 0 | N25: 0 | O25: 0 | P25: 0 | Q25: 0 | R25: 0 | S25: 0 | T25: 0 | U25: 0 | V25: 0 | W25: 0 | X25: 0 | Y25: -30000000 | Z25: 0 | AA25: 0 | AB25: 0 | AC25: 0 | AD25: 0 | AE25: 0 | AF25: 0 | AG25: 0 | AH25: 0 | AI25: 0 | AJ25: 0 | AK25: 0 | AL25: 0 | AM25: 0 | AN25: 0 | AO25: 0 | AP25: =SUM(F25:M25) -> 0 | AQ25: =SUM(N25:Y25) -> -30000000 | AR25: =SUM(Z25:AK25) -> 0 | AS25: =SUM(AL25:AO25) -> 0
A26: Ⅲ. 재무활동현금흐름 | F26: =SUM(F27:F30) -> 10000000 | G26: =SUM(G27:G30) -> 0 | H26: =SUM(H27:H30) -> 0 | I26: =SUM(I27:I30) -> 0 | J26: =SUM(J27:J30) -> 0 | K26: =SUM(K27:K30) -> 0 | L26: =SUM(L27:L30) -> 200000000 | M26: =SUM(M27:M30) -> 0 | ... AO26: =SUM(AO27:AO30) -> -5555556 | AP26: =SUM(F26:M26) -> 210000000 | AQ26: =SUM(N26:Y26) -> 500000000 | AR26: =SUM(Z26:AK26) -> -11111112 | AS26: =SUM(AL26:AO26) -> -22222224
A27: 장기차입금 차입 | B27: 2025-11 정책자금(연 2.5%, 거치 2년) | F27: 0 | G27: 0 | H27: 0 | I27: 0 | J27: 0 | K27: 0 | L27: 200000000 | M27: 0 | N27: 0 | O27: 0 | P27: 0 | Q27: 0 | R27: 0 | S27: 0 | T27: 0 | U27: 0 | V27: 0 | W27: 0 | X27: 0 | Y27: 0 | Z27: 0 | AA27: 0 | AB27: 0 | AC27: 0 | AD27: 0 | AE27: 0 | AF27: 0 | AG27: 0 | AH27: 0 | AI27: 0 | AJ27: 0 | AK27: 0 | AL27: 0 | AM27: 0 | AN27: 0 | AO27: 0 | AP27: =SUM(F27:M27) -> 200000000 | AQ27: =SUM(N27:Y27) -> 0 | AR27: =SUM(Z27:AK27) -> 0 | AS27: =SUM(AL27:AO27) -> 0
A28: 장기차입금 상환 | B28: 2027-11~ 36개월 균등분할상환 | F28: 0 | G28: 0 | H28: 0 | I28: 0 | J28: 0 | K28: 0 | L28: 0 | M28: 0 | N28: 0 | O28: 0 | P28: 0 | Q28: 0 | R28: 0 | S28: 0 | T28: 0 | U28: 0 | V28: 0 | W28: 0 | X28: 0 | Y28: 0 | Z28: 0 | AA28: 0 | AB28: 0 | AC28: 0 | AD28: 0 | AE28: 0 | AF28: 0 | AG28: 0 | AH28: 0 | AI28: 0 | AJ28: -5555556 | AK28: -5555556 | AL28: -5555556 | AM28: -5555556 | AN28: -5555556 | AO28: -5555556 | AP28: =SUM(F28:M28) -> 0 | AQ28: =SUM(N28:Y28) -> 0 | AR28: =SUM(Z28:AK28) -> -11111112 | AS28: =SUM(AL28:AO28) -> -22222224
A29: 유상증자(자본금) | B29: 2025-05 설립자본금, 2026-04 시드투자 5억 | F29: 10000000 | G29: 0 | H29: 0 | I29: 0 | J29: 0 | K29: 0 | L29: 0 | M29: 0 | N29: 0 | O29: 0 | P29: 0 | Q29: 1250000 | R29: 0 | S29: 0 | T29: 0 | U29: 0 | V29: 0 | W29: 0 | X29: 0 | Y29: 0 | Z29: 0 | AA29: 0 | AB29: 0 | AC29: 0 | AD29: 0 | AE29: 0 | AF29: 0 | AG29: 0 | AH29: 0 | AI29: 0 | AJ29: 0 | AK29: 0 | AL29: 0 | AM29: 0 | AN29: 0 | AO29: 0 | AP29: =SUM(F29:M29) -> 10000000 | AQ29: =SUM(N29:Y29) -> 1250000 | AR29: =SUM(Z29:AK29) -> 0 | AS29: =SUM(AL29:AO29) -> 0
A30: 유상증자(주식발행초과금) | F30: 0 | G30: 0 | H30: 0 | I30: 0 | J30: 0 | K30: 0 | L30: 0 | M30: 0 | N30: 0 | O30: 0 | P30: 0 | Q30: 498750000 | R30: 0 | S30: 0 | T30: 0 | U30: 0 | V30: 0 | W30: 0 | X30: 0 | Y30: 0 | Z30: 0 | AA30: 0 | AB30: 0 | AC30: 0 | AD30: 0 | AE30: 0 | AF30: 0 | AG30: 0 | AH30: 0 | AI30: 0 | AJ30: 0 | AK30: 0 | AL30: 0 | AM30: 0 | AN30: 0 | AO30: 0 | AP30: =SUM(F30:M30) -> 0 | AQ30: =SUM(N30:Y30) -> 498750000 | AR30: =SUM(Z30:AK30) -> 0 | AS30: =SUM(AL30:AO30) -> 0
A31: Ⅳ. 현금 증감(Ⅰ+Ⅱ+Ⅲ) | F31: =F5+F22+F26 -> 5406951 | G31: =G5+G22+G26 -> -1994480 | H31: =H5+H22+H26 -> -1504280 | I31: =I5+I22+I26 -> -151108 | J31: =J5+J22+J26 -> -1118471 | K31: =K5+K22+K26 -> -151414 | L31: =L5+L22+L26 -> 197365533 | M31: =M5+M22+M26 -> 937811 | ... AO31: =AO5+AO22+AO26 -> -5524102 | AP31: =SUM(F31:M31) -> 198790542 | AQ31: =SUM(N31:Y31) -> 361203292 | AR31: =SUM(Z31:AK31) -> 70745942 | AS31: =SUM(AL31:AO31) -> 1457333
A32: Ⅴ. 기초 현금 | F32: =0 -> 0 | G32: =F33 -> 5406951 | H32: =G33 -> 3412471 | I32: =H33 -> 1908191 | J32: =I33 -> 1757083 | K32: =J33 -> 638612 | L32: =K33 -> 487198 | M32: =L33 -> 197852731 | N32: =M33 -> 198790542 | ... AO32: =AN33 -> 637721211 | AP32: =F32 -> 0 | AQ32: =N32 -> 198790542 | AR32: =Z32 -> 559993834 | AS32: =AL32 -> 630739776
A33: Ⅵ. 기말 현금 | F33: =F32+F31 -> 5406951 | G33: =G32+G31 -> 3412471 | H33: =H32+H31 -> 1908191 | I33: =I32+I31 -> 1757083 | J33: =J32+J31 -> 638612 | K33: =K32+K31 -> 487198 | L33: =L32+L31 -> 197852731 | M33: =M32+M31 -> 198790542 | ... AO33: =AO32+AO31 -> 632197109 | AP33: =M33 -> 198790542 | AQ33: =Y33 -> 559993834 | AR33: =AK33 -> 630739776 | AS33: =AO33 -> 632197109
A34: 참고: Free Cash Flow(Ⅰ+Ⅱ) | F34: =F5+F22 -> -4593049 | G34: =G5+G22 -> -1994480 | H34: =H5+H22 -> -1504280 | I34: =I5+I22 -> -151108 | J34: =J5+J22 -> -1118471 | K34: =K5+K22 -> -151414 | L34: =L5+L22 -> -2634467 | M34: =M5+M22 -> 937811 | ... AO34: =AO5+AO22 -> 31454 | AP34: =SUM(F34:M34) -> -11209458 | AQ34: =SUM(N34:Y34) -> -138796708 | AR34: =SUM(Z34:AK34) -> 81857054 | AS34: =SUM(AL34:AO34) -> 23679557

Sheet 재무상태표(BS)
A1: 재무상태표(BS) 월말 잔액 (단위: 원)
A2: ※ 2025-12월 잔액은 2025 표준재무상태표와 원 단위까지 일치. 운전자본 항목은 입력값(파란색), 현금·유무형자산·차입금·자본은 현금흐름표·손익계산서와 연결된 산식. 연간 열은 각 연도 말(2028은 4월 말) 잔액.
A3: 계정과목 | B3: 산정 기준 | F3: 2025-05-31 | G3: 2025-06-30 | H3: 2025-07-31 | I3: 2025-08-31 | J3: 2025-09-30 | K3: 2025-10-31 | L3: 2025-11-30 | M3: 2025-12-31 | N3: 2026-01-31 | O3: 2026-02-28 | P3: 2026-03-31 | Q3: 2026-04-30 | R3: 2026-05-31 | S3: 2026-06-30 | T3: 2026-07-31 | U3: 2026-08-31 | V3: 2026-09-30 | W3: 2026-10-31 | X3: 2026-11-30 | Y3: 2026-12-31 | Z3: 2027-01-31 | AA3: 2027-02-28 | AB3: 2027-03-31 | AC3: 2027-04-30 | AD3: 2027-05-31 | AE3: 2027-06-30 | AF3: 2027-07-31 | AG3: 2027-08-31 | AH3: 2027-09-30 | AI3: 2027-10-31 | AJ3: 2027-11-30 | AK3: 2027-12-31 | AL3: 2028-01-31 | AM3: 2028-02-29 | AN3: 2028-03-31 | AO3: 2028-04-30 | AP3: FY2025(5~12월) | AQ3: FY2026 | AR3: FY2027 | AS3: FY2028(1~4월) | AT3: 참고_표준재무상태표 계정(2025 신고)
A4: ※ 데이터구분 | F4: 실적배분 | G4: 실적배분 | H4: 실적배분 | I4: 실적배분 | J4: 실적배분 | K4: 실적배분 | L4: 실적배분 | M4: 실적배분 | N4: 가상 | O4: 가상 | P4: 가상 | Q4: 가상 | R4: 가상 | S4: 가상 | T4: 가상 | U4: 가상 | V4: 가상 | W4: 가상 | X4: 가상 | Y4: 가상 | Z4: 가상 | AA4: 가상 | AB4: 가상 | AC4: 가상 | AD4: 가상 | AE4: 가상 | AF4: 가상 | AG4: 가상 | AH4: 가상 | AI4: 가상 | AJ4: 가상 | AK4: 가상 | AL4: 가상 | AM4: 가상 | AN4: 가상 | AO4: 가상 | AP4: 연간 집계 | AQ4: 연간 집계 | AR4: 연간 집계 | AS4: 연간 집계
A5: [자산]
A6: 유동자산 | F6: =SUM(F7:F11) -> 5406951 | G6: =SUM(G7:G11) -> 3412471 | H6: =SUM(H7:H11) -> 1908191 | I6: =SUM(I7:I11) -> 1757083 | J6: =SUM(J7:J11) -> 638612 | K6: =SUM(K7:K11) -> 487198 | L6: =SUM(L7:L11) -> 198352731 | M6: =SUM(M7:M11) -> 199742022 | ... AO6: =SUM(AO7:AO11) -> 711643426 | AP6: =M6 -> 199742022 | AQ6: =Y6 -> 569624048 | AR6: =AK6 -> 648805926 | AS6: =AO6 -> 711643426 | AT6: Ⅰ.유동자산
A7: 현금및현금성자산 | B7: 현금흐름표 기말현금 | F7: ='현금흐름표(CF)'!F33 -> 5406951 | G7: ='현금흐름표(CF)'!G33 -> 3412471 | H7: ='현금흐름표(CF)'!H33 -> 1908191 | I7: ='현금흐름표(CF)'!I33 -> 1757083 | J7: ='현금흐름표(CF)'!J33 -> 638612 | K7: ='현금흐름표(CF)'!K33 -> 487198 | L7: ='현금흐름표(CF)'!L33 -> 197852731 | M7: ='현금흐름표(CF)'!M33 -> 198790542 | ... AO7: ='현금흐름표(CF)'!AO33 -> 632197109 | AP7: =M7 -> 198790542 | AQ7: =Y7 -> 559993834 | AR7: =AK7 -> 630739776 | AS7: =AO7 -> 632197109 | AT7: 1.현금 및 현금성자산
A8: 매출채권 | B8: 법인 월정산 30일·연간계약 60일 회수(VAT 포함) | F8: 0 | G8: 0 | H8: 0 | I8: 0 | J8: 0 | K8: 0 | L8: 0 | M8: 0 | N8: 0 | O8: 0 | P8: 16500000 | Q8: 19800000 | R8: 176000 | S8: 2428800 | T8: 1656600 | U8: 510400 | V8: 16548400 | W8: 18836400 | X8: 774400 | Y8: 4162400 | Z8: 2875400 | AA8: 1038400 | AB8: 64376400 | AC8: 67764400 | AD8: 1302400 | AE8: 5790400 | AF8: 3953400 | AG8: 1566400 | AH8: 41914400 | AI8: 46384800 | AJ8: 1760000 | AK8: 7260000 | AL8: 4785000 | AM8: 1760000 | AN8: 55330000 | AO8: 60280000 | AP8: =M8 -> 0 | AQ8: =Y8 -> 4162400 | AR8: =AK8 -> 7260000 | AS8: =AO8 -> 60280000 | AT8: 매출채권
A9: 미수금(PG 카드정산 대기) | B9: 월말 카드결제액의 15% 정산 대기(D+3~5) | F9: 0 | G9: 0 | H9: 0 | I9: 0 | J9: 0 | K9: 0 | L9: 0 | M9: 0 | N9: 1370567 | O9: 1913380 | P9: 3683531 | Q9: 3913015 | R9: 3284839 | S9: 3287991 | T9: 3852276 | U9: 5200950 | V9: 7536490 | W9: 7523627 | X9: 5946784 | Y9: 5467814 | Z9: 6866708 | AA9: 8367757 | AB9: 11586526 | AC9: 11672464 | AD9: 9073808 | AE9: 8768914 | AF9: 9716645 | AG9: 12258498 | AH9: 16346776 | AI9: 15571325 | AJ9: 12154279 | AK9: 10806150 | AL9: 12697829 | AM9: 14810081 | AN9: 19547407 | AO9: 19166317 | AP9: =M9 -> 0 | AQ9: =Y9 -> 5467814 | AR9: =AK9 -> 10806150 | AS9: =AO9 -> 19166317 | AT9: 미수금
A10: 선급금 | B10: 컨퍼런스 대관 계약금(대관료 30%) | F10: 0 | G10: 0 | H10: 0 | I10: 0 | J10: 0 | K10: 0 | L10: 500000 | M10: 951480 | N10: 0 | O10: 0 | P10: 750000 | Q10: 0 | R10: 0 | S10: 0 | T10: 0 | U10: 0 | V10: 900000 | W10: 0 | X10: 0 | Y10: 0 | Z10: 0 | AA10: 0 | AB10: 1050000 | AC10: 0 | AD10: 0 | AE10: 0 | AF10: 0 | AG10: 0 | AH10: 1200000 | AI10: 0 | AJ10: 0 | AK10: 0 | AL10: 0 | AM10: 0 | AN10: 1350000 | AO10: 0 | AP10: =M10 -> 951480 | AQ10: =Y10 -> 0 | AR10: =AK10 -> 0 | AS10: =AO10 -> 0 | AT10: 7.선급금
A11: 부가세대급금(환급예정) | B11: 매입세액 > 매출세액일 때 | F11: 0 | G11: 0 | H11: 0 | I11: 0 | J11: 0 | K11: 0 | L11: 0 | M11: 0 | N11: 178764 | O11: 0 | P11: 0 | Q11: 0 | R11: 0 | S11: 0 | T11: 0 | U11: 0 | V11: 0 | W11: 0 | X11: 0 | Y11: 0 | Z11: 0 | AA11: 0 | AB11: 0 | AC11: 0 | AD11: 0 | AE11: 0 | AF11: 0 | AG11: 0 | AH11: 0 | AI11: 0 | AJ11: 0 | AK11: 0 | AL11: 0 | AM11: 0 | AN11: 0 | AO11: 0 | AP11: =M11 -> 0 | AQ11: =Y11 -> 0 | AR11: =AK11 -> 0 | AS11: =AO11 -> 0 | AT11: 부가세대급금
A12: 비유동자산 | F12: =SUM(F13:F15) -> 0 | G12: =SUM(G13:G15) -> 0 | H12: =SUM(H13:H15) -> 0 | I12: =SUM(I13:I15) -> 0 | J12: =SUM(J13:J15) -> 0 | K12: =SUM(K13:K15) -> 0 | L12: =SUM(L13:L15) -> 0 | M12: =SUM(M13:M15) -> 0 | ... AO12: =SUM(AO13:AO15) -> 53246673 | AP12: =M12 -> 0 | AQ12: =Y12 -> 51663335 | AR12: =AK12 -> 55160005 | AS12: =AO12 -> 53246673 | AT12: Ⅱ.비유동자산
A13: 유형자산(순액) | B13: 전월+취득-감가상각 | F13: =0-'현금흐름표(CF)'!F23-'판관비(SG&A)'!F11 -> 0 | G13: =F13-'현금흐름표(CF)'!G23-'판관비(SG&A)'!G11 -> 0 | H13: =G13-'현금흐름표(CF)'!H23-'판관비(SG&A)'!H11 -> 0 | I13: =H13-'현금흐름표(CF)'!I23-'판관비(SG&A)'!I11 -> 0 | J13: =I13-'현금흐름표(CF)'!J23-'판관비(SG&A)'!J11 -> 0 | K13: =J13-'현금흐름표(CF)'!K23-'판관비(SG&A)'!K11 -> 0 | L13: =K13-'현금흐름표(CF)'!L23-'판관비(SG&A)'!L11 -> 0 | M13: =L13-'현금흐름표(CF)'!M23-'판관비(SG&A)'!M11 -> 0 | N13: =M13-'현금흐름표(CF)'!N23-'판관비(SG&A)'!N11 -> 5000000 | ... AO13: =AN13-'현금흐름표(CF)'!AO23-'판관비(SG&A)'!AO11 -> 17263336 | AP13: =M13 -> 0 | AQ13: =Y13 -> 18913335 | AR13: =AK13 -> 18943336 | AS13: =AO13 -> 17263336 | AT13: (2)유형자산
A14: 무형자산(순액) | B14: 전월+취득-상각 | F14: =0-'현금흐름표(CF)'!F24-'판관비(SG&A)'!F12 -> 0 | G14: =F14-'현금흐름표(CF)'!G24-'판관비(SG&A)'!G12 -> 0 | H14: =G14-'현금흐름표(CF)'!H24-'판관비(SG&A)'!H12 -> 0 | I14: =H14-'현금흐름표(CF)'!I24-'판관비(SG&A)'!I12 -> 0 | J14: =I14-'현금흐름표(CF)'!J24-'판관비(SG&A)'!J12 -> 0 | K14: =J14-'현금흐름표(CF)'!K24-'판관비(SG&A)'!K12 -> 0 | L14: =K14-'현금흐름표(CF)'!L24-'판관비(SG&A)'!L12 -> 0 | M14: =L14-'현금흐름표(CF)'!M24-'판관비(SG&A)'!M12 -> 0 | N14: =M14-'현금흐름표(CF)'!N24-'판관비(SG&A)'!N12 -> 0 | ... AO14: =AN14-'현금흐름표(CF)'!AO24-'판관비(SG&A)'!AO12 -> 5983337 | AP14: =M14 -> 0 | AQ14: =Y14 -> 2750000 | AR14: =AK14 -> 6216669 | AS14: =AO14 -> 5983337 | AT14: (3)무형자산
A15: 임차보증금 | B15: 전월+지급 | F15: =0-'현금흐름표(CF)'!F25 -> 0 | G15: =F15-'현금흐름표(CF)'!G25 -> 0 | H15: =G15-'현금흐름표(CF)'!H25 -> 0 | I15: =H15-'현금흐름표(CF)'!I25 -> 0 | J15: =I15-'현금흐름표(CF)'!J25 -> 0 | K15: =J15-'현금흐름표(CF)'!K25 -> 0 | L15: =K15-'현금흐름표(CF)'!L25 -> 0 | M15: =L15-'현금흐름표(CF)'!M25 -> 0 | N15: =M15-'현금흐름표(CF)'!N25 -> 0 | ... AO15: =AN15-'현금흐름표(CF)'!AO25 -> 30000000 | AP15: =M15 -> 0 | AQ15: =Y15 -> 30000000 | AR15: =AK15 -> 30000000 | AS15: =AO15 -> 30000000 | AT15: (4)기타비유동자산
A16: 자산총계 | F16: =F6+F12 -> 5406951 | G16: =G6+G12 -> 3412471 | H16: =H6+H12 -> 1908191 | I16: =I6+I12 -> 1757083 | J16: =J6+J12 -> 638612 | K16: =K6+K12 -> 487198 | L16: =L6+L12 -> 198352731 | M16: =M6+M12 -> 199742022 | ... AO16: =AO6+AO12 -> 764890099 | AP16: =M16 -> 199742022 | AQ16: =Y16 -> 621287383 | AR16: =AK16 -> 703965931 | AS16: =AO16 -> 764890099 | AT16: 자산총계
A17: [부채]
A18: 유동부채 | F18: =SUM(F19:F26) -> 2500000 | G18: =SUM(G19:G26) -> 4120000 | H18: =SUM(H19:H26) -> 5650000 | I18: =SUM(I19:I26) -> 7180000 | J18: =SUM(J19:J26) -> 8300000 | K18: =SUM(K19:K26) -> 10670000 | L18: =SUM(L19:L26) -> 9900000 | M18: =SUM(M19:M26) -> 12768547 | ... AO18: =SUM(AO19:AO26) -> 185758237 | AP18: =M18 -> 12768547 | AQ18: =Y18 -> 64677956 | AR18: =AK18 -> 139975530 | AS18: =AO18 -> 185758237 | AT18: Ⅰ.유동부채
A19: 매입채무(외상매입금) | B19: 클라우드·LLM API 익월 청구분 | F19: 0 | G19: 0 | H19: 0 | I19: 0 | J19: 0 | K19: 0 | L19: 0 | M19: 56354 | N19: 1670725 | O19: 2259618 | P19: 3231709 | Q19: 3646249 | R19: 3791488 | S19: 4145909 | T19: 4483982 | U19: 5258618 | V19: 6282020 | W19: 6763728 | X19: 6793023 | Y19: 6765049 | Z19: 7486453 | AA19: 8424361 | AB19: 9845437 | AC19: 10496303 | AD19: 10392978 | AE19: 10387882 | AF19: 10790910 | AG19: 11955995 | AH19: 13204862 | AI19: 13592835 | AJ19: 13170527 | AK19: 12679792 | AL19: 13108911 | AM19: 14075965 | AN19: 14778132 | AO19: 15227127 | AP19: =M19 -> 56354 | AQ19: =Y19 -> 6765049 | AR19: =AK19 -> 12679792 | AS19: =AO19 -> 15227127 | AT19: 가.외상매입금
A20: 미지급금 | B20: 법인카드 등 익월 결제(비인건 비용의 55%) | F20: 2500000 | G20: 4000000 | H20: 5500000 | I20: 7000000 | J20: 8000000 | K20: 9000000 | L20: 9500000 | M20: 9988590 | N20: 3445200 | O20: 5139200 | P20: 6816480 | Q20: 9236269 | R20: 4398406 | S20: 4365928 | T20: 4703546 | U20: 5950886 | V20: 6587301 | W20: 8660221 | X20: 6210736 | Y20: 6062543 | Z20: 9493883 | AA20: 10937988 | AB20: 13647939 | AC20: 14348609 | AD20: 9833785 | AE20: 9614183 | AF20: 10015458 | AG20: 11927928 | AH20: 13756026 | AI20: 15674660 | AJ20: 10431855 | AK20: 9795038 | AL20: 11111306 | AM20: 12865737 | AN20: 16186407 | AO20: 17522554 | AP20: =M20 -> 9988590 | AQ20: =Y20 -> 6062543 | AR20: =AK20 -> 9795038 | AS20: =AO20 -> 17522554 | AT20: 다.기타미지급금
A21: 예수금(원천세·4대보험) | B21: 급여의 21.8%(근로자 원천분+회사부담 4대보험) 익월 납부 | F21: 0 | G21: 120000 | H21: 150000 | I21: 180000 | J21: 300000 | K21: 350000 | L21: 400000 | M21: 575420 | N21: 2354400 | O21: 2354400 | P21: 2354400 | Q21: 4142000 | R21: 4142000 | S21: 4142000 | T21: 5014000 | U21: 5014000 | V21: 5014000 | W21: 5014000 | X21: 5014000 | Y21: 5014000 | Z21: 5264700 | AA21: 5264700 | AB21: 6088740 | AC21: 6088740 | AD21: 6088740 | AE21: 6821220 | AF21: 6821220 | AG21: 6821220 | AH21: 7965720 | AI21: 7965720 | AJ21: 7965720 | AK21: 7965720 | AL21: 8364006 | AM21: 8364006 | AN21: 8364006 | AO21: 8364006 | AP21: =M21 -> 575420 | AQ21: =Y21 -> 5014000 | AR21: =AK21 -> 7965720 | AS21: =AO21 -> 8364006 | AT21: 라.기타예수금
A22: 셀러 정산 예수금 | B22: 당월 GMV-수수료, 익월 10일 정산(개인셀러 3.3% 원천징수 포함) | F22: 0 | G22: 0 | H22: 0 | I22: 0 | J22: 0 | K22: 0 | L22: 0 | M22: 0 | N22: 0 | O22: 0 | P22: 3360000 | Q22: 3225600 | R22: 4059504 | S22: 4077462 | T22: 5184177 | U22: 7813119 | V22: 11041026 | W22: 9987205 | X22: 8470712 | Y22: 7451793 | Z22: 10095831 | AA22: 13002840 | AB22: 17439288 | AC22: 15752385 | AD22: 12450339 | AE22: 11663033 | AF22: 13827897 | AG22: 19431050 | AH22: 25598646 | AI22: 21583756 | AJ22: 17061517 | AK22: 13986592 | AL22: 18522245 | AM22: 23317448 | AN22: 30567054 | AO22: 26986342 | AP22: =M22 -> 0 | AQ22: =Y22 -> 7451793 | AR22: =AK22 -> 13986592 | AS22: =AO22 -> 26986342 | AT22: 예수금
A23: 부가세예수금 | B23: 매출세액-매입세액, 분기 종료 익월 납부 | F23: 0 | G23: 0 | H23: 0 | I23: 0 | J23: 0 | K23: 0 | L23: 0 | M23: 0 | N23: 0 | O23: 286592 | P23: 2749325 | Q23: 482866 | R23: 1505806 | S23: 2736567 | T23: 1120894 | U23: 2784061 | V23: 6896243 | W23: 2768638 | X23: 4704124 | Y23: 5871359 | Z23: 2067799 | AA23: 4428931 | AB23: 13419584 | AC23: 4072500 | AD23: 7027711 | AE23: 10311376 | AF23: 3421071 | AG23: 7385679 | AH23: 16388007 | AI23: 5857732 | AJ23: 10150850 | AK23: 14516508 | AL23: 4670145 | AM23: 9668492 | AN23: 21167873 | AO23: 7354425 | AP23: =M23 -> 0 | AQ23: =Y23 -> 5871359 | AR23: =AK23 -> 14516508 | AS23: =AO23 -> 7354425 | AT23: 예수금(부가세)
A24: 선수수익(연간구독·크레딧) | B24: 연간구독 미경과분 + 크레딧 미사용분 | F24: 0 | G24: 0 | H24: 0 | I24: 0 | J24: 0 | K24: 0 | L24: 0 | M24: 0 | N24: 1509263 | O24: 3705075 | P24: 20137482 | Q24: 20927656 | R24: 20897487 | S24: 22015142 | T24: 21534809 | U24: 22160336 | V24: 37248286 | W24: 36195942 | X24: 33846125 | Y24: 33513212 | Z24: 32385649 | AA24: 32395352 | AB24: 88454748 | AC24: 84862532 | AD24: 78887890 | AE24: 76249852 | AF24: 70604054 | AG24: 67583962 | AH24: 101788404 | AI24: 95604923 | AJ24: 86705654 | AK24: 81031880 | AL24: 73503239 | AM24: 67964883 | AN24: 115231150 | AO24: 110303783 | AP24: =M24 -> 0 | AQ24: =Y24 -> 33513212 | AR24: =AK24 -> 81031880 | AS24: =AO24 -> 110303783 | AT24: 선수수익
A25: 선수금(컨퍼런스 사전판매) | B25: 행사 전월 판매분(티켓의 40%) | F25: 0 | G25: 0 | H25: 0 | I25: 0 | J25: 0 | K25: 1320000 | L25: 0 | M25: 0 | N25: 0 | O25: 0 | P25: 2500000 | Q25: 0 | R25: 0 | S25: 0 | T25: 0 | U25: 0 | V25: 3780000 | W25: 0 | X25: 0 | Y25: 0 | Z25: 0 | AA25: 0 | AB25: 5400000 | AC25: 0 | AD25: 0 | AE25: 0 | AF25: 0 | AG25: 0 | AH25: 6600000 | AI25: 0 | AJ25: 0 | AK25: 0 | AL25: 0 | AM25: 0 | AN25: 8320000 | AO25: 0 | AP25: =M25 -> 0 | AQ25: =Y25 -> 0 | AR25: =AK25 -> 0 | AS25: =AO25 -> 0 | AT25: 선수금
A26: 미지급법인세 | B26: 2025 신고서 잔액, 2026-03 납부 가정 | F26: 0 | G26: 0 | H26: 0 | I26: 0 | J26: 0 | K26: 0 | L26: 0 | M26: 2148183 | N26: 0 | O26: 0 | P26: 0 | Q26: 0 | R26: 0 | S26: 0 | T26: 0 | U26: 0 | V26: 0 | W26: 0 | X26: 0 | Y26: 0 | Z26: 0 | AA26: 0 | AB26: 0 | AC26: 0 | AD26: 0 | AE26: 0 | AF26: 0 | AG26: 0 | AH26: 0 | AI26: 0 | AJ26: 0 | AK26: 0 | AL26: 0 | AM26: 0 | AN26: 0 | AO26: 0 | AP26: =M26 -> 2148183 | AQ26: =Y26 -> 0 | AR26: =AK26 -> 0 | AS26: =AO26 -> 0 | AT26: 가.미지급법인세
A27: 비유동부채 | F27: =F28 -> 0 | G27: =G28 -> 0 | H27: =H28 -> 0 | I27: =I28 -> 0 | J27: =J28 -> 0 | K27: =K28 -> 0 | L27: =L28 -> 200000000 | M27: =M28 -> 200000000 | ... AO27: =AO28 -> 166666664 | AP27: =M27 -> 200000000 | AQ27: =Y27 -> 200000000 | AR27: =AK27 -> 188888888 | AS27: =AO27 -> 166666664 | AT27: Ⅱ.비유동부채
A28: 장기차입금 | B28: 전월+차입-상환 | F28: =0+'현금흐름표(CF)'!F27+'현금흐름표(CF)'!F28 -> 0 | G28: =F28+'현금흐름표(CF)'!G27+'현금흐름표(CF)'!G28 -> 0 | H28: =G28+'현금흐름표(CF)'!H27+'현금흐름표(CF)'!H28 -> 0 | I28: =H28+'현금흐름표(CF)'!I27+'현금흐름표(CF)'!I28 -> 0 | J28: =I28+'현금흐름표(CF)'!J27+'현금흐름표(CF)'!J28 -> 0 | K28: =J28+'현금흐름표(CF)'!K27+'현금흐름표(CF)'!K28 -> 0 | L28: =K28+'현금흐름표(CF)'!L27+'현금흐름표(CF)'!L28 -> 200000000 | M28: =L28+'현금흐름표(CF)'!M27+'현금흐름표(CF)'!M28 -> 200000000 | N28: =M28+'현금흐름표(CF)'!N27+'현금흐름표(CF)'!N28 -> 200000000 | ... AO28: =AN28+'현금흐름표(CF)'!AO27+'현금흐름표(CF)'!AO28 -> 166666664 | AP28: =M28 -> 200000000 | AQ28: =Y28 -> 200000000 | AR28: =AK28 -> 188888888 | AS28: =AO28 -> 166666664 | AT28: 다.기타장기차입금
A29: 부채총계 | F29: =F18+F27 -> 2500000 | G29: =G18+G27 -> 4120000 | H29: =H18+H27 -> 5650000 | I29: =I18+I27 -> 7180000 | J29: =J18+J27 -> 8300000 | K29: =K18+K27 -> 10670000 | L29: =L18+L27 -> 209900000 | M29: =M18+M27 -> 212768547 | ... AO29: =AO18+AO27 -> 352424901 | AP29: =M29 -> 212768547 | AQ29: =Y29 -> 264677956 | AR29: =AK29 -> 328864418 | AS29: =AO29 -> 352424901 | AT29: 부채총계
A30: [자본]
A31: 자본금 | F31: =0+'현금흐름표(CF)'!F29 -> 10000000 | G31: =F31+'현금흐름표(CF)'!G29 -> 10000000 | H31: =G31+'현금흐름표(CF)'!H29 -> 10000000 | I31: =H31+'현금흐름표(CF)'!I29 -> 10000000 | J31: =I31+'현금흐름표(CF)'!J29 -> 10000000 | K31: =J31+'현금흐름표(CF)'!K29 -> 10000000 | L31: =K31+'현금흐름표(CF)'!L29 -> 10000000 | M31: =L31+'현금흐름표(CF)'!M29 -> 10000000 | N31: =M31+'현금흐름표(CF)'!N29 -> 10000000 | ... AO31: =AN31+'현금흐름표(CF)'!AO29 -> 11250000 | AP31: =M31 -> 10000000 | AQ31: =Y31 -> 11250000 | AR31: =AK31 -> 11250000 | AS31: =AO31 -> 11250000 | AT31: 1.보통주자본금
A32: 주식발행초과금 | F32: =0+'현금흐름표(CF)'!F30 -> 0 | G32: =F32+'현금흐름표(CF)'!G30 -> 0 | H32: =G32+'현금흐름표(CF)'!H30 -> 0 | I32: =H32+'현금흐름표(CF)'!I30 -> 0 | J32: =I32+'현금흐름표(CF)'!J30 -> 0 | K32: =J32+'현금흐름표(CF)'!K30 -> 0 | L32: =K32+'현금흐름표(CF)'!L30 -> 0 | M32: =L32+'현금흐름표(CF)'!M30 -> 0 | N32: =M32+'현금흐름표(CF)'!N30 -> 0 | ... AO32: =AN32+'현금흐름표(CF)'!AO30 -> 498750000 | AP32: =M32 -> 0 | AQ32: =Y32 -> 498750000 | AR32: =AK32 -> 498750000 | AS32: =AO32 -> 498750000 | AT32: Ⅱ.자본잉여금
A33: 이익잉여금(결손금) | F33: =0+'손익계산서(P&L)'!F35 -> -7093049 | G33: =F33+'손익계산서(P&L)'!G35 -> -10707529 | H33: =G33+'손익계산서(P&L)'!H35 -> -13741809 | I33: =H33+'손익계산서(P&L)'!I35 -> -15422917 | J33: =I33+'손익계산서(P&L)'!J35 -> -17661388 | K33: =J33+'손익계산서(P&L)'!K35 -> -20182802 | L33: =K33+'손익계산서(P&L)'!L35 -> -21547269 | M33: =L33+'손익계산서(P&L)'!M35 -> -23026525 | N33: =M33+'손익계산서(P&L)'!N35 -> -38182244 | ... AO33: =AN33+'손익계산서(P&L)'!AO35 -> -97534802 | AP33: =M33 -> -23026525 | AQ33: =Y33 -> -153390573 | AR33: =AK33 -> -134898487 | AS33: =AO33 -> -97534802 | AT33: 5.미처분이익잉여금(미처리결손금)
A34: 자본총계 | F34: =SUM(F31:F33) -> 2906951 | G34: =SUM(G31:G33) -> -707529 | H34: =SUM(H31:H33) -> -3741809 | I34: =SUM(I31:I33) -> -5422917 | J34: =SUM(J31:J33) -> -7661388 | K34: =SUM(K31:K33) -> -10182802 | L34: =SUM(L31:L33) -> -11547269 | M34: =SUM(M31:M33) -> -13026525 | ... AO34: =SUM(AO31:AO33) -> 412465198 | AP34: =M34 -> -13026525 | AQ34: =Y34 -> 356609427 | AR34: =AK34 -> 375101513 | AS34: =AO34 -> 412465198 | AT34: 자본총계
A35: 부채와자본총계 | F35: =F29+F34 -> 5406951 | G35: =G29+G34 -> 3412471 | H35: =H29+H34 -> 1908191 | I35: =I29+I34 -> 1757083 | J35: =J29+J34 -> 638612 | K35: =K29+K34 -> 487198 | L35: =L29+L34 -> 198352731 | M35: =M29+M34 -> 199742022 | ... AO35: =AO29+AO34 -> 764890099 | AP35: =M35 -> 199742022 | AQ35: =Y35 -> 621287383 | AR35: =AK35 -> 703965931 | AS35: =AO35 -> 764890099 | AT35: 부채와 자본총계
A36: 검증: 자산총계 - 부채와자본총계 (0이어야 정상) | F36: =F16-F35 -> 0 | G36: =G16-G35 -> 0 | H36: =H16-H35 -> 0 | I36: =I16-I35 -> 0 | J36: =J16-J35 -> 0 | K36: =K16-K35 -> 0 | L36: =L16-L35 -> 0 | M36: =M16-M35 -> 0 | ... AO36: =AO16-AO35 -> 0 | AP36: =M36 -> 0 | AQ36: =Y36 -> 0 | AR36: =AK36 -> 0 | AS36: =AO36 -> 0

Sheet KPI(추가검토)
A1: KPI · 운영지표 (추가 검토 데이터)
A2: ※ 재무제표만으로는 보이지 않는 사업 드라이버. 파란색=운영 데이터 입력값(실무에서는 결제·회원 DB, PG 정산내역, 마켓 정산내역에서 추출), 검정/초록=다른 시트와 연결된 산식. 연간 열: 인원·구독자 등 잔량은 연말값, 금액은 합계, 비율은 연간 기준 재계산.
A3: 구분 | B3: 지표 | C3: 단위 | D3: 정의·데이터 출처 | F3: 2025-05-31 | G3: 2025-06-30 | H3: 2025-07-31 | I3: 2025-08-31 | J3: 2025-09-30 | K3: 2025-10-31 | L3: 2025-11-30 | M3: 2025-12-31 | N3: 2026-01-31 | O3: 2026-02-28 | P3: 2026-03-31 | Q3: 2026-04-30 | R3: 2026-05-31 | S3: 2026-06-30 | T3: 2026-07-31 | U3: 2026-08-31 | V3: 2026-09-30 | W3: 2026-10-31 | X3: 2026-11-30 | Y3: 2026-12-31 | Z3: 2027-01-31 | AA3: 2027-02-28 | AB3: 2027-03-31 | AC3: 2027-04-30 | AD3: 2027-05-31 | AE3: 2027-06-30 | AF3: 2027-07-31 | AG3: 2027-08-31 | AH3: 2027-09-30 | AI3: 2027-10-31 | AJ3: 2027-11-30 | AK3: 2027-12-31 | AL3: 2028-01-31 | AM3: 2028-02-29 | AN3: 2028-03-31 | AO3: 2028-04-30 | AP3: FY2025(5~12월) | AQ3: FY2026 | AR3: FY2027 | AS3: FY2028(1~4월) | AT3: 왜 필요한가(요약)
A4: ※ 데이터구분 | F4: 실적배분 | G4: 실적배분 | H4: 실적배분 | I4: 실적배분 | J4: 실적배분 | K4: 실적배분 | L4: 실적배분 | M4: 실적배분 | N4: 가상 | O4: 가상 | P4: 가상 | Q4: 가상 | R4: 가상 | S4: 가상 | T4: 가상 | U4: 가상 | V4: 가상 | W4: 가상 | X4: 가상 | Y4: 가상 | Z4: 가상 | AA4: 가상 | AB4: 가상 | AC4: 가상 | AD4: 가상 | AE4: 가상 | AF4: 가상 | AG4: 가상 | AH4: 가상 | AI4: 가상 | AJ4: 가상 | AK4: 가상 | AL4: 가상 | AM4: 가상 | AN4: 가상 | AO4: 가상 | AP4: 연간 집계 | AQ4: 연간 집계 | AR4: 연간 집계 | AS4: 연간 집계
A5: 인력 | B5: 개발조직 인원 | C5: 명 | D5: 인사기록 | F5: 0 | G5: 1 | H5: 1 | I5: 1 | J5: 1 | K5: 1 | L5: 1 | M5: 1 | N5: 2 | O5: 2 | P5: 2 | Q5: 3 | R5: 3 | S5: 3 | T5: 3 | U5: 3 | V5: 3 | W5: 3 | X5: 3 | Y5: 3 | Z5: 3 | AA5: 3 | AB5: 3 | AC5: 3 | AD5: 3 | AE5: 3 | AF5: 3 | AG5: 3 | AH5: 4 | AI5: 4 | AJ5: 4 | AK5: 4 | AL5: 4 | AM5: 4 | AN5: 4 | AO5: 4 | AP5: =M5 -> 1 | AQ5: =Y5 -> 3 | AR5: =AK5 -> 4 | AS5: =AO5 -> 4 | AT5: 인건비가 판관비의 최대 비중 → 인원 계획이 손익을 좌우
A6: 인력 | B6: 사업·마케팅조직 인원 | C6: 명 | D6: 인사기록 | F6: 0 | G6: 0 | H6: 0 | I6: 0 | J6: 0 | K6: 0 | L6: 0 | M6: 0 | N6: 0 | O6: 0 | P6: 0 | Q6: 1 | R6: 1 | S6: 1 | T6: 1 | U6: 1 | V6: 1 | W6: 1 | X6: 1 | Y6: 1 | Z6: 1 | AA6: 1 | AB6: 2 | AC6: 2 | AD6: 2 | AE6: 2 | AF6: 2 | AG6: 2 | AH6: 2 | AI6: 2 | AJ6: 2 | AK6: 2 | AL6: 2 | AM6: 2 | AN6: 2 | AO6: 2 | AP6: =M6 -> 0 | AQ6: =Y6 -> 1 | AR6: =AK6 -> 2 | AS6: =AO6 -> 2
A7: 인력 | B7: 경영지원·운영조직 인원 | C7: 명 | D7: 인사기록(대표 급여 2026-07~) | F7: 0 | G7: 0 | H7: 0 | I7: 0 | J7: 1 | K7: 1 | L7: 1 | M7: 1 | N7: 1 | O7: 1 | P7: 1 | Q7: 1 | R7: 1 | S7: 1 | T7: 2 | U7: 2 | V7: 2 | W7: 2 | X7: 2 | Y7: 2 | Z7: 2 | AA7: 2 | AB7: 2 | AC7: 2 | AD7: 2 | AE7: 3 | AF7: 3 | AG7: 3 | AH7: 3 | AI7: 3 | AJ7: 3 | AK7: 3 | AL7: 3 | AM7: 3 | AN7: 3 | AO7: 3 | AP7: =M7 -> 1 | AQ7: =Y7 -> 2 | AR7: =AK7 -> 3 | AS7: =AO7 -> 3
A8: 인력 | B8: 총 인원 | C8: 명 | F8: =SUM(F5:F7) -> 0 | G8: =SUM(G5:G7) -> 1 | H8: =SUM(H5:H7) -> 1 | I8: =SUM(I5:I7) -> 1 | J8: =SUM(J5:J7) -> 2 | K8: =SUM(K5:K7) -> 2 | L8: =SUM(L5:L7) -> 2 | M8: =SUM(M5:M7) -> 2 | ... AS8: =SUM(AS5:AS7) -> 9
A9: 인력 | B9: 인당 월 인건비(Labor Costs/인원) | C9: 원 | F9: =IF(F8=0,0,'판관비(SG&A)'!F33/F8) -> 0 | G9: =IF(G8=0,0,'판관비(SG&A)'!G33/G8) -> 3310693 | H9: =IF(H8=0,0,'판관비(SG&A)'!H33/H8) -> 3310693 | I9: =IF(I8=0,0,'판관비(SG&A)'!I33/I8) -> 3310693 | J9: =IF(J8=0,0,'판관비(SG&A)'!J33/J8) -> 2576822.5 | K9: =IF(K8=0,0,'판관비(SG&A)'!K33/K8) -> 2576822.5 | L9: =IF(L8=0,0,'판관비(SG&A)'!L33/L8) -> 2576822.5 | M9: =IF(M8=0,0,'판관비(SG&A)'!M33/M8) -> 2576819 | ... AO9: =IF(AO8=0,0,'판관비(SG&A)'!AO33/AO8) -> 5286024
A11: [a] SaaS | B11: 개인 Pro 월간 활성 구독자 | C11: 명 | D11: 결제 DB(월말 활성) | F11: 0 | G11: 0 | H11: 0 | I11: 0 | J11: 45 | K11: 78 | L11: 99 | M11: 112 | N11: 135 | O11: 167 | P11: 214 | Q11: 250 | R11: 269 | S11: 283 | T11: 307 | U11: 357 | V11: 434 | W11: 483 | X11: 506 | Y11: 512 | Z11: 557 | AA11: 625 | AB11: 727 | AC11: 796 | AD11: 821 | AE11: 833 | AF11: 861 | AG11: 934 | AH11: 1048 | AI11: 1109 | AJ11: 1120 | AK11: 1101 | AL11: 1122 | AM11: 1177 | AN11: 1284 | AO11: 1346 | AP11: =M11 -> 112 | AQ11: =Y11 -> 512 | AR11: =AK11 -> 1101 | AS11: =AO11 -> 1346 | AT11: 플랜·결제주기별 구독자 수가 매출의 원천 드라이버
A12: [a] SaaS | B12: 개인 Max 월간 활성 구독자 | C12: 명 | D12: 결제 DB | F12: 0 | G12: 0 | H12: 0 | I12: 0 | J12: 0 | K12: 12 | L12: 20 | M12: 26 | N12: 35 | O12: 46 | P12: 62 | Q12: 75 | R12: 83 | S12: 89 | T12: 99 | U12: 116 | V12: 141 | W12: 159 | X12: 168 | Y12: 173 | Z12: 188 | AA12: 209 | AB12: 241 | AC12: 264 | AD12: 274 | AE12: 280 | AF12: 290 | AG12: 314 | AH12: 350 | AI12: 371 | AJ12: 377 | AK12: 374 | AL12: 383 | AM12: 402 | AN12: 436 | AO12: 457 | AP12: =M12 -> 26 | AQ12: =Y12 -> 173 | AR12: =AK12 -> 374 | AS12: =AO12 -> 457
A13: [a] SaaS | B13: 개인 Pro 연간 유효 계약 | C13: 명 | D13: 결제 DB | F13: 0 | G13: 0 | H13: 0 | I13: 0 | J13: 0 | K13: 0 | L13: 0 | M13: 0 | N13: 5 | O13: 11 | P13: 19 | Q13: 27 | R13: 33 | S13: 40 | T13: 47 | U13: 59 | V13: 74 | W13: 87 | X13: 98 | Y13: 107 | Z13: 117 | AA13: 130 | AB13: 147 | AC13: 161 | AD13: 172 | AE13: 182 | AF13: 193 | AG13: 208 | AH13: 227 | AI13: 242 | AJ13: 253 | AK13: 262 | AL13: 272 | AM13: 285 | AN13: 301 | AO13: 314 | AP13: =M13 -> 0 | AQ13: =Y13 -> 107 | AR13: =AK13 -> 262 | AS13: =AO13 -> 314
A14: [a] SaaS | B14: 개인 Max 연간 유효 계약 | C14: 명 | D14: 결제 DB | F14: 0 | G14: 0 | H14: 0 | I14: 0 | J14: 0 | K14: 0 | L14: 0 | M14: 0 | N14: 2 | O14: 5 | P14: 10 | Q14: 14 | R14: 17 | S14: 20 | T14: 24 | U14: 29 | V14: 37 | W14: 43 | X14: 49 | Y14: 53 | Z14: 59 | AA14: 65 | AB14: 73 | AC14: 81 | AD14: 86 | AE14: 91 | AF14: 97 | AG14: 104 | AH14: 113 | AI14: 121 | AJ14: 127 | AK14: 131 | AL14: 136 | AM14: 142 | AN14: 150 | AO14: 157 | AP14: =M14 -> 0 | AQ14: =Y14 -> 53 | AR14: =AK14 -> 131 | AS14: =AO14 -> 157
A15: [a] SaaS | B15: 개인 유료 구독자 합계 | C15: 명 | F15: =SUM(F11:F14) -> 0 | G15: =SUM(G11:G14) -> 0 | H15: =SUM(H11:H14) -> 0 | I15: =SUM(I11:I14) -> 0 | J15: =SUM(J11:J14) -> 45 | K15: =SUM(K11:K14) -> 90 | L15: =SUM(L11:L14) -> 119 | M15: =SUM(M11:M14) -> 138 | ... AO15: =SUM(AO11:AO14) -> 2274 | AP15: =M15 -> 138 | AQ15: =Y15 -> 845 | AR15: =AK15 -> 1868 | AS15: =AO15 -> 2274
A16: [a] SaaS | B16: 개인 신규 유료 구독자 | C16: 명 | D16: 결제 DB(신규 결제) | F16: 0 | G16: 0 | H16: 0 | I16: 0 | J16: 45 | K16: 51 | L16: 42 | M16: 35 | N16: 56 | O16: 75 | P16: 104 | Q16: 97 | R16: 80 | S16: 77 | T16: 95 | U16: 137 | V16: 187 | W16: 163 | X16: 134 | Y16: 113 | Z16: 159 | AA16: 200 | AB16: 262 | AC16: 231 | AD16: 179 | AE16: 163 | AF16: 189 | AG16: 260 | AH16: 335 | AI16: 276 | AJ16: 213 | AK16: 171 | AL16: 226 | AM16: 282 | AN16: 366 | AO16: 320 | AP16: =SUM(F16:M16) -> 173 | AQ16: =SUM(N16:Y16) -> 1318 | AR16: =SUM(Z16:AK16) -> 2638 | AS16: =SUM(AL16:AO16) -> 1194 | AT16: CAC 계산 분모
A17: [a] SaaS | B17: 월간 플랜 해지 구독자 | C17: 명 | D17: 결제 DB(해지·갱신실패) | F17: 0 | G17: 0 | H17: 0 | I17: 0 | J17: 0 | K17: 6 | L17: 12 | M17: 16 | N17: 19 | O17: 23 | P17: 28 | Q17: 37 | R17: 43 | S17: 47 | T17: 49 | U17: 54 | V17: 63 | W17: 76 | X17: 85 | Y17: 89 | Z17: 79 | AA17: 86 | AB17: 96 | AC17: 111 | AD17: 122 | AE17: 126 | AF17: 128 | AG17: 132 | AH17: 143 | AI17: 161 | AJ17: 170 | AK17: 172 | AL17: 170 | AM17: 173 | AN17: 181 | AO17: 198 | AP17: =SUM(F17:M17) -> 34 | AQ17: =SUM(N17:Y17) -> 613 | AR17: =SUM(Z17:AK17) -> 1526 | AS17: =SUM(AL17:AO17) -> 722 | AT17: 취업 성공 시 해지되는 구조라 해지율이 높고 계절성이 큼
A18: [a] SaaS | B18: 월간 플랜 해지율 | C18: % | F18: =0 -> 0 | G18: =IF((F11+F12)=0,0,G17/(F11+F12)) -> 0 | H18: =IF((G11+G12)=0,0,H17/(G11+G12)) -> 0 | I18: =IF((H11+H12)=0,0,I17/(H11+H12)) -> 0 | J18: =IF((I11+I12)=0,0,J17/(I11+I12)) -> 0 | K18: =IF((J11+J12)=0,0,K17/(J11+J12)) -> 0.13333333 | L18: =IF((K11+K12)=0,0,L17/(K11+K12)) -> 0.13333333 | M18: =IF((L11+L12)=0,0,M17/(L11+L12)) -> 0.13445378 | N18: =IF((M11+M12)=0,0,N17/(M11+M12)) -> 0.13768116 | ... AO18: =IF((AN11+AN12)=0,0,AO17/(AN11+AN12)) -> 0.11511628
A19: [a] SaaS | B19: 법인 Pro 연간 좌석 | C19: 석 | D19: 법인 계약서 | F19: 0 | G19: 0 | H19: 0 | I19: 0 | J19: 0 | K19: 0 | L19: 0 | M19: 0 | N19: 0 | O19: 0 | P19: 100 | Q19: 100 | R19: 100 | S19: 100 | T19: 100 | U19: 100 | V19: 180 | W19: 180 | X19: 180 | Y19: 180 | Z19: 180 | AA19: 180 | AB19: 360 | AC19: 360 | AD19: 360 | AE19: 360 | AF19: 360 | AG19: 360 | AH19: 494 | AI19: 494 | AJ19: 494 | AK19: 494 | AL19: 494 | AM19: 494 | AN19: 438 | AO19: 438 | AP19: =M19 -> 0 | AQ19: =Y19 -> 180 | AR19: =AK19 -> 494 | AS19: =AO19 -> 438 | AT19: 대학·기관 계약은 금액이 크고 회수기간이 길어 매출채권 관리 필요
A20: [a] SaaS | B20: 법인 Max 연간 좌석 | C20: 석 | D20: 법인 계약서 | F20: 0 | G20: 0 | H20: 0 | I20: 0 | J20: 0 | K20: 0 | L20: 0 | M20: 0 | N20: 0 | O20: 0 | P20: 0 | Q20: 0 | R20: 0 | S20: 0 | T20: 0 | U20: 0 | V20: 0 | W20: 0 | X20: 0 | Y20: 0 | Z20: 0 | AA20: 0 | AB20: 40 | AC20: 40 | AD20: 40 | AE20: 40 | AF20: 40 | AG20: 40 | AH20: 40 | AI20: 40 | AJ20: 40 | AK20: 40 | AL20: 40 | AM20: 40 | AN20: 32 | AO20: 32 | AP20: =M20 -> 0 | AQ20: =Y20 -> 0 | AR20: =AK20 -> 40 | AS20: =AO20 -> 32
A21: [a] SaaS | B21: 법인 Pro 월간 좌석 | C21: 석 | D21: 세금계산서 발행내역 | F21: 0 | G21: 0 | H21: 0 | I21: 0 | J21: 0 | K21: 0 | L21: 0 | M21: 0 | N21: 0 | O21: 0 | P21: 0 | Q21: 0 | R21: 10 | S21: 13 | T21: 16 | U21: 19 | V21: 22 | W21: 25 | X21: 28 | Y21: 31 | Z21: 34 | AA21: 37 | AB21: 40 | AC21: 43 | AD21: 46 | AE21: 49 | AF21: 52 | AG21: 55 | AH21: 58 | AI21: 60 | AJ21: 60 | AK21: 60 | AL21: 60 | AM21: 60 | AN21: 60 | AO21: 60 | AP21: =M21 -> 0 | AQ21: =Y21 -> 31 | AR21: =AK21 -> 60 | AS21: =AO21 -> 60
A22: [a] SaaS | B22: 법인 Max 월간 좌석 | C22: 석 | D22: 세금계산서 발행내역 | F22: 0 | G22: 0 | H22: 0 | I22: 0 | J22: 0 | K22: 0 | L22: 0 | M22: 0 | N22: 0 | O22: 0 | P22: 0 | Q22: 0 | R22: 0 | S22: 0 | T22: 0 | U22: 5 | V22: 6 | W22: 7 | X22: 8 | Y22: 9 | Z22: 10 | AA22: 11 | AB22: 12 | AC22: 13 | AD22: 14 | AE22: 15 | AF22: 16 | AG22: 17 | AH22: 18 | AI22: 19 | AJ22: 20 | AK22: 20 | AL22: 20 | AM22: 20 | AN22: 20 | AO22: 20 | AP22: =M22 -> 0 | AQ22: =Y22 -> 9 | AR22: =AK22 -> 20 | AS22: =AO22 -> 20
A23: [a] SaaS | B23: 무료 이용자 MAU | C23: 명 | D23: 서비스 로그 | F23: 0 | G23: 0 | H23: 0 | I23: 0 | J23: 315 | K23: 630 | L23: 833 | M23: 966 | N23: 1239 | O23: 1603 | P23: 2135 | Q23: 2562 | R23: 2814 | S23: 3024 | T23: 3339 | U23: 3927 | V23: 4802 | W23: 5404 | X23: 5747 | Y23: 5915 | Z23: 6447 | AA23: 7203 | AB23: 8316 | AC23: 9114 | AD23: 9471 | AE23: 9702 | AF23: 10087 | AG23: 10920 | AH23: 12166 | AI23: 12901 | AJ23: 13139 | AK23: 13076 | AL23: 13391 | AM23: 14042 | AN23: 15197 | AO23: 15918 | AP23: =M23 -> 966 | AQ23: =Y23 -> 5915 | AR23: =AK23 -> 13076 | AS23: =AO23 -> 15918 | AT23: 무료 이용자도 LLM 토큰비를 발생시키는 원가 드라이버
A24: [a] SaaS | B24: MRR(구독 매출, 크레딧 제외) | C24: 원 | F24: =SUM('매출(Revenue)'!F5:F12) -> 0 | G24: =SUM('매출(Revenue)'!G5:G12) -> 0 | H24: =SUM('매출(Revenue)'!H5:H12) -> 0 | I24: =SUM('매출(Revenue)'!I5:I12) -> 0 | J24: =SUM('매출(Revenue)'!J5:J12) -> 810000 | K24: =SUM('매출(Revenue)'!K5:K12) -> 1836000 | L24: =SUM('매출(Revenue)'!L5:L12) -> 2502000 | M24: =SUM('매출(Revenue)'!M5:M12) -> 2952000 | ... AO24: =SUM('매출(Revenue)'!AO5:AO12) -> 57975000 | AP24: =M24 -> 2952000 | AQ24: =Y24 -> 21673000 | AR24: =AK24 -> 49917000 | AS24: =AO24 -> 57975000 | AT24: 반복매출 규모(투자자 핵심 지표)
A25: [a] SaaS | B25: ARR(MRR×12) | C25: 원 | F25: =F24*12 -> 0 | G25: =G24*12 -> 0 | H25: =H24*12 -> 0 | I25: =I24*12 -> 0 | J25: =J24*12 -> 9720000 | K25: =K24*12 -> 22032000 | L25: =L24*12 -> 30024000 | M25: =M24*12 -> 35424000 | ... AO25: =AO24*12 -> 695700000 | AP25: =M25 -> 35424000 | AQ25: =Y25 -> 260076000 | AR25: =AK25 -> 599004000 | AS25: =AO25 -> 695700000
A26: [a] SaaS | B26: 개인 ARPPU(개인 구독매출/개인 유료구독자) | C26: 원 | F26: =IF(F15=0,0,('매출(Revenue)'!F5+'매출(Revenue)'!F7+'매출(Revenue)'!F9+'매출(Revenue)'!F11)/F15) -> 0 | G26: =IF(G15=0,0,('매출(Revenue)'!G5+'매출(Revenue)'!G7+'매출(Revenue)'!G9+'매출(Revenue)'!G11)/G15) -> 0 | H26: =IF(H15=0,0,('매출(Revenue)'!H5+'매출(Revenue)'!H7+'매출(Revenue)'!H9+'매출(Revenue)'!H11)/H15) -> 0 | I26: =IF(I15=0,0,('매출(Revenue)'!I5+'매출(Revenue)'!I7+'매출(Revenue)'!I9+'매출(Revenue)'!I11)/I15) -> 0 | J26: =IF(J15=0,0,('매출(Revenue)'!J5+'매출(Revenue)'!J7+'매출(Revenue)'!J9+'매출(Revenue)'!J11)/J15) -> 18000 | K26: =IF(K15=0,0,('매출(Revenue)'!K5+'매출(Revenue)'!K7+'매출(Revenue)'!K9+'매출(Revenue)'!K11)/K15) -> 20400 | L26: =IF(L15=0,0,('매출(Revenue)'!L5+'매출(Revenue)'!L7+'매출(Revenue)'!L9+'매출(Revenue)'!L11)/L15) -> 21025.21 | M26: =IF(M15=0,0,('매출(Revenue)'!M5+'매출(Revenue)'!M7+'매출(Revenue)'!M9+'매출(Revenue)'!M11)/M15) -> 21391.304 | ... AO26: =IF(AO15=0,0,('매출(Revenue)'!AO5+'매출(Revenue)'!AO7+'매출(Revenue)'!AO9+'매출(Revenue)'!AO11)/AO15) -> 22031.662 | AP26: =M26 -> 21391.304 | AQ26: =Y26 -> 22057.988 | AR26: =AK26 -> 22024.625 | AS26: =AO26 -> 22031.662
A27: [a] SaaS | B27: 연간구독 결제액(개인, VAT 별도) | C27: 원 | D27: PG 결제내역 | F27: 0 | G27: 0 | H27: 0 | I27: 0 | J27: 0 | K27: 0 | L27: 0 | M27: 0 | N27: 1646468.8 | O27: 2193462.3 | P27: 3042930.4 | Q27: 2842966.4 | R27: 2324125.1 | S27: 2251819 | T27: 2761293 | U27: 4013079.1 | V27: 5467820.3 | W27: 4767939.3 | X27: 3897790.4 | Y27: 3304460.1 | Z27: 5371875.7 | AA27: 6816928.1 | AB27: 9011748.4 | AC27: 8026508.6 | AD27: 6258047.9 | AE27: 5785369.6 | AF27: 6772196 | AG27: 9399889 | AH27: 12237799 | AI27: 10202051 | AJ27: 7977635.1 | AK27: 6472825.7 | AL27: 9019992.5 | AM27: 11298919 | AN27: 14741013 | AO27: 12954307 | AP27: =SUM(F27:M27) -> 0 | AQ27: =SUM(N27:Y27) -> 38514154 | AR27: =SUM(Z27:AK27) -> 94332874 | AS27: =SUM(AL27:AO27) -> 48014232 | AT27: 현금 유입과 매출 인식 시점이 달라 선수수익 발생
A28: [a] SaaS | B28: 법인 연간계약 청구액(VAT 별도) | C28: 원 | D28: 세금계산서 발행내역 | F28: 0 | G28: 0 | H28: 0 | I28: 0 | J28: 0 | K28: 0 | L28: 0 | M28: 0 | N28: 0 | O28: 0 | P28: 15000000 | Q28: 0 | R28: 0 | S28: 0 | T28: 0 | U28: 0 | V28: 12000000 | W28: 0 | X28: 0 | Y28: 0 | Z28: 0 | AA28: 0 | AB28: 54000000 | AC28: 0 | AD28: 0 | AE28: 0 | AF28: 0 | AG28: 0 | AH28: 32100000 | AI28: 0 | AJ28: 0 | AK28: 0 | AL28: 0 | AM28: 0 | AN28: 43200000 | AO28: 0 | AP28: =SUM(F28:M28) -> 0 | AQ28: =SUM(N28:Y28) -> 27000000 | AR28: =SUM(Z28:AK28) -> 86100000 | AS28: =SUM(AL28:AO28) -> 43200000
A29: [a] SaaS | B29: 크레딧 결제액(개인+법인, VAT 별도) | C29: 원 | D29: PG 결제내역 | F29: 0 | G29: 0 | H29: 0 | I29: 0 | J29: 0 | K29: 0 | L29: 0 | M29: 0 | N29: 0 | O29: 1074480 | P29: 1784640 | Q29: 1810285.7 | R29: 1476514.3 | S29: 3390902.9 | T29: 1714114.3 | U29: 2665645.7 | V29: 6550514.3 | W29: 3625097.1 | X29: 2857988.6 | Y29: 5265120 | Z29: 3166868.6 | AA29: 4326960 | AB29: 9883520 | AC29: 5992045.7 | AD29: 4646777.1 | AE29: 8202880 | AF29: 4891165.7 | AG29: 7069165.7 | AH29: 14388686 | AI29: 8377097.1 | AJ29: 6360891.4 | AK29: 9881360 | AL29: 6408411.4 | AM29: 8218320 | AN29: 16883680 | AO29: 10228114 | AP29: =SUM(F29:M29) -> 0 | AQ29: =SUM(N29:Y29) -> 32215303 | AR29: =SUM(Z29:AK29) -> 87187417 | AS29: =SUM(AL29:AO29) -> 41738526 | AT29: 미사용 크레딧 = 부채(선수수익), 소멸 정책이 매출에 영향
A30: [a] SaaS | B30: 크레딧 매출 인식액 | C30: 원 | F30: ='매출(Revenue)'!F13+'매출(Revenue)'!F14 -> 0 | G30: ='매출(Revenue)'!G13+'매출(Revenue)'!G14 -> 0 | H30: ='매출(Revenue)'!H13+'매출(Revenue)'!H14 -> 0 | I30: ='매출(Revenue)'!I13+'매출(Revenue)'!I14 -> 0 | J30: ='매출(Revenue)'!J13+'매출(Revenue)'!J14 -> 0 | K30: ='매출(Revenue)'!K13+'매출(Revenue)'!K14 -> 0 | L30: ='매출(Revenue)'!L13+'매출(Revenue)'!L14 -> 0 | M30: ='매출(Revenue)'!M13+'매출(Revenue)'!M14 -> 0 | ... AO30: ='매출(Revenue)'!AO13+'매출(Revenue)'!AO14 -> 12408117 | AP30: =SUM(F30:M30) -> 0 | AQ30: =SUM(N30:Y30) -> 29535767 | AR30: =SUM(Z30:AK30) -> 85069213 | AS30: =SUM(AL30:AO30) -> 41634499
A31: [a] SaaS | B31: LLM 토큰비용률(LLM비/[a]매출) | C31: % | F31: =IF('손익계산서(P&L)'!F6=0,0,'매출원가(COGS)'!F6/'손익계산서(P&L)'!F6) -> 0 | G31: =IF('손익계산서(P&L)'!G6=0,0,'매출원가(COGS)'!G6/'손익계산서(P&L)'!G6) -> 0 | H31: =IF('손익계산서(P&L)'!H6=0,0,'매출원가(COGS)'!H6/'손익계산서(P&L)'!H6) -> 0 | I31: =IF('손익계산서(P&L)'!I6=0,0,'매출원가(COGS)'!I6/'손익계산서(P&L)'!I6) -> 0 | J31: =IF('손익계산서(P&L)'!J6=0,0,'매출원가(COGS)'!J6/'손익계산서(P&L)'!J6) -> 0.21388889 | K31: =IF('손익계산서(P&L)'!K6=0,0,'매출원가(COGS)'!K6/'손익계산서(P&L)'!K6) -> 0.21617647 | L31: =IF('손익계산서(P&L)'!L6=0,0,'매출원가(COGS)'!L6/'손익계산서(P&L)'!L6) -> 0.21668665 | M31: =IF('손익계산서(P&L)'!M6=0,0,'매출원가(COGS)'!M6/'손익계산서(P&L)'!M6) -> 0.21697154 | ... AS31: =IF('손익계산서(P&L)'!AS6=0,0,'매출원가(COGS)'!AS6/'손익계산서(P&L)'!AS6) -> 0.16726015 | AT31: AI SaaS 매출총이익률을 결정하는 핵심 원가
A32: [a] SaaS | B32: CAC(광고비[a]/개인 신규 유료) | C32: 원 | F32: =IF(F16=0,0,'판관비(SG&A)'!F16/F16) -> 0 | G32: =IF(G16=0,0,'판관비(SG&A)'!G16/G16) -> 0 | H32: =IF(H16=0,0,'판관비(SG&A)'!H16/H16) -> 0 | I32: =IF(I16=0,0,'판관비(SG&A)'!I16/I16) -> 0 | J32: =IF(J16=0,0,'판관비(SG&A)'!J16/J16) -> 17777.778 | K32: =IF(K16=0,0,'판관비(SG&A)'!K16/K16) -> 17647.059 | L32: =IF(L16=0,0,'판관비(SG&A)'!L16/L16) -> 16666.667 | M32: =IF(M16=0,0,'판관비(SG&A)'!M16/M16) -> 17142.857 | ... AS32: =IF(AS16=0,0,'판관비(SG&A)'!AS16/AS16) -> 26000 | AT32: 광고선전비 효율, LTV/CAC 계산 기초
A33: [a] SaaS | B33: 반복매출 비중(성격='반복*') | C33: % | F33: =IF('손익계산서(P&L)'!F5=0,0,SUMIF('매출(Revenue)'!$E$5:$E$22,"반복*",'매출(Revenue)'!F5:F22)/'손익계산서(P&L)'!F5) -> 0 | G33: =IF('손익계산서(P&L)'!G5=0,0,SUMIF('매출(Revenue)'!$E$5:$E$22,"반복*",'매출(Revenue)'!G5:G22)/'손익계산서(P&L)'!G5) -> 0 | H33: =IF('손익계산서(P&L)'!H5=0,0,SUMIF('매출(Revenue)'!$E$5:$E$22,"반복*",'매출(Revenue)'!H5:H22)/'손익계산서(P&L)'!H5) -> 0 | I33: =IF('손익계산서(P&L)'!I5=0,0,SUMIF('매출(Revenue)'!$E$5:$E$22,"반복*",'매출(Revenue)'!I5:I22)/'손익계산서(P&L)'!I5) -> 0 | J33: =IF('손익계산서(P&L)'!J5=0,0,SUMIF('매출(Revenue)'!$E$5:$E$22,"반복*",'매출(Revenue)'!J5:J22)/'손익계산서(P&L)'!J5) -> 0.16167665 | K33: =IF('손익계산서(P&L)'!K5=0,0,SUMIF('매출(Revenue)'!$E$5:$E$22,"반복*",'매출(Revenue)'!K5:K22)/'손익계산서(P&L)'!K5) -> 0.32008368 | L33: =IF('손익계산서(P&L)'!L5=0,0,SUMIF('매출(Revenue)'!$E$5:$E$22,"반복*",'매출(Revenue)'!L5:L22)/'손익계산서(P&L)'!L5) -> 0.27189741 | M33: =IF('손익계산서(P&L)'!M5=0,0,SUMIF('매출(Revenue)'!$E$5:$E$22,"반복*",'매출(Revenue)'!M5:M22)/'손익계산서(P&L)'!M5) -> 0.45910683 | ... AS33: =IF('손익계산서(P&L)'!AS5=0,0,SUMIF('매출(Revenue)'!$E$5:$E$22,"반복*",'매출(Revenue)'!AS5:AS22)/'손익계산서(P&L)'!AS5) -> 0.63892042
A35: [b] 마켓 | B35: 전자책 GMV(거래액, VAT 포함 판매가) | C35: 원 | D35: 마켓 주문·정산 DB | F35: 0 | G35: 0 | H35: 0 | I35: 0 | J35: 0 | K35: 0 | L35: 0 | M35: 0 | N35: 0 | O35: 0 | P35: 4200000 | Q35: 4032000 | R35: 3386880 | S35: 3371827.2 | T35: 4248502.3 | U35: 6344430.1 | V35: 8882202.1 | W35: 7958453.1 | X35: 6685100.6 | Y35: 5823465.4 | Z35: 7861678.3 | AA35: 10089154 | AB35: 13482778 | AC35: 12134500 | AD35: 9555919.1 | AE35: 8918857.8 | AF35: 10535401 | AG35: 14749561 | AH35: 19358799 | AI35: 16261391 | AJ35: 12805846 | AK35: 10458107 | AL35: 13849522 | AM35: 17435009 | AN35: 22855712 | AO35: 20178329 | AP35: =SUM(F35:M35) -> 0 | AQ35: =SUM(N35:Y35) -> 54932861 | AR35: =SUM(Z35:AK35) -> 1.4621199e+08 | AS35: =SUM(AL35:AO35) -> 74318572 | AT35: 순액 매출(수수료)만으로는 거래 규모·정산 부채를 알 수 없음
A36: [b] 마켓 | B36: 강의 GMV | C36: 원 | D36: 마켓 주문·정산 DB | F36: 0 | G36: 0 | H36: 0 | I36: 0 | J36: 0 | K36: 0 | L36: 0 | M36: 0 | N36: 0 | O36: 0 | P36: 0 | Q36: 0 | R36: 1800000 | S36: 1840000 | T36: 2380500 | U36: 3650100 | V36: 5247018.8 | W36: 4827257.2 | X36: 4163509.4 | Y36: 3724027.8 | Z36: 5075317.9 | AA36: 6575356.3 | AB36: 8870753.5 | AC36: 8059713.1 | AD36: 6407472 | AE36: 6037262.5 | AF36: 7199435.5 | AG36: 10175202 | AH36: 13482143 | AI36: 11432857 | AJ36: 9089121.4 | AK36: 7493475.7 | AL36: 9923502.8 | AM36: 12492587 | AN36: 16376646 | AO36: 14458239 | AP36: =SUM(F36:M36) -> 0 | AQ36: =SUM(N36:Y36) -> 27632413 | AR36: =SUM(Z36:AK36) -> 99898110 | AS36: =SUM(AL36:AO36) -> 53250976
A37: [b] 마켓 | B37: GMV 합계 | C37: 원 | F37: =F35+F36 -> 0 | G37: =G35+G36 -> 0 | H37: =H35+H36 -> 0 | I37: =I35+I36 -> 0 | J37: =J35+J36 -> 0 | K37: =K35+K36 -> 0 | L37: =L35+L36 -> 0 | M37: =M35+M36 -> 0 | ... AS37: =AS35+AS36 -> 1.2756955e+08
A38: [b] 마켓 | B38: 실효 수수료율(Take rate) | C38: % | F38: =IF(F37=0,0,'손익계산서(P&L)'!F7/F37) -> 0 | G38: =IF(G37=0,0,'손익계산서(P&L)'!G7/G37) -> 0 | H38: =IF(H37=0,0,'손익계산서(P&L)'!H7/H37) -> 0 | I38: =IF(I37=0,0,'손익계산서(P&L)'!I7/I37) -> 0 | J38: =IF(J37=0,0,'손익계산서(P&L)'!J7/J37) -> 0 | K38: =IF(K37=0,0,'손익계산서(P&L)'!K7/K37) -> 0 | L38: =IF(L37=0,0,'손익계산서(P&L)'!L7/L37) -> 0 | M38: =IF(M37=0,0,'손익계산서(P&L)'!M7/M37) -> 0 | ... AS38: =IF(AS37=0,0,'손익계산서(P&L)'!AS7/AS37) -> 0.22087136
A39: [b] 마켓 | B39: 판매자 정산액(GMV-수수료) | C39: 원 | F39: =F37-'손익계산서(P&L)'!F7 -> 0 | G39: =G37-'손익계산서(P&L)'!G7 -> 0 | H39: =H37-'손익계산서(P&L)'!H7 -> 0 | I39: =I37-'손익계산서(P&L)'!I7 -> 0 | J39: =J37-'손익계산서(P&L)'!J7 -> 0 | K39: =K37-'손익계산서(P&L)'!K7 -> 0 | L39: =L37-'손익계산서(P&L)'!L7 -> 0 | M39: =M37-'손익계산서(P&L)'!M7 -> 0 | ... AS39: =AS37-'손익계산서(P&L)'!AS7 -> 99393089 | AT39: 셀러 정산 예수금·원천징수(개인셀러 3.3%) 관리
A40: [b] 마켓 | B40: 활성 판매자(개인) | C40: 명 | D40: 판매자 DB | F40: 0 | G40: 0 | H40: 0 | I40: 0 | J40: 0 | K40: 0 | L40: 0 | M40: 0 | N40: 0 | O40: 0 | P40: 25 | Q40: 25 | R40: 27 | S40: 27 | T40: 30 | U40: 38 | V40: 47 | W40: 44 | X40: 39 | Y40: 36 | Z40: 43 | AA40: 51 | AB40: 62 | AC40: 57 | AD40: 48 | AE40: 46 | AF40: 51 | AG40: 65 | AH40: 80 | AI40: 69 | AJ40: 57 | AK40: 49 | AL40: 60 | AM40: 70 | AN40: 87 | AO40: 77 | AP40: =M40 -> 0 | AQ40: =Y40 -> 36 | AR40: =AK40 -> 49 | AS40: =AO40 -> 77 | AT40: 개인/사업자 셀러는 원천징수·세금계산서 처리 방식이 다름
A41: [b] 마켓 | B41: 활성 판매자(사업자) | C41: 명 | D41: 판매자 DB | F41: 0 | G41: 0 | H41: 0 | I41: 0 | J41: 0 | K41: 0 | L41: 0 | M41: 0 | N41: 0 | O41: 0 | P41: 8 | Q41: 8 | R41: 9 | S41: 9 | T41: 10 | U41: 12 | V41: 15 | W41: 14 | X41: 13 | Y41: 12 | Z41: 15 | AA41: 18 | AB41: 23 | AC41: 21 | AD41: 18 | AE41: 17 | AF41: 20 | AG41: 26 | AH41: 33 | AI41: 29 | AJ41: 24 | AK41: 21 | AL41: 26 | AM41: 32 | AN41: 41 | AO41: 37 | AP41: =M41 -> 0 | AQ41: =Y41 -> 12 | AR41: =AK41 -> 21 | AS41: =AO41 -> 37
A43: [c] 컨퍼런스 | B43: 개인 티켓 판매 수 | C43: 명 | D43: 티켓 판매내역 | F43: 0 | G43: 0 | H43: 0 | I43: 0 | J43: 0 | K43: 0 | L43: 150 | M43: 0 | N43: 0 | O43: 0 | P43: 0 | Q43: 250 | R43: 0 | S43: 0 | T43: 0 | U43: 0 | V43: 0 | W43: 350 | X43: 0 | Y43: 0 | Z43: 0 | AA43: 0 | AB43: 0 | AC43: 450 | AD43: 0 | AE43: 0 | AF43: 0 | AG43: 0 | AH43: 0 | AI43: 550 | AJ43: 0 | AK43: 0 | AL43: 0 | AM43: 0 | AN43: 0 | AO43: 650 | AP43: =SUM(F43:M43) -> 150 | AQ43: =SUM(N43:Y43) -> 600 | AR43: =SUM(Z43:AK43) -> 1000 | AS43: =SUM(AL43:AO43) -> 650 | AT43: 행사 1회당 손익(티켓-대관·시설·광고) 판단
A44: [c] 컨퍼런스 | B44: 개인 티켓 객단가 | C44: 원 | F44: =IF(F43=0,0,'매출(Revenue)'!F21/F43) -> 0 | G44: =IF(G43=0,0,'매출(Revenue)'!G21/G43) -> 0 | H44: =IF(H43=0,0,'매출(Revenue)'!H21/H43) -> 0 | I44: =IF(I43=0,0,'매출(Revenue)'!I21/I43) -> 0 | J44: =IF(J43=0,0,'매출(Revenue)'!J21/J43) -> 0 | K44: =IF(K43=0,0,'매출(Revenue)'!K21/K43) -> 0 | L44: =IF(L43=0,0,'매출(Revenue)'!L21/L43) -> 22000 | M44: =IF(M43=0,0,'매출(Revenue)'!M21/M43) -> 0 | ... AS44: =IF(AS43=0,0,'매출(Revenue)'!AS21/AS43) -> 32000
A46: 현금 | B46: 기말 현금 | C46: 원 | F46: ='현금흐름표(CF)'!F33 -> 5406951 | G46: ='현금흐름표(CF)'!G33 -> 3412471 | H46: ='현금흐름표(CF)'!H33 -> 1908191 | I46: ='현금흐름표(CF)'!I33 -> 1757083 | J46: ='현금흐름표(CF)'!J33 -> 638612 | K46: ='현금흐름표(CF)'!K33 -> 487198 | L46: ='현금흐름표(CF)'!L33 -> 197852731 | M46: ='현금흐름표(CF)'!M33 -> 198790542 | ... AO46: ='현금흐름표(CF)'!AO33 -> 632197109 | AP46: =M46 -> 198790542 | AQ46: =Y46 -> 559993834 | AR46: =AK46 -> 630739776 | AS46: =AO46 -> 632197109
A47: 현금 | B47: 순현금소진(Net burn = -(영업CF+투자CF)) | C47: 원 | F47: =-('현금흐름표(CF)'!F5+'현금흐름표(CF)'!F22) -> 4593049 | G47: =-('현금흐름표(CF)'!G5+'현금흐름표(CF)'!G22) -> 1994480 | H47: =-('현금흐름표(CF)'!H5+'현금흐름표(CF)'!H22) -> 1504280 | I47: =-('현금흐름표(CF)'!I5+'현금흐름표(CF)'!I22) -> 151108 | J47: =-('현금흐름표(CF)'!J5+'현금흐름표(CF)'!J22) -> 1118471 | K47: =-('현금흐름표(CF)'!K5+'현금흐름표(CF)'!K22) -> 151414 | L47: =-('현금흐름표(CF)'!L5+'현금흐름표(CF)'!L22) -> 2634467 | M47: =-('현금흐름표(CF)'!M5+'현금흐름표(CF)'!M22) -> -937811 | ... AO47: =-('현금흐름표(CF)'!AO5+'현금흐름표(CF)'!AO22) -> -31454 | AP47: =SUM(F47:M47) -> 11209458 | AQ47: =SUM(N47:Y47) -> 138796708 | AR47: =SUM(Z47:AK47) -> -81857054 | AS47: =SUM(AL47:AO47) -> -23679557 | AT47: 정부보조금 포함 실제 현금 소진 속도
A48: 현금 | B48: 최근 3개월 평균 Net burn | C48: 원 | F48: =F47 -> 4593049 | G48: =G47 -> 1994480 | H48: =AVERAGE(F47:H47) -> 2697269.7 | I48: =AVERAGE(G47:I47) -> 1216622.7 | J48: =AVERAGE(H47:J47) -> 924619.67 | K48: =AVERAGE(I47:K47) -> 473664.33 | L48: =AVERAGE(J47:L47) -> 1301450.7 | M48: =AVERAGE(K47:M47) -> 616023.33 | N48: =AVERAGE(L47:N47) -> 8746395 | O48: =AVERAGE(M47:O47) -> 13057674 | ... AO48: =AVERAGE(AM47:AO47) -> -10133406 | AP48: =M48 -> 616023.33 | AQ48: =Y48 -> 10285806 | AR48: =AK48 -> -7785207.3 | AS48: =AO48 -> -10133406
A49: 현금 | B49: 런웨이(개월, 기말현금/3개월 평균 burn) | C49: 개월 | F49: =IF(F48<=0,"현금흐름 흑자",F46/F48) -> 1.177203 | G49: =IF(G48<=0,"현금흐름 흑자",G46/G48) -> 1.7109577 | H49: =IF(H48<=0,"현금흐름 흑자",H46/H48) -> 0.70745281 | I49: =IF(I48<=0,"현금흐름 흑자",I46/I48) -> 1.44423 | J49: =IF(J48<=0,"현금흐름 흑자",J46/J48) -> 0.69067534 | K49: =IF(K48<=0,"현금흐름 흑자",K46/K48) -> 1.0285723 | L49: =IF(L48<=0,"현금흐름 흑자",L46/L48) -> 152.02476 | M49: =IF(M48<=0,"현금흐름 흑자",M46/M48) -> 322.6997 | ... AO49: =IF(AO48<=0,"현금흐름 흑자",AO46/AO48) -> 현금흐름 흑자 | AP49: =M49 -> 322.6997 | AQ49: =Y49 -> 54.443361 | AR49: =AK49 -> 현금흐름 흑자 | AS49: =AO49 -> 현금흐름 흑자
A50: 현금 | B50: 정부보조금 의존도(보조금/(매출+보조금)) | C50: % | F50: =IF(('손익계산서(P&L)'!F5+'손익계산서(P&L)'!F29)=0,0,'손익계산서(P&L)'!F29/('손익계산서(P&L)'!F5+'손익계산서(P&L)'!F29)) -> 0 | G50: =IF(('손익계산서(P&L)'!G5+'손익계산서(P&L)'!G29)=0,0,'손익계산서(P&L)'!G29/('손익계산서(P&L)'!G5+'손익계산서(P&L)'!G29)) -> 0.66415558 | H50: =IF(('손익계산서(P&L)'!H5+'손익계산서(P&L)'!H29)=0,0,'손익계산서(P&L)'!H29/('손익계산서(P&L)'!H5+'손익계산서(P&L)'!H29)) -> 0.61638423 | I50: =IF(('손익계산서(P&L)'!I5+'손익계산서(P&L)'!I29)=0,0,'손익계산서(P&L)'!I29/('손익계산서(P&L)'!I5+'손익계산서(P&L)'!I29)) -> 0.53327636 | J50: =IF(('손익계산서(P&L)'!J5+'손익계산서(P&L)'!J29)=0,0,'손익계산서(P&L)'!J29/('손익계산서(P&L)'!J5+'손익계산서(P&L)'!J29)) -> 0.38110006 | K50: =IF(('손익계산서(P&L)'!K5+'손익계산서(P&L)'!K29)=0,0,'손익계산서(P&L)'!K29/('손익계산서(P&L)'!K5+'손익계산서(P&L)'!K29)) -> 0.26392385 | L50: =IF(('손익계산서(P&L)'!L5+'손익계산서(P&L)'!L29)=0,0,'손익계산서(P&L)'!L29/('손익계산서(P&L)'!L5+'손익계산서(P&L)'!L29)) -> 0.18267448 | M50: =IF(('손익계산서(P&L)'!M5+'손익계산서(P&L)'!M29)=0,0,'손익계산서(P&L)'!M29/('손익계산서(P&L)'!M5+'손익계산서(P&L)'!M29)) -> 0.24234485 | ... AS50: =IF(('손익계산서(P&L)'!AS5+'손익계산서(P&L)'!AS29)=0,0,'손익계산서(P&L)'!AS29/('손익계산서(P&L)'!AS5+'손익계산서(P&L)'!AS29)) -> 0.15821537 | AT50: 보조금 종료 시점의 손익·현금 절벽 점검
A51: 현금 | B51: 보조금 제외 영업CF | C51: 원 | F51: ='현금흐름표(CF)'!F5-'손익계산서(P&L)'!F29 -> -4593049 | G51: ='현금흐름표(CF)'!G5-'손익계산서(P&L)'!G29 -> -7136160 | H51: ='현금흐름표(CF)'!H5-'손익계산서(P&L)'!H29 -> -6645960 | I51: ='현금흐름표(CF)'!I5-'손익계산서(P&L)'!I29 -> -4264452 | J51: ='현금흐름표(CF)'!J5-'손익계산서(P&L)'!J29 -> -4203479 | K51: ='현금흐름표(CF)'!K5-'손익계산서(P&L)'!K29 -> -2208086 | L51: ='현금흐름표(CF)'!L5-'손익계산서(P&L)'!L29 -> -4691139 | M51: ='현금흐름표(CF)'!M5-'손익계산서(P&L)'!M29 -> -1118860 | ... AO51: ='현금흐름표(CF)'!AO5-'손익계산서(P&L)'!AO29 -> -15968546 | AP51: =SUM(F51:M51) -> -34861185 | AQ51: =SUM(N51:Y51) -> -166196708 | AR51: =SUM(Z51:AK51) -> -101542946 | AS51: =SUM(AL51:AO51) -> -40320443

Sheet 가정(Assumptions)
A1: 핵심 가정 · 시나리오 레버 (연습용 가상 값)
A2: ※ Base 열이 이 파일 데이터에 반영된 값입니다. Best/Worst는 2회차 세션4(시나리오 설계) 연습용 출발점이며 파일 숫자에는 반영되어 있지 않습니다.
A4: 구분 | B4: 가정 항목 | C4: Base(반영값) | D4: Best | E4: Worst | F4: 단위 | G4: 근거·설명
A5: 매출[a] | B5: 가격(VAT 별도) Pro 월/연 | C5: 18,000 / 180,000 | D5: 동일 | E5: 동일 | F5: 원 | G5: 연간=월 10개월분(약 17% 할인)
A6: 매출[a] | B6: 가격(VAT 별도) Max 월/연 | C6: 36,000 / 360,000 | D6: 동일 | E6: 동일 | F6: 원
A7: 매출[a] | B7: 신규 유료 구독 증가율(월) | C7: 2025-09~2026-12 9%, 2027 3%, 2028 2% | D7: +2%p | E7: -3%p | F7: % | G7: 출시 초기 고성장 후 둔화
A8: 매출[a] | B8: Max/Pro 신규 비율, 연간 선택 비율 | C8: 30% / Pro 12%·Max 6% | D8: 35% / 15%·8% | E8: 25% / 8%·4% | F8: %
A9: 매출[a] | B9: 월간 플랜 해지율 Pro/Max | C9: 14%·11%(2026) → 12%·10%(2027~) | D9: -2%p | E9: +4%p | F9: %/월 | G9: 취업 성공 시 해지 → B2C 구독 중 해지율 높은 편
A10: 매출[a] | B10: 연간구독 갱신율 / 법인 재계약률 | C10: 45% / 80% | D10: 55% / 90% | E10: 30% / 60% | F10: %
A11: 매출[a] | B11: 계절성 지수(신규 가입) | C11: 3월 1.4, 9월 1.5, 12월 0.7 등 | D11: - | E11: - | F11: 배수 | G11: 상·하반기 공채 시즌
A12: 매출[a] | B12: 크레딧 결제액 | C12: 개인 월구독 매출의 약 22%(계절성 반영) | D12: 30% | E12: 15% | F12: % | G12: 구매월 70%·익월 30% 사용 가정
A13: 매출[a] | B13: 법인 연간계약 | C13: 2026-03 100석 / 2026-09 80석 / 2027-03 200석+Max 40석 / 2027-09 150석 | D13: +50% | E13: -50%·지연 6개월 | F13: 석 | G13: 대학 취업지원센터·기관
A14: 매출[b] | B14: GMV 출시·증가율 | C14: 전자책 2026-03 300만원, 강의 2026-05 200만원, 2026 월 12~15% | D14: +5%p | E14: -7%p | F14: %
A15: 매출[b] | B15: 수수료율(Take rate) | C15: 전자책 20%, 강의 25% | D15: 동일 | E15: -5%p(경쟁) | F15: %
A16: 매출[c] | B16: 컨퍼런스 | C16: 연 2회(4·10월), 개인 250→650명 | D16: +20% | E16: -30% | F16: 명 | G16: 상·하반기 공채 시즌 직전
A17: 원가 | B17: LLM 토큰비/유료 구독자 | C17: Pro 2,800원, Max 7,000원, 무료 MAU 150원, 6개월마다 -7% | D17: -15% | E17: +30%(모델 업그레이드) | F17: 원/월 | G17: 모델 단가 하락 추세 반영
A18: 원가 | B18: PG 수수료율 | C18: 카드 3.3%, 마켓 3.0% | D18: 2.8% | E18: 3.5% | F18: %
A19: 판관비 | B19: 인원 계획 | C19: 2026-07 6명 → 2027-09 9명 | D19: 동일 | E19: 동일 | F19: 명
A20: 판관비 | B20: CAC(광고비[a]/신규 유료) | C20: 2026 20,000원 → 2027 24,000원 → 2028 26,000원 | D20: -20% | E20: +40% | F20: 원
A21: 판관비 | B21: 임차료 | C21: 2026 창업센터 33만원 → 2027 사무실 330만원(보증금 3천만원) | D21: - | E21: - | F21: 원/월
A22: 영업외 | B22: 정부보조금 | C22: 초기창업패키지 월 700만원(2026-05~11), TIPS R&D 월 1,600만원(2026-11~) | D22: 동일 | E22: TIPS 미선정 | F22: 원/월 | G22: 보조금 회계처리(비용 차감 vs 수익) 세무사 확인 필요
A23: 재무 | B23: 자금조달 | C23: 2025-11 정책자금 2억(연 2.5%, 거치 2년) / 2026-04 시드 5억 | D23: 시드 8억 | E23: 시드 3억·6개월 지연 | F23: 원
A24: 운전자본 | B24: 회수·지급 조건 | C24: 법인 30일(연간계약 60일), PG D+3~5, 셀러 정산 익월 10일, 부가세 분기 납부 | D24: - | E24: 법인 회수 90일 | F24: 일

Sheet 검토사항(Review)
A1: 추가 반영 데이터와 반영 이유
A3: # | B3: 추가 항목 | C3: 반영 위치 | D3: 왜 필요한가(두위드 사업 특성) | E3: 실무에서 준비할 데이터
A4: 1 | B4: 부가세 예수금·대급금 | C4: 재무상태표 23·11행 / 현금흐름표 | D4: B2C 카드결제 매출은 결제 시점에 VAT 10%를 함께 받고 분기마다 납부합니다. 매출에 넣으면 안 되는 '맡아둔 돈'이라 현금이 실제보다 많아 보이는 착시가 생깁니다. 전자책(전자출판물)은 면세일 수 있어 과세·면세 구분도 필요합니다. | E4: 홈택스 부가세 신고서, PG 매출전표(과세/면세 구분)
A5: 2 | B5: 선수수익(연간구독·크레딧) | C5: 재무상태표 24행 / KPI 연간구독·크레딧 결제액 | D5: 연간구독은 결제 즉시 12개월치 현금이 들어오지만 매출은 매달 1/12씩 인식합니다. 크레딧은 '사용' 시점에 매출이 됩니다. 결제액(Billings)과 매출을 따로 봐야 성장률·현금흐름을 정확히 해석할 수 있습니다. | E5: 결제 DB의 결제일·플랜·기간, 크레딧 충전·사용·소멸 로그
A6: 3 | B6: 셀러 정산 예수금 | C6: 재무상태표 22행 / KPI GMV·판매자 정산액 | D6: 마켓플레이스는 구매자가 낸 거래액(GMV) 전체가 일단 회사 통장에 들어오지만, 수수료를 뺀 나머지는 판매자에게 돌려줄 부채입니다. 매출원가의 '제3자 판매자 정산대금'을 0원으로 두고 순액(수수료)으로 매출을 잡는 이유이며, 개인셀러 3.3% 원천징수 의무도 함께 관리해야 합니다. | E6: 마켓 주문·정산 내역, 원천세 신고 내역
A7: 4 | B7: PG 미수금 | C7: 재무상태표 9행 | D7: 카드 결제액은 PG사가 수수료를 떼고 D+3~5일 뒤 입금합니다. 월말 현금이 손익보다 적게 보이는 원인입니다. | E7: PG 정산내역(정산일·수수료)
A8: 5 | B8: 법인 매출채권 | C8: 재무상태표 8행 / KPI 법인 좌석 | D8: 대학·기관 계약은 세금계산서 발행 후 30~60일 뒤 입금되어 DSO(매출채권 회수기간) 관리 대상입니다. 2회차 세션1 운전자본 분석의 핵심 데이터입니다. | E8: 세금계산서 발행내역, 입금 내역
A9: 6 | B9: 구독자·해지·ARPPU·MRR/ARR | C9: KPI [a] 섹션 | D9: 구독 매출은 '구독자 수 × 가격'으로 분해해야 성장 원인(신규 vs 해지 vs 가격)을 설명할 수 있습니다. 취업준비 서비스는 취업에 성공하면 해지하는 구조라 해지율과 계절성이 일반 SaaS보다 큽니다. | E9: 결제 DB(월말 활성·신규·해지), 플랜별 가격
A10: 7 | B10: LLM 토큰비용률 · 무료 MAU | C10: KPI / 매출원가 6행 | D10: AI SaaS의 매출총이익률은 LLM 토큰비가 좌우합니다. 무료 이용자도 비용을 만들기 때문에 유료 전환율과 함께 봐야 합니다. 모델 단가 인하·업그레이드 시나리오의 민감도가 큽니다. | E10: OpenAI·Anthropic 사용량 대시보드(월별·기능별), 서비스 로그
A11: 8 | B11: CAC · 사업부문별 광고비 | C11: KPI CAC / 판관비 16~19행 | D11: 광고선전비를 a·b·c로 나눠 두었기 때문에 사업별 고객획득비용과 회수기간(LTV/CAC)을 계산할 수 있습니다. | E11: 광고 플랫폼 캠페인별 비용, 가입·결제 전환 데이터
A12: 9 | B12: 정부보조금 의존도 | C12: 손익계산서 29행 / KPI | D12: 2025년 영업외수익(23,703,137원)이 순손실을 절반으로 줄였습니다. 보조금은 반복되지 않으므로 '보조금 제외 영업CF'로 체력을 따로 봐야 합니다. 일반기업회계기준상 비용 보전 목적 보조금은 관련 비용에서 차감하는 것이 원칙이라 표시 방법을 세무사와 확인해야 합니다. | E12: 협약서, 보조금 집행·정산 내역
A13: 10 | B13: 런웨이 · Net burn | C13: KPI 현금 섹션 | D13: 스타트업 의사결정의 핵심은 '현금이 몇 달 남았나'입니다. 2회차 세션2·4(런웨이, 자금조달 시점) 프롬프트에 바로 쓸 수 있습니다. | E13: 통장 잔액, 월별 입출금 합계
A14: 11 | B14: 2025 계정 재분류 | C14: 매출원가·판관비 2025 열 | D14: 2025 신고서는 매출원가 0원, 지급수수료 50,385,211원입니다. 이 파일은 클라우드·LLM·PG·행사비를 매출원가로 옮겨 매출총이익률을 계산할 수 있게 했습니다(합계는 원 단위까지 동일). 세무 신고 분류와 관리회계 분류를 함께 보는 연습입니다. | E14: 계정별원장(지급수수료) 거래처별 내역
A15: 12 | B15: 2025 미지급법인세 2,148,183원 | C15: 재무상태표 26행 | D15: 당기순손실인데 미지급법인세가 남아 있습니다. 이자소득 원천세·지방소득세 등 다른 성격일 수 있어 세무사 확인이 필요합니다. 이 파일은 2026-03에 납부한 것으로 가정했습니다. | E15: 2025 법인세 신고서, 세목별 납부내역
A16: 13 | B16: 유동성 장기부채 | C16: 재무상태표 28행 | D16: 정책자금 2억은 2027-11부터 상환이 시작되므로, 2026-11부터 1년 내 상환분을 유동부채로 분리하면 유동비율이 낮아집니다. 이 파일은 단순화를 위해 장기차입금 한 줄로 두었습니다. | E16: 대출 약정서(거치·상환 조건)
